Workbook

Sheet DATA
D2: Mean-Variance Optimization
B3: Date | D3: VFF-US | E3: FENC-US | F3: BDOUY-US | G3: SPMYY-US | H3: AHCHY-US | I3: NSC-US | J3: FQVTF-US | K3: CRAI-US | L3: CHEF-US | M3: SCGPY-US | N3: KOS-US | O3: DIISY-US | P3: TSLA-US | Q3: AMZN-US | R3: AAPL-US | S3: AVGO-US | T3: F-US | U3: SMCI-US | V3: CMCSA-US | W3: HAL-US | X3: BIRDF-US | Y3: EPRT-US | Z3: OTSKY-US | AA3: OHI-US | AB3: AGYS-US | AC3: CWBK-US | AD3: SSBI-US | AE3: PLOW-US | AF3: NWN-US | AG3: MNSB-US
B4: 43496 | D4: 5.5747 | E4: 6.69 | F4: 26.51 | G4: 7.925 | H4: 27.018 | I4: 167.74 | J4: 34.3 | K4: 41.74 | L4: 32.12 | M4: 1.452 | N4: 5.13 | O4: 17.716 | P4: 20.46798 | Q4: 85.9365 | R4: 41.61 | S4: 26.825 | T4: 8.8 | U4: 1.5100001 | V4: 36.57 | W4: 31.36 | X4: 4.7501 | Y4: 15.9 | Z4: 20.459 | AA4: 40.19 | AB4: 17.7 | AC4: 19.5 | AD4: 10.705365 | AE4: 35.4 | AF4: 62.6 | AG4: 19.85
B5: 43524 | D5: 10.58 | E5: 6.65 | F5: 25.68 | G5: 8.04 | H5: 28.6 | I5: 179.3 | J5: 36.19 | K5: 49.96 | L5: 32.01 | M5: 1.72 | N5: 6.4 | O5: 18.978 | P5: 21.325312 | Q5: 81.99151 | R5: 43.2875 | S5: 27.536 | T5: 8.77 | U5: 1.9120001 | V5: 38.67 | W5: 30.69 | X5: 5.036 | Y5: 16.97 | Z5: 20.85 | AA5: 35.9 | AB5: 20.9 | AC5: 21.5 | AD5: 11.309092 | AE5: 42.18 | AF5: 64.22 | AG5: 23
B6: 43553 | D6: 14.01 | E6: 4.85 | F6: 26.09 | G6: 7.76 | H6: 30.542 | I6: 186.89 | J6: 39.27 | K6: 50.54 | L6: 31.05 | M6: 1.668 | N6: 6.23 | O6: 18.399 | P6: 18.65731 | Q6: 89.0375 | R6: 47.4875 | S6: 30.071 | T6: 8.78 | U6: 2.11275 | V6: 39.98 | W6: 29.3 | X6: 5.905 | Y6: 19.52 | Z6: 19.646 | AA6: 38.15 | AB6: 21.17 | AC6: 21.65 | AD6: 10.527274 | AE6: 38.07 | AF6: 65.63 | AG6: 21.6
B7: 43585 | D7: 12.5 | E7: 4.45 | F7: 25.4 | G7: 8 | H7: 30.496 | I7: 204.02 | J7: 40.7 | K7: 52.08 | L7: 32.68 | M7: 1.624 | N7: 6.69 | O7: 17.177 | P7: 15.912651 | Q7: 96.326004 | R7: 50.1675 | S7: 31.84 | T7: 10.45 | U7: 2.2420003 | V7: 43.53 | W7: 28.33 | X7: 5.8286 | Y7: 20.68 | Z7: 17.818 | AA7: 35.39 | AB7: 19.13 | AC7: 21.55 | AD7: 10.364548 | AE7: 37.76 | AF7: 66.89 | AG7: 23
B8: 43616 | D8: 12.1 | E8: 3.75 | F8: 26.5 | G8: 8.2 | H8: 29.207 | I8: 195.14 | J8: 33.35 | K8: 37.44 | L8: 31.67 | M8: 1.674 | N8: 6.16 | O8: 15.957 | P8: 12.343988 | Q8: 88.7535 | R8: 43.7675 | S8: 25.164 | T8: 9.52 | U8: 1.9 | V8: 41 | W8: 21.29 | X8: 4.1716 | Y8: 21.26 | Z8: 16.79 | AA8: 35.62 | AB8: 21.8 | AC8: 21.3 | AD8: 10.409093 | AE8: 37.1 | AF8: 68.82 | AG8: 23.66
B9: 43644 | D9: 11.44 | E9: 4 | F9: 27.39 | G9: 7.87 | H9: 31.328 | I9: 199.33 | J9: 29.795 | K9: 38.33 | L9: 35.07 | M9: 1.833 | N9: 6.27 | O9: 16.891 | P9: 14.897321 | Q9: 94.68151 | R9: 49.48 | S9: 28.786 | T9: 10.23 | U9: 1.9350001 | V9: 42.28 | W9: 22.74 | X9: 4.27 | Y9: 20.04 | Z9: 16.317 | AA9: 36.75 | AB9: 21.47 | AC9: 20.825 | AD9: 10.000001 | AE9: 39.79 | AF9: 69.5 | AG9: 22.79
B10: 43677 | D10: 11.37 | E10: 4.68 | F10: 28.35 | G10: 8.11 | H10: 29.222 | I10: 191.12 | J10: 28.87 | K10: 43.42 | L10: 36.47 | M10: 1.805 | N10: 6.01 | O10: 15.791 | P10: 16.107317 | Q10: 93.339005 | R10: 53.26 | S10: 28.998999 | T10: 9.53 | U10: 1.831 | V10: 43.17 | W10: 23 | X10: 4.19114 | Y10: 21.12 | Z10: 18.499 | AA10: 36.3 | AB10: 24.53 | AC10: 21.75 | AD10: 11.136366 | AE10: 41.1 | AF10: 71.42 | AG10: 22.82
B11: 43707 | D11: 10.5 | E11: 4.3 | F11: 28.4 | G11: 8.82 | H11: 28.174 | I11: 174.05 | J11: 27.93 | K11: 38.89 | L11: 38.58 | M11: 1.777 | N11: 6.32 | O11: 13.791 | P11: 15.040653 | Q11: 88.81451 | R11: 52.185 | S11: 28.264002 | T11: 9.17 | U11: 1.89 | V11: 44.26 | W11: 18.84 | X11: 3.9 | Y11: 22.71 | Z11: 20.58 | AA11: 40.68 | AB11: 27.25 | AC11: 21.36 | AD11: 11.013639 | AE11: 41.76 | AF11: 71.36 | AG11: 21.31
B12: 43738 | D12: 9.05 | E12: 4.81 | F12: 27.25 | G12: 9.98 | H12: 29.69 | I12: 179.66 | J12: 30 | K12: 41.97 | L12: 40.32 | M12: 1.839 | N12: 6.24 | O12: 14.798 | P12: 16.057983 | Q12: 86.7955 | R12: 55.9925 | S12: 27.607 | T12: 9.16 | U12: 1.9200001 | V12: 45.08 | W12: 18.85 | X12: 4.35 | Y12: 22.91 | Z12: 18.691 | AA12: 41.79 | AB12: 25.61 | AC12: 22.525 | AD12: 10.718184 | AE12: 44.57 | AF12: 71.34 | AG12: 21.05
B13: 43769 | D13: 7.91 | E13: 5.34 | F13: 29.44 | G13: 10.15 | H13: 29.951 | I13: 182 | J13: 23.86 | K13: 49.25 | L13: 33.125 | M13: 2.019 | N13: 6.2 | O13: 14.084 | P13: 20.994648 | Q13: 88.833 | R13: 62.19 | S13: 29.285002 | T13: 8.59 | U13: 2.068 | V13: 44.82 | W13: 19.25 | X13: 4.606 | Y13: 25.66 | Z13: 20.989 | AA13: 44.04 | AB13: 25.19 | AC13: 23.675 | AD13: 11.068183 | AE13: 46.83 | AF13: 69.36 | AG13: 20.74
B14: 43798 | D14: 6.62 | E14: 6.261 | F14: 31.38 | G14: 11.05 | H14: 31.97 | I14: 193.5 | J14: 28.46 | K14: 51.27 | L14: 35.56 | M14: 2.013 | N14: 5.97 | O14: 15.801 | P14: 21.995977 | Q14: 90.04 | R14: 66.8125 | S14: 31.621 | T14: 9.06 | U14: 2.1299999 | V14: 44.15 | W14: 20.99 | X14: 4.9998 | Y14: 26.09 | Z14: 21.797 | AA14: 42.03 | AB14: 25.33 | AC14: 24.25 | AD14: 11.359092 | AE14: 54.11 | AF14: 68.77 | AG14: 21.93
B15: 43830 | D15: 6.23 | E15: 6.49 | F15: 32.08 | G15: 13 | H15: 36.449 | I15: 194.13 | J15: 27.85 | K15: 54.47 | L15: 38.11 | M15: 2.145 | N15: 5.7 | O15: 16.559 | P15: 27.88864 | Q15: 92.392 | R15: 73.4125 | S15: 31.602 | T15: 9.3 | U15: 2.4020002 | V15: 44.97 | W15: 24.47 | X15: 5.4494 | Y15: 24.81 | Z15: 22.466 | AA15: 42.35 | AB15: 25.41 | AC15: 24 | AD15: 11.786366 | AE15: 55 | AF15: 73.73 | AG15: 23
... B75: 45657 | D75: 0.771 | E75: 6.32 | F75: 24.894 | G75: 9.36 | H75: 12.796 | I75: 234.7 | J75: 8.49 | K75: 187.2 | L75: 49.32 | M75: 1.895 | N75: 3.42 | O75: 12.785 | P75: 403.84 | Q75: 219.39 | R75: 250.42 | S75: 231.84 | T75: 9.9 | U75: 30.48 | V75: 37.53 | W75: 27.19 | X75: 18.075 | Y75: 31.28 | Z75: 27.361 | AA75: 37.85 | AB75: 131.71 | AC75: 35.65 | AD75: 7.65 | AE75: 23.63 | AF75: 39.56 | AG75: 18.1
D80: Winner stocks | O80: Looser stocks | Z80: Small growth stocks | AK80: Small value stocks | AV80: Large growth stocks | BG80: Large value stocks
B81: Date | D81: VFF-US | E81: BIRDF-US | F81: BDOUY-US | G81: RPGRF-US | H81: DAY-US | I81: GLAD-US | J81: NVZMF-US | K81: AICAF-US | L81: PAYS-US | M81: FENC-US | O81: SPMYY-US | P81: AHCHY-US | Q81: NSC-US | R81: NWN-US | S81: WDFN-US | T81: DHLGY-US | U81: TEL-US | V81: YRAIF-US | W81: SSBI-US | X81: SSAAY-US | Z81: FQVTF-US | AA81: CRAI-US | AB81: CHEF-US | AC81: KALU-US | AD81: MLKN-US | AE81: DCO-US | AF81: NUV-US | AG81: NXRT-US | AH81: AAT-US | AI81: LMB-US | AK81: SCGPY-US | AL81: KOS-US | AM81: DIISY-US | AN81: SVM-US | AO81: MAG-US | AP81: GTX-US | AQ81: ORC-US | AR81: CIM-US | AS81: CHRRF-US | AT81: TORXF-US | AV81: TSLA-US | AW81: AMZN-US | AX81: AAPL-US | AY81: AVGO-US | AZ81: CSCO-US | BA81: MSFT-US | BB81: UNH-US | BC81: META-US | BD81: NVO-US | BE81: BSX-US | BG81: F-US | BH81: SMCI-US | BI81: CMCSA-US | BJ81: HAL-US | BK81: CNH-US | BL81: RNECY-US | BM81: PR-US | BN81: STLA-US | BO81: IPG-US | BP81: ABEV-US
B82: 43496 | D82: 5.5747 | E82: 4.7501 | F82: 26.51 | G82: 55.3 | H82: 41.21 | I82: 17.34 | J82: 42.42 | K82: 0.9975 | L82: 4.58 | M82: 6.69 | O82: 7.925 | P82: 27.018 | Q82: 167.74 | R82: 62.6 | S82: 29 | T82: 29.585 | U82: 80.95 | V82: 41.45 | W82: 10.705365 | X82: 1.977 | Z82: 34.3 | AA82: 41.74 | AB82: 32.12 | AC82: 100.37 | AD82: 34.23 | AE82: 39.37 | AF82: 9.67 | AG82: 37.41 | AH82: 42.94 | AI82: 5.65 | AK82: 1.452 | AL82: 5.13 | AM82: 17.716 | AN82: 2.33 | AO82: 9.01 | AP82: 15.97 | AQ82: 34.7 | AR82: 57.089943 | AS82: 37.658607 | AT82: 10.855 | AV82: 20.46798 | AW82: 85.9365 | AX82: 41.61 | AY82: 26.825 | AZ82: 47.29 | BA82: 104.43 | BB82: 270.2 | BC82: 166.69 | BD82: 23.51 | BE82: 38.15 | BG82: 8.8 | BH82: 1.5100001 | BI82: 36.57 | BJ82: 31.36 | BK82: 8.613 | BL82: 2.872 | BM82: 13.17 | BN82: 16.225363 | BO82: 22.75 | BP82: 4.81
B83: 43524 | D83: 10.58 | E83: 5.036 | F83: 25.68 | G83: 58 | H83: 49.02 | I83: 18.14 | J83: 45.515 | K83: 1.08 | L83: 7.36 | M83: 6.65 | O83: 8.04 | P83: 28.6 | Q83: 179.3 | R83: 64.22 | S83: 29.75 | T83: 31.03 | U83: 82.09 | V83: 42.15 | W83: 11.309092 | X83: 1.961 | Z83: 36.19 | AA83: 49.96 | AB83: 32.01 | AC83: 109.48 | AD83: 36.68 | AE83: 42.43 | AF83: 9.69 | AG83: 35.94 | AH83: 43.44 | AI83: 5.78 | AK83: 1.72 | AL83: 6.4 | AM83: 18.978 | AN83: 2.58 | AO83: 9.79 | AP83: 16.74 | AQ83: 33.399998 | AR83: 55.46994 | AS83: 40.880013 | AT83: 12.13 | AV83: 21.325312 | AW83: 81.99151 | AX83: 43.2875 | AY83: 27.536 | AZ83: 51.77 | BA83: 112.03 | BB83: 242.22 | BC83: 161.45 | BD83: 24.475 | BE83: 40.12 | BG83: 8.77 | BH83: 1.9120001 | BI83: 38.67 | BJ83: 30.69 | BK83: 9.456048 | BL83: 2.929 | BM83: 9.07 | BN83: 13.887251 | BO83: 23.03 | BP83: 4.53
B84: 43553 | D84: 14.01 | E84: 5.905 | F84: 26.09 | G84: 53.14 | H84: 51.3 | I84: 18.02 | J84: 46.17 | K84: 1.23 | L84: 7.95 | M84: 4.85 | O84: 7.76 | P84: 30.542 | Q84: 186.89 | R84: 65.63 | S84: 29.925 | T84: 32.555 | U84: 80.75 | V84: 41 | W84: 10.527274 | X84: 1.802 | Z84: 39.27 | AA84: 50.54 | AB84: 31.05 | AC84: 104.73 | AD84: 35.18 | AE84: 43.52 | AF84: 10 | AG84: 38.34 | AH84: 45.86 | AI84: 7.575 | AK84: 1.668 | AL84: 6.23 | AM84: 18.399 | AN84: 2.55 | AO84: 10.66 | AP84: 14.73 | AQ84: 32.9 | AR84: 56.21994 | AS84: 37.407997 | AT84: 12.6411 | AV84: 18.65731 | AW84: 89.0375 | AX84: 47.4875 | AY84: 30.071 | AZ84: 53.99 | BA84: 117.94 | BB84: 247.26 | BC84: 166.69 | BD84: 26.155 | BE84: 38.38 | BG84: 8.78 | BH84: 2.11275 | BI84: 39.98 | BJ84: 29.3 | BK84: 8.865046 | BL84: 2.313 | BM84: 8.79 | BN84: 14.000386 | BO84: 21.01 | BP84: 4.3
B85: 43585 | D85: 12.5 | E85: 5.8286 | F85: 25.4 | G85: 56.41 | H85: 53.15 | I85: 19 | J85: 46.14 | K85: 1.19 | L85: 8.13 | M85: 4.45 | O85: 8 | P85: 30.496 | Q85: 204.02 | R85: 66.89 | S85: 30.65 | T85: 34.79 | U85: 95.65 | V85: 45 | W85: 10.364548 | X85: 1.884 | Z85: 40.7 | AA85: 52.08 | AB85: 32.68 | AC85: 98.4 | AD85: 38.82 | AE85: 40.58 | AF85: 9.97 | AG85: 37.49 | AH85: 46.19 | AI85: 9.1 | AK85: 1.624 | AL85: 6.69 | AM85: 17.177 | AN85: 2.24 | AO85: 9.83 | AP85: 18.8 | AQ85: 32.850002 | AR85: 57.50994 | AS85: 38.57 | AT85: 9.54 | AV85: 15.912651 | AW85: 96.326004 | AX85: 50.1675 | AY85: 31.84 | AZ85: 55.95 | BA85: 130.6 | BB85: 233.07 | BC85: 193.4 | BD85: 24.505 | BE85: 37.12 | BG85: 10.45 | BH85: 2.2420003 | BI85: 43.53 | BJ85: 28.33 | BK85: 9.473431 | BL85: 2.662 | BM85: 10.53 | BN85: 14.528346 | BO85: 23 | BP85: 4.71
B86: 43616 | D86: 12.1 | E86: 4.1716 | F86: 26.5 | G86: 61.84 | H86: 49.18 | I86: 18 | J86: 46.36 | K86: 0.92665 | L86: 9.76 | M86: 3.75 | O86: 8.2 | P86: 29.207 | Q86: 195.14 | R86: 68.82 | S86: 30 | T86: 29.38 | U86: 84.23 | V86: 42.8 | W86: 10.409093 | X86: 1.534 | Z86: 33.35 | AA86: 37.44 | AB86: 31.67 | AC86: 89.12 | AD86: 35.49 | AE86: 45.13 | AF86: 10.07 | AG86: 40.08 | AH86: 45.39 | AI86: 9.05 | AK86: 1.674 | AL86: 6.16 | AM86: 15.957 | AN86: 2.18 | AO86: 9.77 | AP86: 15.38 | AQ86: 30.4 | AR86: 54.71994 | AS86: 38.60501 | AT86: 9.18 | AV86: 12.343988 | AW86: 88.7535 | AX86: 43.7675 | AY86: 25.164 | AZ86: 52.03 | BA86: 123.68 | BB86: 241.8 | BC86: 177.47 | BD86: 23.6 | BE86: 38.41 | BG86: 9.52 | BH86: 1.9 | BI86: 41 | BJ86: 21.29 | BK86: 7.5352883 | BL86: 2.28 | BM86: 7.9 | BN86: 11.897971 | BO86: 21.22 | BP86: 4.47
B87: 43644 | D87: 11.44 | E87: 4.27 | F87: 27.39 | G87: 67.54 | H87: 50.2 | I87: 18.76 | J87: 46.43 | K87: 1.01 | L87: 13.37 | M87: 4 | O87: 7.87 | P87: 31.328 | Q87: 199.33 | R87: 69.5 | S87: 29.55 | T87: 32.79 | U87: 95.78 | V87: 48.6 | W87: 10.000001 | X87: 1.744 | Z87: 29.795 | AA87: 38.33 | AB87: 35.07 | AC87: 97.61 | AD87: 44.7 | AE87: 45.07 | AF87: 10.18 | AG87: 41.4 | AH87: 47.12 | AI87: 9.1 | AK87: 1.833 | AL87: 6.27 | AM87: 16.891 | AN87: 2.46 | AO87: 10.54 | AP87: 15.35 | AQ87: 31.800001 | AR87: 56.60994 | AS87: 40.887703 | AT87: 10.3 | AV87: 14.897321 | AW87: 94.68151 | AX87: 49.48 | AY87: 28.786 | AZ87: 54.73 | BA87: 133.96 | BB87: 244.01 | BC87: 193 | BD87: 25.52 | BE87: 42.98 | BG87: 10.23 | BH87: 1.9350001 | BI87: 42.28 | BJ87: 22.74 | BK87: 8.934575 | BL87: 2.483 | BM87: 7.59 | BN87: 13.029315 | BO87: 22.59 | BP87: 4.67
B88: 43677 | D88: 11.37 | E88: 4.19114 | F88: 28.35 | G88: 67.045 | H88: 53.31 | I88: 18.96 | J88: 45.65 | K88: 0.98 | L88: 14.11 | M88: 4.68 | O88: 8.11 | P88: 29.222 | Q88: 191.12 | R88: 71.42 | S88: 30 | T88: 32.48 | U88: 92.4 | V88: 47.15 | W88: 11.136366 | X88: 1.433 | Z88: 28.87 | AA88: 43.42 | AB88: 36.47 | AC88: 96.27 | AD88: 45.34 | AE88: 42.15 | AF88: 10.32 | AG88: 43.16 | AH88: 46.4 | AI88: 8.88 | AK88: 1.805 | AL88: 6.01 | AM88: 15.791 | AN88: 3.07 | AO88: 11.12 | AP88: 14.17 | AQ88: 30.95 | AR88: 57.839943 | AS88: 41.839138 | AT88: 12.9 | AV88: 16.107317 | AW88: 93.339005 | AX88: 53.26 | AY88: 28.998999 | AZ88: 55.4 | BA88: 136.27 | BB88: 249.01 | BC88: 194.23 | BD88: 23.96 | BE88: 42.46 | BG88: 9.53 | BH88: 1.831 | BI88: 43.17 | BJ88: 23 | BK88: 8.786824 | BL88: 2.989 | BM88: 5.95 | BN88: 12.435359 | BO88: 22.92 | BP88: 5.27
B89: 43707 | D89: 10.5 | E89: 3.9 | F89: 28.4 | G89: 70.385 | H89: 57.77 | I89: 18.64 | J89: 42.2 | K89: 0.8673 | L89: 13.29 | M89: 4.3 | O89: 8.82 | P89: 28.174 | Q89: 174.05 | R89: 71.36 | S89: 31.75 | T89: 32.82 | U89: 91.22 | V89: 43.42 | W89: 11.013639 | X89: 1.386 | Z89: 27.93 | AA89: 38.89 | AB89: 38.58 | AC89: 88.43 | AD89: 42.28 | AE89: 41.18 | AF89: 10.53 | AG89: 46.4 | AH89: 46.86 | AI89: 4.84 | AK89: 1.777 | AL89: 6.32 | AM89: 13.791 | AN89: 4.29 | AO89: 12.75 | AP89: 9.84 | AQ89: 27.15 | AR89: 57.20994 | AS89: 38.77497 | AT89: 16.064 | AV89: 15.040653 | AW89: 88.81451 | AX89: 52.185 | AY89: 28.264002 | AZ89: 46.81 | BA89: 137.86 | BB89: 234 | BC89: 185.67 | BD89: 26.055 | BE89: 42.73 | BG89: 9.17 | BH89: 1.89 | BI89: 44.26 | BJ89: 18.84 | BK89: 8.917192 | BL89: 3.128 | BM89: 4.82 | BN89: 12.388221 | BO89: 19.88 | BP89: 4.54
B90: 43738 | D90: 9.05 | E90: 4.35 | F90: 27.25 | G90: 73.04 | H90: 49.37 | I90: 19.5 | J90: 42.08 | K90: 0.8775 | L90: 10.1 | M90: 4.81 | O90: 9.98 | P90: 29.69 | Q90: 179.66 | R90: 71.34 | S90: 31.275 | T90: 33.26 | U90: 93.18 | V90: 43.135 | W90: 10.718184 | X90: 1.393 | Z90: 30 | AA90: 41.97 | AB90: 40.32 | AC90: 98.97 | AD90: 46.09 | AE90: 42.4 | AF90: 10.51 | AG90: 46.76 | AH90: 46.74 | AI90: 4.93 | AK90: 1.839 | AL90: 6.24 | AM90: 14.798 | AN90: 3.89 | AO90: 10.61 | AP90: 9.96 | AQ90: 28.75 | AR90: 58.67994 | AS90: 40.250015 | AT90: 12.4007 | AV90: 16.057983 | AW90: 86.7955 | AX90: 55.9925 | AY90: 27.607 | AZ90: 49.41 | BA90: 139.03 | BB90: 217.32 | BC90: 178.08 | BD90: 25.85 | BE90: 40.69 | BG90: 9.16 | BH90: 1.9200001 | BI90: 45.08 | BJ90: 18.85 | BK90: 8.8215885 | BL90: 3.248 | BM90: 4.515 | BN90: 12.20909 | BO90: 21.56 | BP90: 4.62
B91: 43769 | D91: 7.91 | E91: 4.606 | F91: 29.44 | G91: 74.5 | H91: 48.25 | I91: 19.74 | J91: 47.0606 | K91: 0.8848 | L91: 10.78 | M91: 5.34 | O91: 10.15 | P91: 29.951 | Q91: 182 | R91: 69.36 | S91: 31.5 | T91: 35.45 | U91: 89.5 | V91: 38.95 | W91: 11.068183 | X91: 1.399 | Z91: 23.86 | AA91: 49.25 | AB91: 33.125 | AC91: 107.08 | AD91: 46.5 | AE91: 49.58 | AF91: 10.43 | AG91: 48.77 | AH91: 48.96 | AI91: 4.5 | AK91: 2.019 | AL91: 6.2 | AM91: 14.084 | AN91: 4.17 | AO91: 9.86 | AP91: 9.5 | AQ91: 27.85 | AR91: 60.779938 | AS91: 41.109528 | AT91: 14.6455 | AV91: 20.994648 | AW91: 88.833 | AX91: 62.19 | AY91: 29.285002 | AZ91: 47.51 | BA91: 143.37 | BB91: 252.7 | BC91: 191.65 | BD91: 27.61 | BE91: 41.7 | BG91: 8.59 | BH91: 2.068 | BI91: 44.82 | BJ91: 19.25 | BK91: 9.482121 | BL91: 3.423 | BM91: 3.4 | BN91: 14.443496 | BO91: 21.75 | BP91: 4.31
B92: 43798 | D92: 6.62 | E92: 4.9998 | F92: 31.38 | G92: 70.92 | H92: 60.36 | I92: 20.82 | J92: 47.49 | K92: 0.92 | L92: 10.26 | M92: 6.261 | O92: 11.05 | P92: 31.97 | Q92: 193.5 | R92: 68.77 | S92: 32.125 | T92: 37.2385 | U92: 92.71 | V92: 37.6 | W92: 11.359092 | X92: 1.557 | Z92: 28.46 | AA92: 51.27 | AB92: 35.56 | AC92: 109.58 | AD92: 47.78 | AE92: 48.88 | AF92: 10.51 | AG92: 47.85 | AH92: 47.53 | AI92: 3 | AK92: 2.013 | AL92: 5.97 | AM92: 15.801 | AN92: 5.12 | AO92: 10.69 | AP92: 11.57 | AQ92: 28.4 | AR92: 61.10994 | AS92: 42.850502 | AT92: 14.975 | AV92: 21.995977 | AW92: 90.04 | AX92: 66.8125 | AY92: 31.621 | AZ92: 45.31 | BA92: 151.38 | BB92: 279.87 | BC92: 201.64 | BD92: 28.075 | BE92: 43.25 | BG92: 9.06 | BH92: 2.1299999 | BI92: 44.15 | BJ92: 20.99 | BK92: 9.343062 | BL92: 3.255 | BM92: 3.09 | BN92: 13.906107 | BO92: 22.4 | BP92: 4.21
B93: 43830 | D93: 6.23 | E93: 5.4494 | F93: 32.08 | G93: 72.515 | H93: 67.88 | I93: 19.86 | J93: 49.18 | K93: 1 | L93: 10.15 | M93: 6.49 | O93: 13 | P93: 36.449 | Q93: 194.13 | R93: 73.73 | S93: 32.75 | T93: 37.82 | U93: 95.84 | V93: 41.575 | W93: 11.786366 | X93: 1.755 | Z93: 27.85 | AA93: 54.47 | AB93: 38.11 | AC93: 110.89 | AD93: 41.65 | AE93: 50.53 | AF93: 10.7 | AG93: 45 | AH93: 45.9 | AI93: 3.78 | AK93: 2.145 | AL93: 5.7 | AM93: 16.559 | AN93: 5.67 | AO93: 11.84 | AP93: 9.99 | AQ93: 29.25 | AR93: 61.679935 | AS93: 43.144363 | AT93: 15.8 | AV93: 27.88864 | AW93: 92.392 | AX93: 73.4125 | AY93: 31.602 | AZ93: 47.96 | BA93: 157.7 | BB93: 293.98 | BC93: 205.25 | BD93: 28.94 | BE93: 45.22 | BG93: 9.3 | BH93: 2.4020002 | BI93: 44.97 | BJ93: 24.47 | BK93: 9.560343 | BL93: 3.451 | BM93: 4.62 | BN93: 13.84954 | BO93: 23.1 | BP93: 4.66
... B153: 45657 | D153: 0.771 | E153: 18.075 | F153: 24.894 | G153: 145.43 | H153: 72.64 | I153: 28.44 | J153: 54.86 | K153: 0.655 | L153: 3.02 | M153: 6.32 | O153: 9.36 | P153: 12.796 | Q153: 234.7 | R153: 39.56 | S153: 20.175 | T153: 34.9 | U153: 142.97 | V153: 26.635 | W153: 7.65 | X153: 2.035 | Z153: 8.49 | AA153: 187.2 | AB153: 49.32 | AC153: 70.27 | AD153: 22.59 | AE153: 63.66 | AF153: 8.59 | AG153: 41.75 | AH153: 26.26 | AI153: 85.54 | AK153: 1.895 | AL153: 3.42 | AM153: 12.785 | AN153: 3 | AO153: 13.6 | AP153: 9.03 | AQ153: 7.78 | AR153: 14 | AS153: 15.120004 | AT153: 19.574 | AV153: 403.84 | AW153: 219.39 | AX153: 250.42 | AY153: 231.84 | AZ153: 59.2 | BA153: 421.5 | BB153: 505.86 | BC153: 585.51 | BD153: 86.02 | BE153: 89.32 | BG153: 9.9 | BH153: 30.48 | BI153: 37.53 | BJ153: 27.19 | BK153: 11.33 | BL153: 6.511 | BM153: 14.38 | BN153: 13.05 | BO153: 28.02 | BP153: 1.85
D158: Long position | T158: Short position
B159: Date | D159: BIRDF-US | E159: EPRT-US | F159: OTSKY-US | G159: OHI-US | H159: AGYS-US | I159: SAPMY-US | J159: UTHR-US | K159: APO-US | L159: PAYS-US | M159: POWL-US | N159: JEF-US | O159: LAZ-US | P159: PCYO-US | Q159: FNF-US | R159: ITRI-US | T159: AHCHY-US | U159: SSBI-US | V159: NSC-US | W159: NWN-US | X159: MNSB-US | Y159: CWBK-US | Z159: PLOW-US | AA159: WPC-US | AB159: FBTT-US | AC159: ESCA-US | AD159: SPOK-US | AE159: UNLYF-US | AF159: DHLGY-US | AG159: TEL-US | AH159: YRAIF-US
B160: 43496 | D160: 4.7501 | E160: 15.9 | F160: 20.459 | G160: 40.19 | H160: 17.7 | I160: 45.361908 | J160: 115.33 | K160: 29.28 | L160: 4.58 | M160: 27.91 | N160: 18.610497 | O160: 39.79 | P160: 10.17 | Q160: 34.759365 | R160: 54.63 | T160: 27.018 | U160: 10.705365 | V160: 167.74 | W160: 62.6 | X160: 19.85 | Y160: 19.5 | Z160: 35.4 | AA160: 73.31628 | AB160: 33 | AC160: 11.16 | AD160: 13.84 | AE160: 52.455 | AF160: 29.585 | AG160: 80.95 | AH160: 41.45
B161: 43524 | D161: 5.036 | E161: 16.97 | F161: 20.85 | G161: 35.9 | H161: 20.9 | I161: 49.504765 | J161: 126.29 | K161: 29.3 | L161: 7.36 | M161: 32.09 | N161: 18.127571 | O161: 37.43 | P161: 10.14 | Q161: 33.730812 | R161: 53.01 | T161: 28.6 | U161: 11.309092 | V161: 179.3 | W161: 64.22 | X161: 23 | Y161: 21.5 | Z161: 42.18 | AA161: 72.31771 | AB161: 36 | AC161: 12.2 | AD161: 13.81 | AE161: 53.2 | AF161: 31.03 | AG161: 82.09 | AH161: 42.15
B162: 43553 | D162: 5.905 | E162: 19.52 | F162: 19.646 | G162: 38.15 | H162: 21.17 | I162: 50.423817 | J162: 117.37 | K162: 28.25 | L162: 7.95 | M162: 26.55 | N162: 16.804 | O162: 36.14 | P162: 9.86 | Q162: 35.13426 | R162: 46.65 | T162: 30.542 | U162: 10.527274 | V162: 186.89 | W162: 65.63 | X162: 21.6 | Y162: 21.65 | Z162: 38.07 | AA162: 76.68399 | AB162: 34.625 | AC162: 11.17 | AD162: 13.62 | AE162: 57.75 | AF162: 32.555 | AG162: 80.75 | AH162: 41
B163: 43585 | D163: 5.8286 | E163: 20.68 | F163: 17.818 | G163: 35.39 | H163: 19.13 | I163: 48.20953 | J163: 102.57 | K163: 32.69 | L163: 8.13 | M163: 29.25 | N163: 18.395864 | O163: 38.88 | P163: 10.05 | Q163: 38.40256 | R163: 53.66 | T163: 30.496 | U163: 10.364548 | V163: 204.02 | W163: 66.89 | X163: 23 | Y163: 21.55 | Z163: 37.76 | AA163: 77.65318 | AB163: 33.85 | AC163: 12.04 | AD163: 13.85 | AE163: 60.45 | AF163: 34.79 | AG163: 95.65 | AH163: 45
B164: 43616 | D164: 4.1716 | E164: 21.26 | F164: 16.79 | G164: 35.62 | H164: 21.8 | I164: 40.680958 | J164: 83.97 | K164: 29.41 | L164: 9.76 | M164: 34.42 | N164: 15.802378 | O164: 31.16 | P164: 9.42 | Q164: 37.05679 | R164: 56.65 | T164: 29.207 | U164: 10.409093 | V164: 195.14 | W164: 68.82 | X164: 23.66 | Y164: 21.3 | Z164: 37.1 | AA164: 81.26565 | AB164: 33.5 | AC164: 11.13 | AD164: 15.45 | AE164: 61.05 | AF164: 29.38 | AG164: 84.23 | AH164: 42.8
B165: 43644 | D165: 4.27 | E165: 20.04 | F165: 16.317 | G165: 36.75 | H165: 21.47 | I165: 47.452385 | J165: 78.06 | K165: 34.3 | L165: 13.37 | M165: 38 | N165: 17.197493 | O165: 34.39 | P165: 10.6 | Q165: 38.739002 | R165: 62.57 | T165: 31.328 | U165: 10.000001 | V165: 199.33 | W165: 69.5 | X165: 22.79 | Y165: 20.825 | Z165: 39.79 | AA165: 79.4741 | AB165: 31.5 | AC165: 11.47 | AD165: 15.04 | AE165: 61.6998 | AF165: 32.79 | AG165: 95.78 | AH165: 48.6
B166: 43677 | D166: 4.19114 | E166: 21.12 | F166: 18.499 | G166: 36.3 | H166: 24.53 | I166: 47.633343 | J166: 79.24 | K166: 33 | L166: 14.11 | M166: 36.99 | N166: 19.075535 | O166: 38.71 | P166: 10.87 | Q166: 41.21907 | R166: 62 | T166: 29.222 | U166: 11.136366 | V166: 191.12 | W166: 71.42 | X166: 22.82 | Y166: 21.75 | Z166: 41.1 | AA166: 84.721466 | AB166: 31.25 | AC166: 11.53 | AD166: 12.99 | AE166: 60.225 | AF166: 32.48 | AG166: 92.4 | AH166: 47.15
B167: 43707 | D167: 3.9 | E167: 22.71 | F167: 20.58 | G167: 40.68 | H167: 27.25 | I167: 45.35239 | J167: 82.56 | K167: 37.73 | L167: 13.29 | M167: 36.32 | N167: 16.669853 | O167: 34.34 | P167: 10.85 | Q167: 42.23801 | R167: 69.45 | T167: 28.174 | U167: 11.013639 | V167: 174.05 | W167: 71.36 | X167: 21.31 | Y167: 21.36 | Z167: 41.76 | AA167: 87.912964 | AB167: 31.075 | AC167: 10.33 | AD167: 11.75 | AE167: 62.6 | AF167: 32.82 | AG167: 91.22 | AH167: 43.42
B168: 43738 | D168: 4.35 | E168: 22.91 | F168: 18.691 | G168: 41.79 | H168: 25.61 | I168: 43.10953 | J168: 79.75 | K168: 37.82 | L168: 10.1 | M168: 39.15 | N168: 17.581831 | O168: 35 | P168: 10.28 | Q168: 42.689808 | R168: 73.96 | T168: 29.69 | U168: 10.718184 | V168: 179.66 | W168: 71.34 | X168: 21.05 | Y168: 22.525 | Z168: 44.57 | AA168: 87.61926 | AB168: 31.175 | AC168: 10.89 | AD168: 11.94 | AE168: 59.55 | AF168: 33.26 | AG168: 93.18 | AH168: 43.135
B169: 43769 | D169: 4.606 | E169: 25.66 | F169: 20.989 | G169: 44.04 | H169: 25.19 | I169: 43.1381 | J169: 89.84 | K169: 41.16 | L169: 10.78 | M169: 39.16 | N169: 17.839827 | O169: 37.33 | P169: 11.18 | Q169: 44.064415 | R169: 76.26 | T169: 29.951 | U169: 11.068183 | V169: 182 | W169: 69.36 | X169: 20.74 | Y169: 23.675 | Z169: 46.83 | AA169: 90.125465 | AB169: 31.5 | AC169: 11.46 | AD169: 11.9 | AE169: 59.675 | AF169: 35.45 | AG169: 89.5 | AH169: 38.95
B170: 43798 | D170: 4.9998 | E170: 26.09 | F170: 21.797 | G170: 42.03 | H170: 25.33 | I170: 43.580963 | J170: 92.26 | K170: 43.8 | L170: 10.26 | M170: 41.59 | N170: 19.970667 | O170: 38.64 | P170: 12.42 | Q170: 45.785084 | R170: 80.08 | T170: 31.97 | U170: 11.359092 | V170: 193.5 | W170: 68.77 | X170: 21.93 | Y170: 24.25 | Z170: 54.11 | AA170: 81.66703 | AB170: 30.55 | AC170: 11.35 | AD170: 12.31 | AE170: 59.105 | AF170: 37.2385 | AG170: 92.71 | AH170: 37.6
B171: 43830 | D171: 5.4494 | E171: 24.81 | F171: 22.466 | G171: 42.35 | H171: 25.41 | I171: 46.566677 | J171: 88.08 | K171: 47.71 | L171: 10.15 | M171: 48.99 | N171: 20.41977 | O171: 39.96 | P171: 12.59 | Q171: 43.593395 | R171: 83.95 | T171: 36.449 | U171: 11.786366 | V171: 194.13 | W171: 73.73 | X171: 23 | Y171: 24 | Z171: 55 | AA171: 78.358055 | AB171: 31.2 | AC171: 9.83 | AD171: 12.23 | AE171: 57.65 | AF171: 37.82 | AG171: 95.84 | AH171: 41.575
... B231: 45657 | D231: 18.075 | E231: 31.28 | F231: 27.361 | G231: 37.85 | H231: 131.71 | I231: 0.52 | J231: 352.84 | K231: 165.16 | L231: 3.02 | M231: 221.65 | N231: 78.4 | O231: 51.48 | P231: 12.68 | Q231: 56.14 | R231: 108.58 | T231: 12.796 | U231: 7.65 | V231: 234.7 | W231: 39.56 | X231: 18.1 | Y231: 35.65 | Z231: 23.63 | AA231: 54.48 | AB231: 16.385 | AC231: 14.28 | AD231: 16.05 | AE231: 58.9 | AF231: 34.9 | AG231: 142.97 | AH231: 26.635
D236: Commodities
B237: Date | D237: OILDB-FDS | E237: NYGOLD-FDS | F237: NGAS-FDS | G237: CORNCI-FDS | H237: COPP-FDS
B238: 43496 | D238: 62.46 | E238: 1320.7 | F238: 2.814 | G238: 3.57 | H238: 2.789
B239: 43524 | D239: 65.03 | E239: 1312.9 | F239: 2.812 | G239: 3.465 | H239: 2.95
B240: 43553 | D240: 67.93 | E240: 1292 | F240: 2.662 | G240: 3.475 | H240: 2.936
B241: 43585 | D241: 72.19 | E241: 1283.1 | F241: 2.575 | G241: 3.525 | H241: 2.9015
B242: 43616 | D242: 66.78 | E242: 1304.9 | F242: 2.454 | G242: 4.22 | H242: 2.646
B243: 43644 | D243: 67.52 | E243: 1408.9 | F243: 2.308 | G243: 4.3225 | H243: 2.7055
B244: 43677 | D244: 64.07 | E244: 1413.4 | F244: 2.233 | G244: 4.2275 | H244: 2.658
B245: 43707 | D245: 61.04 | E245: 1519.6 | F245: 2.285 | G245: 3.68 | H245: 2.533
B246: 43738 | D246: 60.99 | E246: 1471.5 | F246: 2.33 | G246: 3.94 | H246: 2.5645
B247: 43769 | D247: 59.3 | E247: 1512.7 | F247: 2.633 | G247: 4.015 | H247: 2.633
B248: 43798 | D248: 64.5 | E248: 1464 | F248: 2.281 | G248: 3.7275 | H248: 2.642
B249: 43830 | D249: 67.77 | E249: 1516.8 | F249: 2.189 | G249: 4.0025 | H249: 2.794
... B309: 45657 | D309: 74.58 | E309: 2624.26 | F309: 3.633 | G309: 4.53 | H309: 3.986
D314: Fama & French (3-factor-model) | I314: Carhart (4-factor-model)
D315: Mkt-RF (Market excess return = Market - Risk-free) | E315: SMB (Small Minus Big (Size factor)) | F315: HML (High Minus Low (Value factor)) | G315: RF (Risk-free rate (1-month T-bill)) | I315: Mkt-RF (Market excess return = Market - Risk-free) | J315: SMB (Small Minus Big (Size factor)) | K315: HML (High Minus Low (Value factor)) | L315: RF (Risk-free rate (1-month T-bill)) | M315: MOM Momentum factor (Winners minus Losers)
D316: 1-Factor | E316: 2-Factor | F316: 3-Factor | G316: rf rate | I316: 1-Factor | J316: 2-Factor | K316: 3-Factor | L316: rf rate | M316: 4-Factor
B317: 201901 | D317: 8.37 | E317: 2.75 | F317: -0.39 | G317: 0.21 | I317: 8.37 | J317: 2.75 | K317: -0.39 | L317: 0.21 | M317: -8.59
B318: 201902 | D318: 3.42 | E318: 2.07 | F318: -2.67 | G318: 0.18 | I318: 3.42 | J318: 2.07 | K318: -2.67 | L318: 0.18 | M318: 0.5
B319: 201903 | D319: 1.1 | E319: -3.05 | F319: -4.16 | G319: 0.19 | I319: 1.1 | J319: -3.05 | K319: -4.16 | L319: 0.19 | M319: 2.23
B320: 201904 | D320: 3.97 | E320: -1.7 | F320: 2.15 | G320: 0.21 | I320: 3.97 | J320: -1.7 | K320: 2.15 | L320: 0.21 | M320: -2.89
B321: 201905 | D321: -6.92 | E321: -1.19 | F321: -2.43 | G321: 0.21 | I321: -6.92 | J321: -1.19 | K321: -2.43 | L321: 0.21 | M321: 7.56
B322: 201906 | D322: 6.92 | E322: 0.25 | F322: -0.67 | G322: 0.18 | I322: 6.92 | J322: 0.25 | K322: -0.67 | L322: 0.18 | M322: -2.27
B323: 201907 | D323: 1.23 | E323: -1.96 | F323: 0.5 | G323: 0.19 | I323: 1.23 | J323: -1.96 | K323: 0.5 | L323: 0.19 | M323: 2.92
B324: 201908 | D324: -2.55 | E324: -2.39 | F324: -4.77 | G324: 0.16 | I324: -2.55 | J324: -2.39 | K324: -4.77 | L324: 0.16 | M324: 7.53
B325: 201909 | D325: 1.41 | E325: -0.97 | F325: 6.76 | G325: 0.18 | I325: 1.41 | J325: -0.97 | K325: 6.76 | L325: 0.18 | M325: -6.83
B326: 201910 | D326: 2.07 | E326: 0.27 | F326: -1.92 | G326: 0.15 | I326: 2.07 | J326: 0.27 | K326: -1.92 | L326: 0.15 | M326: 0.13
B327: 201911 | D327: 3.87 | E327: 0.72 | F327: -2 | G327: 0.12 | I327: 3.87 | J327: 0.72 | K327: -2 | L327: 0.12 | M327: -2.59
B328: 201912 | D328: 2.77 | E328: 0.76 | F328: 1.73 | G328: 0.14 | I328: 2.77 | J328: 0.76 | K328: 1.73 | L328: 0.14 | M328: -2.2
... B388: 202412 | D388: -3.17 | E388: -2.72 | F388: -3 | G388: 0.37 | I388: -3.17 | J388: -2.72 | K388: -3 | L388: 0.37 | M388: -0.3
H389: AVERAGE | I389: =AVERAGE(I377:I388) -> 1.4983333 | J389: =AVERAGE(J377:J388) -> -0.69833333 | K389: =AVERAGE(K377:K388) -> -0.57916667 | L389: =AVERAGE(L317:L376) -> 0.14683333 | M389: =AVERAGE(M377:M388) -> 1.2916667

Sheet Question 1 - Prices
C1: Mean-Variance Optimization
A2: Date | C2: VFF-US | D2: FENC-US | E2: BDOUY-US | F2: SPMYY-US | G2: AHCHY-US | H2: NSC-US | I2: FQVTF-US | J2: CRAI-US | K2: CHEF-US | L2: SCGPY-US | M2: KOS-US | N2: DIISY-US | O2: TSLA-US | P2: AMZN-US | Q2: AAPL-US | R2: AVGO-US | S2: F-US | T2: SMCI-US | U2: CMCSA-US | V2: HAL-US | W2: BIRDF-US | X2: EPRT-US | Y2: OTSKY-US | Z2: OHI-US | AA2: AGYS-US
A3: 43496 | C3: 5.5747 | D3: 6.69 | E3: 26.51 | F3: 7.925 | G3: 27.018 | H3: 167.74 | I3: 34.3 | J3: 41.74 | K3: 32.12 | L3: 1.452 | M3: 5.13 | N3: 17.716 | O3: 20.46798 | P3: 85.9365 | Q3: 41.61 | R3: 26.825 | S3: 8.8 | T3: 1.5100001 | U3: 36.57 | V3: 31.36 | W3: 4.7501 | X3: 15.9 | Y3: 20.459 | Z3: 40.19 | AA3: 17.7
A4: 43524 | C4: 10.58 | D4: 6.65 | E4: 25.68 | F4: 8.04 | G4: 28.6 | H4: 179.3 | I4: 36.19 | J4: 49.96 | K4: 32.01 | L4: 1.72 | M4: 6.4 | N4: 18.978 | O4: 21.325312 | P4: 81.99151 | Q4: 43.2875 | R4: 27.536 | S4: 8.77 | T4: 1.9120001 | U4: 38.67 | V4: 30.69 | W4: 5.036 | X4: 16.97 | Y4: 20.85 | Z4: 35.9 | AA4: 20.9
A5: 43553 | C5: 14.01 | D5: 4.85 | E5: 26.09 | F5: 7.76 | G5: 30.542 | H5: 186.89 | I5: 39.27 | J5: 50.54 | K5: 31.05 | L5: 1.668 | M5: 6.23 | N5: 18.399 | O5: 18.65731 | P5: 89.0375 | Q5: 47.4875 | R5: 30.071 | S5: 8.78 | T5: 2.11275 | U5: 39.98 | V5: 29.3 | W5: 5.905 | X5: 19.52 | Y5: 19.646 | Z5: 38.15 | AA5: 21.17
A6: 43585 | C6: 12.5 | D6: 4.45 | E6: 25.4 | F6: 8 | G6: 30.496 | H6: 204.02 | I6: 40.7 | J6: 52.08 | K6: 32.68 | L6: 1.624 | M6: 6.69 | N6: 17.177 | O6: 15.912651 | P6: 96.326004 | Q6: 50.1675 | R6: 31.84 | S6: 10.45 | T6: 2.2420003 | U6: 43.53 | V6: 28.33 | W6: 5.8286 | X6: 20.68 | Y6: 17.818 | Z6: 35.39 | AA6: 19.13
A7: 43616 | C7: 12.1 | D7: 3.75 | E7: 26.5 | F7: 8.2 | G7: 29.207 | H7: 195.14 | I7: 33.35 | J7: 37.44 | K7: 31.67 | L7: 1.674 | M7: 6.16 | N7: 15.957 | O7: 12.343988 | P7: 88.7535 | Q7: 43.7675 | R7: 25.164 | S7: 9.52 | T7: 1.9 | U7: 41 | V7: 21.29 | W7: 4.1716 | X7: 21.26 | Y7: 16.79 | Z7: 35.62 | AA7: 21.8
A8: 43644 | C8: 11.44 | D8: 4 | E8: 27.39 | F8: 7.87 | G8: 31.328 | H8: 199.33 | I8: 29.795 | J8: 38.33 | K8: 35.07 | L8: 1.833 | M8: 6.27 | N8: 16.891 | O8: 14.897321 | P8: 94.68151 | Q8: 49.48 | R8: 28.786 | S8: 10.23 | T8: 1.9350001 | U8: 42.28 | V8: 22.74 | W8: 4.27 | X8: 20.04 | Y8: 16.317 | Z8: 36.75 | AA8: 21.47
A9: 43677 | C9: 11.37 | D9: 4.68 | E9: 28.35 | F9: 8.11 | G9: 29.222 | H9: 191.12 | I9: 28.87 | J9: 43.42 | K9: 36.47 | L9: 1.805 | M9: 6.01 | N9: 15.791 | O9: 16.107317 | P9: 93.339005 | Q9: 53.26 | R9: 28.998999 | S9: 9.53 | T9: 1.831 | U9: 43.17 | V9: 23 | W9: 4.19114 | X9: 21.12 | Y9: 18.499 | Z9: 36.3 | AA9: 24.53
A10: 43707 | C10: 10.5 | D10: 4.3 | E10: 28.4 | F10: 8.82 | G10: 28.174 | H10: 174.05 | I10: 27.93 | J10: 38.89 | K10: 38.58 | L10: 1.777 | M10: 6.32 | N10: 13.791 | O10: 15.040653 | P10: 88.81451 | Q10: 52.185 | R10: 28.264002 | S10: 9.17 | T10: 1.89 | U10: 44.26 | V10: 18.84 | W10: 3.9 | X10: 22.71 | Y10: 20.58 | Z10: 40.68 | AA10: 27.25
A11: 43738 | C11: 9.05 | D11: 4.81 | E11: 27.25 | F11: 9.98 | G11: 29.69 | H11: 179.66 | I11: 30 | J11: 41.97 | K11: 40.32 | L11: 1.839 | M11: 6.24 | N11: 14.798 | O11: 16.057983 | P11: 86.7955 | Q11: 55.9925 | R11: 27.607 | S11: 9.16 | T11: 1.9200001 | U11: 45.08 | V11: 18.85 | W11: 4.35 | X11: 22.91 | Y11: 18.691 | Z11: 41.79 | AA11: 25.61
A12: 43769 | C12: 7.91 | D12: 5.34 | E12: 29.44 | F12: 10.15 | G12: 29.951 | H12: 182 | I12: 23.86 | J12: 49.25 | K12: 33.125 | L12: 2.019 | M12: 6.2 | N12: 14.084 | O12: 20.994648 | P12: 88.833 | Q12: 62.19 | R12: 29.285002 | S12: 8.59 | T12: 2.068 | U12: 44.82 | V12: 19.25 | W12: 4.606 | X12: 25.66 | Y12: 20.989 | Z12: 44.04 | AA12: 25.19
A13: 43798 | C13: 6.62 | D13: 6.261 | E13: 31.38 | F13: 11.05 | G13: 31.97 | H13: 193.5 | I13: 28.46 | J13: 51.27 | K13: 35.56 | L13: 2.013 | M13: 5.97 | N13: 15.801 | O13: 21.995977 | P13: 90.04 | Q13: 66.8125 | R13: 31.621 | S13: 9.06 | T13: 2.1299999 | U13: 44.15 | V13: 20.99 | W13: 4.9998 | X13: 26.09 | Y13: 21.797 | Z13: 42.03 | AA13: 25.33
A14: 43830 | C14: 6.23 | D14: 6.49 | E14: 32.08 | F14: 13 | G14: 36.449 | H14: 194.13 | I14: 27.85 | J14: 54.47 | K14: 38.11 | L14: 2.145 | M14: 5.7 | N14: 16.559 | O14: 27.88864 | P14: 92.392 | Q14: 73.4125 | R14: 31.602 | S14: 9.3 | T14: 2.4020002 | U14: 44.97 | V14: 24.47 | W14: 5.4494 | X14: 24.81 | Y14: 22.466 | Z14: 42.35 | AA14: 25.41
... A74: 45657 | C74: 0.771 | D74: 6.32 | E74: 24.894 | F74: 9.36 | G74: 12.796 | H74: 234.7 | I74: 8.49 | J74: 187.2 | K74: 49.32 | L74: 1.895 | M74: 3.42 | N74: 12.785 | O74: 403.84 | P74: 219.39 | Q74: 250.42 | R74: 231.84 | S74: 9.9 | T74: 30.48 | U74: 37.53 | V74: 27.19 | W74: 18.075 | X74: 31.28 | Y74: 27.361 | Z74: 37.85 | AA74: 131.71

Sheet Question 1 - Return
A1: Date | B1: VFF-US | C1: FENC-US | D1: BDOUY-US | E1: SPMYY-US | F1: AHCHY-US | G1: NSC-US | H1: FQVTF-US | I1: CRAI-US | J1: CHEF-US | K1: SCGPY-US | L1: KOS-US | M1: DIISY-US | N1: TSLA-US | O1: AMZN-US | P1: AAPL-US | Q1: AVGO-US | R1: F-US | S1: SMCI-US | T1: CMCSA-US | U1: HAL-US | V1: BIRDF-US | W1: EPRT-US | X1: OTSKY-US | Y1: OHI-US | Z1: AGYS-US | AB1: Excess Return | AC1: VFF-US | AD1: FENC-US | AE1: BDOUY-US | AF1: SPMYY-US | AG1: AHCHY-US | AH1: NSC-US | AI1: FQVTF-US | AJ1: CRAI-US | AK1: CHEF-US | AL1: SCGPY-US | AM1: KOS-US | AN1: DIISY-US | AO1: TSLA-US | AP1: AMZN-US | AQ1: AAPL-US | AR1: AVGO-US | AS1: F-US | AT1: SMCI-US | AU1: CMCSA-US | AV1: HAL-US | AW1: BIRDF-US | AX1: EPRT-US | AY1: OTSKY-US | AZ1: OHI-US | BA1: AGYS-US | BD1: ST.DEV
A2: 43496 | BC2: VFF-US | BD2: 0.27615672
A3: 43524 | B3: =('Question 1 - Prices'!C4-'Question 1 - Prices'!C3)/'Question 1 - Prices'!C3 -> 0.89785997 | C3: =('Question 1 - Prices'!D4-'Question 1 - Prices'!D3)/'Question 1 - Prices'!D3 -> -0.0059790732 | D3: =('Question 1 - Prices'!E4-'Question 1 - Prices'!E3)/'Question 1 - Prices'!E3 -> -0.03130894 | E3: =('Question 1 - Prices'!F4-'Question 1 - Prices'!F3)/'Question 1 - Prices'!F3 -> 0.014511041 | F3: =('Question 1 - Prices'!G4-'Question 1 - Prices'!G3)/'Question 1 - Prices'!G3 -> 0.058553557 | G3: =('Question 1 - Prices'!H4-'Question 1 - Prices'!H3)/'Question 1 - Prices'!H3 -> 0.06891618 | H3: =('Question 1 - Prices'!I4-'Question 1 - Prices'!I3)/'Question 1 - Prices'!I3 -> 0.055102041 | I3: =('Question 1 - Prices'!J4-'Question 1 - Prices'!J3)/'Question 1 - Prices'!J3 -> 0.1969334 | ... Z3: =('Question 1 - Prices'!AA4-'Question 1 - Prices'!AA3)/'Question 1 - Prices'!AA3 -> 0.18079096 | AC3: =B3-B$62 -> 0.90194713 | AD3: =C3-C$62 -> -0.026743013 | AE3: =D3-D$62 -> -0.033490953 | AF3: =E3-E$62 -> 0.01321533 | AG3: =F3-F$62 -> 0.068209978 | AH3: =G3-G$62 -> 0.05961511 | AI3: =H3-H$62 -> 0.060834258 | AJ3: =I3-I$62 -> 0.1759683 | ... BA3: =Z3-Z$62 -> 0.1428744 | BC3: FENC-US | BD3: 0.15043912
A4: 43553 | B4: =('Question 1 - Prices'!C5-'Question 1 - Prices'!C4)/'Question 1 - Prices'!C4 -> 0.3241966 | C4: =('Question 1 - Prices'!D5-'Question 1 - Prices'!D4)/'Question 1 - Prices'!D4 -> -0.27067669 | D4: =('Question 1 - Prices'!E5-'Question 1 - Prices'!E4)/'Question 1 - Prices'!E4 -> 0.015965732 | E4: =('Question 1 - Prices'!F5-'Question 1 - Prices'!F4)/'Question 1 - Prices'!F4 -> -0.034825871 | F4: =('Question 1 - Prices'!G5-'Question 1 - Prices'!G4)/'Question 1 - Prices'!G4 -> 0.067902098 | G4: =('Question 1 - Prices'!H5-'Question 1 - Prices'!H4)/'Question 1 - Prices'!H4 -> 0.042331288 | H4: =('Question 1 - Prices'!I5-'Question 1 - Prices'!I4)/'Question 1 - Prices'!I4 -> 0.085106383 | I4: =('Question 1 - Prices'!J5-'Question 1 - Prices'!J4)/'Question 1 - Prices'!J4 -> 0.011609287 | ... Z4: =('Question 1 - Prices'!AA5-'Question 1 - Prices'!AA4)/'Question 1 - Prices'!AA4 -> 0.01291866 | AC4: =B4-B$62 -> 0.32828375 | AD4: =C4-C$62 -> -0.29144063 | AE4: =D4-D$62 -> 0.013783719 | AF4: =E4-E$62 -> -0.036121582 | AG4: =F4-F$62 -> 0.077558519 | AH4: =G4-G$62 -> 0.033030219 | AI4: =H4-H$62 -> 0.0908386 | AJ4: =I4-I$62 -> -0.0093558101 | ... BA4: =Z4-Z$62 -> -0.024997903 | BC4: BDOUY-US | BD4: 0.086733407
A5: 43585 | B5: =('Question 1 - Prices'!C6-'Question 1 - Prices'!C5)/'Question 1 - Prices'!C5 -> -0.10778016 | C5: =('Question 1 - Prices'!D6-'Question 1 - Prices'!D5)/'Question 1 - Prices'!D5 -> -0.082474227 | D5: =('Question 1 - Prices'!E6-'Question 1 - Prices'!E5)/'Question 1 - Prices'!E5 -> -0.026446915 | E5: =('Question 1 - Prices'!F6-'Question 1 - Prices'!F5)/'Question 1 - Prices'!F5 -> 0.030927835 | F5: =('Question 1 - Prices'!G6-'Question 1 - Prices'!G5)/'Question 1 - Prices'!G5 -> -0.0015061227 | G5: =('Question 1 - Prices'!H6-'Question 1 - Prices'!H5)/'Question 1 - Prices'!H5 -> 0.091658195 | H5: =('Question 1 - Prices'!I6-'Question 1 - Prices'!I5)/'Question 1 - Prices'!I5 -> 0.036414566 | I5: =('Question 1 - Prices'!J6-'Question 1 - Prices'!J5)/'Question 1 - Prices'!J5 -> 0.030470914 | ... Z5: =('Question 1 - Prices'!AA6-'Question 1 - Prices'!AA5)/'Question 1 - Prices'!AA5 -> -0.096362778 | AC5: =B5-B$62 -> -0.103693 | AD5: =C5-C$62 -> -0.10323817 | AE5: =D5-D$62 -> -0.028628927 | AF5: =E5-E$62 -> 0.029632124 | AG5: =F5-F$62 -> 0.0081502982 | AH5: =G5-G$62 -> 0.082357125 | AI5: =H5-H$62 -> 0.042146783 | AJ5: =I5-I$62 -> 0.0095058166 | ... BA5: =Z5-Z$62 -> -0.13427934 | BC5: SPMYY-US | BD5: 0.13625678
A6: 43616 | B6: =('Question 1 - Prices'!C7-'Question 1 - Prices'!C6)/'Question 1 - Prices'!C6 -> -0.032 | C6: =('Question 1 - Prices'!D7-'Question 1 - Prices'!D6)/'Question 1 - Prices'!D6 -> -0.15730337 | D6: =('Question 1 - Prices'!E7-'Question 1 - Prices'!E6)/'Question 1 - Prices'!E6 -> 0.043307087 | E6: =('Question 1 - Prices'!F7-'Question 1 - Prices'!F6)/'Question 1 - Prices'!F6 -> 0.025 | F6: =('Question 1 - Prices'!G7-'Question 1 - Prices'!G6)/'Question 1 - Prices'!G6 -> -0.042267838 | G6: =('Question 1 - Prices'!H7-'Question 1 - Prices'!H6)/'Question 1 - Prices'!H6 -> -0.043525145 | H6: =('Question 1 - Prices'!I7-'Question 1 - Prices'!I6)/'Question 1 - Prices'!I6 -> -0.18058968 | I6: =('Question 1 - Prices'!J7-'Question 1 - Prices'!J6)/'Question 1 - Prices'!J6 -> -0.28110599 | ... Z6: =('Question 1 - Prices'!AA7-'Question 1 - Prices'!AA6)/'Question 1 - Prices'!AA6 -> 0.13957135 | AC6: =B6-B$62 -> -0.027912847 | AD6: =C6-C$62 -> -0.17806731 | AE6: =D6-D$62 -> 0.041125074 | AF6: =E6-E$62 -> 0.023704289 | AG6: =F6-F$62 -> -0.032611417 | AH6: =G6-G$62 -> -0.052826214 | AI6: =H6-H$62 -> -0.17485746 | AJ6: =I6-I$62 -> -0.30207109 | ... BA6: =Z6-Z$62 -> 0.10165479 | BC6: AHCHY-US | BD6: 0.10490687
A7: 43644 | B7: =('Question 1 - Prices'!C8-'Question 1 - Prices'!C7)/'Question 1 - Prices'!C7 -> -0.054545455 | C7: =('Question 1 - Prices'!D8-'Question 1 - Prices'!D7)/'Question 1 - Prices'!D7 -> 0.066666667 | D7: =('Question 1 - Prices'!E8-'Question 1 - Prices'!E7)/'Question 1 - Prices'!E7 -> 0.033584906 | E7: =('Question 1 - Prices'!F8-'Question 1 - Prices'!F7)/'Question 1 - Prices'!F7 -> -0.040243902 | F7: =('Question 1 - Prices'!G8-'Question 1 - Prices'!G7)/'Question 1 - Prices'!G7 -> 0.072619577 | G7: =('Question 1 - Prices'!H8-'Question 1 - Prices'!H7)/'Question 1 - Prices'!H7 -> 0.021471764 | H7: =('Question 1 - Prices'!I8-'Question 1 - Prices'!I7)/'Question 1 - Prices'!I7 -> -0.1065967 | I7: =('Question 1 - Prices'!J8-'Question 1 - Prices'!J7)/'Question 1 - Prices'!J7 -> 0.023771368 | ... Z7: =('Question 1 - Prices'!AA8-'Question 1 - Prices'!AA7)/'Question 1 - Prices'!AA7 -> -0.015137615 | AC7: =B7-B$62 -> -0.050458301 | AD7: =C7-C$62 -> 0.045902727 | AE7: =D7-D$62 -> 0.031402893 | AF7: =E7-E$62 -> -0.041539613 | AG7: =F7-F$62 -> 0.082275998 | AH7: =G7-G$62 -> 0.012170694 | AI7: =H7-H$62 -> -0.10086448 | AJ7: =I7-I$62 -> 0.00280627 | ... BA7: =Z7-Z$62 -> -0.053054178 | BC7: NSC-US | BD7: 0.083175772
A8: 43677 | B8: =('Question 1 - Prices'!C9-'Question 1 - Prices'!C8)/'Question 1 - Prices'!C8 -> -0.0061188811 | C8: =('Question 1 - Prices'!D9-'Question 1 - Prices'!D8)/'Question 1 - Prices'!D8 -> 0.17 | D8: =('Question 1 - Prices'!E9-'Question 1 - Prices'!E8)/'Question 1 - Prices'!E8 -> 0.035049288 | E8: =('Question 1 - Prices'!F9-'Question 1 - Prices'!F8)/'Question 1 - Prices'!F8 -> 0.030495553 | F8: =('Question 1 - Prices'!G9-'Question 1 - Prices'!G8)/'Question 1 - Prices'!G8 -> -0.067224208 | G8: =('Question 1 - Prices'!H9-'Question 1 - Prices'!H8)/'Question 1 - Prices'!H8 -> -0.04118798 | H8: =('Question 1 - Prices'!I9-'Question 1 - Prices'!I8)/'Question 1 - Prices'!I8 -> -0.031045477 | I8: =('Question 1 - Prices'!J9-'Question 1 - Prices'!J8)/'Question 1 - Prices'!J8 -> 0.13279416 | ... Z8: =('Question 1 - Prices'!AA9-'Question 1 - Prices'!AA8)/'Question 1 - Prices'!AA8 -> 0.14252445 | AC8: =B8-B$62 -> -0.0020317277 | AD8: =C8-C$62 -> 0.14923606 | AE8: =D8-D$62 -> 0.032867275 | AF8: =E8-E$62 -> 0.029199842 | AG8: =F8-F$62 -> -0.057567787 | AH8: =G8-G$62 -> -0.050489049 | AI8: =H8-H$62 -> -0.02531326 | AJ8: =I8-I$62 -> 0.11182906 | ... BA8: =Z8-Z$62 -> 0.10460789 | BC8: FQVTF-US | BD8: 0.13443418
A9: 43707 | B9: =('Question 1 - Prices'!C10-'Question 1 - Prices'!C9)/'Question 1 - Prices'!C9 -> -0.07651715 | C9: =('Question 1 - Prices'!D10-'Question 1 - Prices'!D9)/'Question 1 - Prices'!D9 -> -0.081196581 | D9: =('Question 1 - Prices'!E10-'Question 1 - Prices'!E9)/'Question 1 - Prices'!E9 -> 0.0017636684 | E9: =('Question 1 - Prices'!F10-'Question 1 - Prices'!F9)/'Question 1 - Prices'!F9 -> 0.087546239 | F9: =('Question 1 - Prices'!G10-'Question 1 - Prices'!G9)/'Question 1 - Prices'!G9 -> -0.035863391 | G9: =('Question 1 - Prices'!H10-'Question 1 - Prices'!H9)/'Question 1 - Prices'!H9 -> -0.089315613 | H9: =('Question 1 - Prices'!I10-'Question 1 - Prices'!I9)/'Question 1 - Prices'!I9 -> -0.032559751 | I9: =('Question 1 - Prices'!J10-'Question 1 - Prices'!J9)/'Question 1 - Prices'!J9 -> -0.1043298 | ... Z9: =('Question 1 - Prices'!AA10-'Question 1 - Prices'!AA9)/'Question 1 - Prices'!AA9 -> 0.11088463 | AC9: =B9-B$62 -> -0.072429997 | AD9: =C9-C$62 -> -0.10196052 | AE9: =D9-D$62 -> -0.00041834449 | AF9: =E9-E$62 -> 0.086250528 | AG9: =F9-F$62 -> -0.02620697 | AH9: =G9-G$62 -> -0.098616683 | AI9: =H9-H$62 -> -0.026827534 | AJ9: =I9-I$62 -> -0.1252949 | ... BA9: =Z9-Z$62 -> 0.072968068 | BC9: CRAI-US | BD9: 0.10883734
A10: 43738 | B10: =('Question 1 - Prices'!C11-'Question 1 - Prices'!C10)/'Question 1 - Prices'!C10 -> -0.13809524 | C10: =('Question 1 - Prices'!D11-'Question 1 - Prices'!D10)/'Question 1 - Prices'!D10 -> 0.11860465 | D10: =('Question 1 - Prices'!E11-'Question 1 - Prices'!E10)/'Question 1 - Prices'!E10 -> -0.040492958 | E10: =('Question 1 - Prices'!F11-'Question 1 - Prices'!F10)/'Question 1 - Prices'!F10 -> 0.13151927 | F10: =('Question 1 - Prices'!G11-'Question 1 - Prices'!G10)/'Question 1 - Prices'!G10 -> 0.053808476 | G10: =('Question 1 - Prices'!H11-'Question 1 - Prices'!H10)/'Question 1 - Prices'!H10 -> 0.032232117 | H10: =('Question 1 - Prices'!I11-'Question 1 - Prices'!I10)/'Question 1 - Prices'!I10 -> 0.074113856 | I10: =('Question 1 - Prices'!J11-'Question 1 - Prices'!J10)/'Question 1 - Prices'!J10 -> 0.079197737 | ... Z10: =('Question 1 - Prices'!AA11-'Question 1 - Prices'!AA10)/'Question 1 - Prices'!AA10 -> -0.060183486 | AC10: =B10-B$62 -> -0.13400808 | AD10: =C10-C$62 -> 0.097840711 | AE10: =D10-D$62 -> -0.042674971 | AF10: =E10-E$62 -> 0.13022356 | AG10: =F10-F$62 -> 0.063464897 | AH10: =G10-G$62 -> 0.022931048 | AI10: =H10-H$62 -> 0.079846073 | AJ10: =I10-I$62 -> 0.05823264 | ... BA10: =Z10-Z$62 -> -0.098100049 | BC10: CHEF-US | BD10: 0.16945624
A11: 43769 | B11: =('Question 1 - Prices'!C12-'Question 1 - Prices'!C11)/'Question 1 - Prices'!C11 -> -0.12596685 | C11: =('Question 1 - Prices'!D12-'Question 1 - Prices'!D11)/'Question 1 - Prices'!D11 -> 0.11018711 | D11: =('Question 1 - Prices'!E12-'Question 1 - Prices'!E11)/'Question 1 - Prices'!E11 -> 0.080366972 | E11: =('Question 1 - Prices'!F12-'Question 1 - Prices'!F11)/'Question 1 - Prices'!F11 -> 0.017034068 | F11: =('Question 1 - Prices'!G12-'Question 1 - Prices'!G11)/'Question 1 - Prices'!G11 -> 0.0087908387 | G11: =('Question 1 - Prices'!H12-'Question 1 - Prices'!H11)/'Question 1 - Prices'!H11 -> 0.013024602 | H11: =('Question 1 - Prices'!I12-'Question 1 - Prices'!I11)/'Question 1 - Prices'!I11 -> -0.20466667 | I11: =('Question 1 - Prices'!J12-'Question 1 - Prices'!J11)/'Question 1 - Prices'!J11 -> 0.17345723 | ... Z11: =('Question 1 - Prices'!AA12-'Question 1 - Prices'!AA11)/'Question 1 - Prices'!AA11 -> -0.016399844 | AC11: =B11-B$62 -> -0.1218797 | AD11: =C11-C$62 -> 0.08942317 | AE11: =D11-D$62 -> 0.07818496 | AF11: =E11-E$62 -> 0.015738357 | AG11: =F11-F$62 -> 0.01844726 | AH11: =G11-G$62 -> 0.0037235323 | AI11: =H11-H$62 -> -0.19893445 | AJ11: =I11-I$62 -> 0.15249213 | ... BA11: =Z11-Z$62 -> -0.054316407 | BC11: SCGPY-US | BD11: 0.077805315
A12: 43798 | B12: =('Question 1 - Prices'!C13-'Question 1 - Prices'!C12)/'Question 1 - Prices'!C12 -> -0.1630847 | C12: =('Question 1 - Prices'!D13-'Question 1 - Prices'!D12)/'Question 1 - Prices'!D12 -> 0.17247191 | D12: =('Question 1 - Prices'!E13-'Question 1 - Prices'!E12)/'Question 1 - Prices'!E12 -> 0.065896739 | E12: =('Question 1 - Prices'!F13-'Question 1 - Prices'!F12)/'Question 1 - Prices'!F12 -> 0.088669951 | F12: =('Question 1 - Prices'!G13-'Question 1 - Prices'!G12)/'Question 1 - Prices'!G12 -> 0.067410103 | G12: =('Question 1 - Prices'!H13-'Question 1 - Prices'!H12)/'Question 1 - Prices'!H12 -> 0.063186813 | H12: =('Question 1 - Prices'!I13-'Question 1 - Prices'!I12)/'Question 1 - Prices'!I12 -> 0.19279128 | I12: =('Question 1 - Prices'!J13-'Question 1 - Prices'!J12)/'Question 1 - Prices'!J12 -> 0.041015228 | ... Z12: =('Question 1 - Prices'!AA13-'Question 1 - Prices'!AA12)/'Question 1 - Prices'!AA12 -> 0.005557761 | AC12: =B12-B$62 -> -0.15899755 | AD12: =C12-C$62 -> 0.15170797 | AE12: =D12-D$62 -> 0.063714726 | AF12: =E12-E$62 -> 0.08737424 | AG12: =F12-F$62 -> 0.077066524 | AH12: =G12-G$62 -> 0.053885743 | AI12: =H12-H$62 -> 0.1985235 | AJ12: =I12-I$62 -> 0.020050131 | ... BA12: =Z12-Z$62 -> -0.032358802 | BC12: KOS-US | BD12: 0.2208126
A13: 43830 | B13: =('Question 1 - Prices'!C14-'Question 1 - Prices'!C13)/'Question 1 - Prices'!C13 -> -0.058912387 | C13: =('Question 1 - Prices'!D14-'Question 1 - Prices'!D13)/'Question 1 - Prices'!D13 -> 0.036575627 | D13: =('Question 1 - Prices'!E14-'Question 1 - Prices'!E13)/'Question 1 - Prices'!E13 -> 0.022307202 | E13: =('Question 1 - Prices'!F14-'Question 1 - Prices'!F13)/'Question 1 - Prices'!F13 -> 0.17647059 | F13: =('Question 1 - Prices'!G14-'Question 1 - Prices'!G13)/'Question 1 - Prices'!G13 -> 0.14010009 | G13: =('Question 1 - Prices'!H14-'Question 1 - Prices'!H13)/'Question 1 - Prices'!H13 -> 0.003255814 | H13: =('Question 1 - Prices'!I14-'Question 1 - Prices'!I13)/'Question 1 - Prices'!I13 -> -0.021433591 | I13: =('Question 1 - Prices'!J14-'Question 1 - Prices'!J13)/'Question 1 - Prices'!J13 -> 0.062414667 | ... Z13: =('Question 1 - Prices'!AA14-'Question 1 - Prices'!AA13)/'Question 1 - Prices'!AA13 -> 0.0031583103 | AC13: =B13-B$62 -> -0.054825233 | AD13: =C13-C$62 -> 0.015811687 | AE13: =D13-D$62 -> 0.020125189 | AF13: =E13-E$62 -> 0.17517488 | AG13: =F13-F$62 -> 0.14975651 | AH13: =G13-G$62 -> -0.0060452558 | AI13: =H13-H$62 -> -0.015701374 | AJ13: =I13-I$62 -> 0.04144957 | ... BA13: =Z13-Z$62 -> -0.034758253 | BC13: DIISY-US | BD13: 0.11417749
A14: 43861 | B14: =('Question 1 - Prices'!C15-'Question 1 - Prices'!C14)/'Question 1 - Prices'!C14 -> -0.12359551 | C14: =('Question 1 - Prices'!D15-'Question 1 - Prices'!D14)/'Question 1 - Prices'!D14 -> 0.026194145 | D14: =('Question 1 - Prices'!E15-'Question 1 - Prices'!E14)/'Question 1 - Prices'!E14 -> -0.071150249 | E14: =('Question 1 - Prices'!F15-'Question 1 - Prices'!F14)/'Question 1 - Prices'!F14 -> -0.096153846 | F14: =('Question 1 - Prices'!G15-'Question 1 - Prices'!G14)/'Question 1 - Prices'!G14 -> -0.11490027 | G14: =('Question 1 - Prices'!H15-'Question 1 - Prices'!H14)/'Question 1 - Prices'!H14 -> 0.072528718 | H14: =('Question 1 - Prices'!I15-'Question 1 - Prices'!I14)/'Question 1 - Prices'!I14 -> -0.33788151 | I14: =('Question 1 - Prices'!J15-'Question 1 - Prices'!J14)/'Question 1 - Prices'!J14 -> -0.021846888 | ... Z14: =('Question 1 - Prices'!AA15-'Question 1 - Prices'!AA14)/'Question 1 - Prices'!AA14 -> 0.27902401 | AC14: =B14-B$62 -> -0.11950835 | AD14: =C14-C$62 -> 0.0054302051 | AE14: =D14-D$62 -> -0.073332262 | AF14: =E14-E$62 -> -0.097449557 | AG14: =F14-F$62 -> -0.10524385 | AH14: =G14-G$62 -> 0.063227648 | AI14: =H14-H$62 -> -0.33214929 | AJ14: =I14-I$62 -> -0.042811986 | ... BA14: =Z14-Z$62 -> 0.24110744 | BC14: TSLA-US | BD14: 0.21227491
... A26: 44225 | B26: =('Question 1 - Prices'!C27-'Question 1 - Prices'!C26)/'Question 1 - Prices'!C26 -> 0.16568047 | C26: =('Question 1 - Prices'!D27-'Question 1 - Prices'!D26)/'Question 1 - Prices'!D26 -> -0.033557047 | D26: =('Question 1 - Prices'!E27-'Question 1 - Prices'!E26)/'Question 1 - Prices'!E26 -> -0.058141103 | E26: =('Question 1 - Prices'!F27-'Question 1 - Prices'!F26)/'Question 1 - Prices'!F26 -> -0.040636042 | F26: =('Question 1 - Prices'!G27-'Question 1 - Prices'!G26)/'Question 1 - Prices'!G26 -> -0.053566295 | G26: =('Question 1 - Prices'!H27-'Question 1 - Prices'!H26)/'Question 1 - Prices'!H26 -> -0.0041664913 | H26: =('Question 1 - Prices'!I27-'Question 1 - Prices'!I26)/'Question 1 - Prices'!I26 -> -0.039011146 | I26: =('Question 1 - Prices'!J27-'Question 1 - Prices'!J26)/'Question 1 - Prices'!J26 -> 0.044767328 | ... Z26: =('Question 1 - Prices'!AA27-'Question 1 - Prices'!AA26)/'Question 1 - Prices'!AA26 -> -0.041427827 | AC26: =B26-B$62 -> 0.16976763 | AD26: =C26-C$62 -> -0.054320987 | AE26: =D26-D$62 -> -0.060323116 | AF26: =E26-E$62 -> -0.041931753 | AG26: =F26-F$62 -> -0.043909874 | AH26: =G26-G$62 -> -0.013467561 | AI26: =H26-H$62 -> -0.033278929 | AJ26: =I26-I$62 -> 0.02380223 | ... BA26: =Z26-Z$62 -> -0.07934439 | BC26: AGYS-US | BD26: 0.14413002
A27: 44253 | B27: =('Question 1 - Prices'!C28-'Question 1 - Prices'!C27)/'Question 1 - Prices'!C27 -> 0.3358714 | C27: =('Question 1 - Prices'!D28-'Question 1 - Prices'!D27)/'Question 1 - Prices'!D27 -> 0.016666667 | D27: =('Question 1 - Prices'!E28-'Question 1 - Prices'!E27)/'Question 1 - Prices'!E27 -> 0.038097966 | E27: =('Question 1 - Prices'!F28-'Question 1 - Prices'!F27)/'Question 1 - Prices'!F27 -> -0.019521179 | F27: =('Question 1 - Prices'!G28-'Question 1 - Prices'!G27)/'Question 1 - Prices'!G27 -> 0.085487681 | G27: =('Question 1 - Prices'!H28-'Question 1 - Prices'!H27)/'Question 1 - Prices'!H27 -> 0.065252303 | H27: =('Question 1 - Prices'!I28-'Question 1 - Prices'!I27)/'Question 1 - Prices'!I27 -> -0.039256506 | I27: =('Question 1 - Prices'!J28-'Question 1 - Prices'!J27)/'Question 1 - Prices'!J27 -> 0.036835181 | ... Z27: =('Question 1 - Prices'!AA28-'Question 1 - Prices'!AA27)/'Question 1 - Prices'!AA27 -> 0.61973362 | AC27: =B27-B$62 -> 0.33995856 | AD27: =C27-C$62 -> -0.0040972731 | AE27: =D27-D$62 -> 0.035915953 | AF27: =E27-E$62 -> -0.02081689 | AG27: =F27-F$62 -> 0.095144102 | AH27: =G27-G$62 -> 0.055951234 | AI27: =H27-H$62 -> -0.033524289 | AJ27: =I27-I$62 -> 0.015870084 | ... BA27: =Z27-Z$62 -> 0.58181706
A28: 44286 | B28: =('Question 1 - Prices'!C29-'Question 1 - Prices'!C28)/'Question 1 - Prices'!C28 -> -0.16212793 | C28: =('Question 1 - Prices'!D29-'Question 1 - Prices'!D28)/'Question 1 - Prices'!D28 -> -0.15163934 | D28: =('Question 1 - Prices'!E29-'Question 1 - Prices'!E28)/'Question 1 - Prices'!E28 -> -0.03352649 | E28: =('Question 1 - Prices'!F29-'Question 1 - Prices'!F28)/'Question 1 - Prices'!F28 -> -0.025544703 | F28: =('Question 1 - Prices'!G29-'Question 1 - Prices'!G28)/'Question 1 - Prices'!G28 -> 0.010788795 | G28: =('Question 1 - Prices'!H29-'Question 1 - Prices'!H28)/'Question 1 - Prices'!H28 -> 0.065301912 | H28: =('Question 1 - Prices'!I29-'Question 1 - Prices'!I28)/'Question 1 - Prices'!I28 -> -0.078006501 | I28: =('Question 1 - Prices'!J29-'Question 1 - Prices'!J28)/'Question 1 - Prices'!J28 -> 0.35290919 | ... Z28: =('Question 1 - Prices'!AA29-'Question 1 - Prices'!AA28)/'Question 1 - Prices'!AA28 -> -0.19516697 | AC28: =B28-B$62 -> -0.15804078 | AD28: =C28-C$62 -> -0.17240328 | AE28: =D28-D$62 -> -0.035708503 | AF28: =E28-E$62 -> -0.026840414 | AG28: =F28-F$62 -> 0.020445215 | AH28: =G28-G$62 -> 0.056000843 | AI28: =H28-H$62 -> -0.072274284 | AJ28: =I28-I$62 -> 0.33194409 | ... BA28: =Z28-Z$62 -> -0.23308354
A29: 44316 | B29: =('Question 1 - Prices'!C30-'Question 1 - Prices'!C29)/'Question 1 - Prices'!C29 -> -0.15570673 | C29: =('Question 1 - Prices'!D30-'Question 1 - Prices'!D29)/'Question 1 - Prices'!D29 -> 0.0064412238 | D29: =('Question 1 - Prices'!E30-'Question 1 - Prices'!E29)/'Question 1 - Prices'!E29 -> 0.018891268 | E29: =('Question 1 - Prices'!F30-'Question 1 - Prices'!F29)/'Question 1 - Prices'!F29 -> 0.10639938 | F29: =('Question 1 - Prices'!G30-'Question 1 - Prices'!G29)/'Question 1 - Prices'!G29 -> -0.080190711 | G29: =('Question 1 - Prices'!H30-'Question 1 - Prices'!H29)/'Question 1 - Prices'!H29 -> 0.039922538 | H29: =('Question 1 - Prices'!I30-'Question 1 - Prices'!I29)/'Question 1 - Prices'!I29 -> 0.18381736 | I29: =('Question 1 - Prices'!J30-'Question 1 - Prices'!J29)/'Question 1 - Prices'!J29 -> 0.075294748 | ... Z29: =('Question 1 - Prices'!AA30-'Question 1 - Prices'!AA29)/'Question 1 - Prices'!AA29 -> 0.051084237 | AC29: =B29-B$62 -> -0.15161957 | AD29: =C29-C$62 -> -0.014322716 | AE29: =D29-D$62 -> 0.016709255 | AF29: =E29-E$62 -> 0.10510367 | AG29: =F29-F$62 -> -0.07053429 | AH29: =G29-G$62 -> 0.030621469 | AI29: =H29-H$62 -> 0.18954957 | AJ29: =I29-I$62 -> 0.054329651 | ... BA29: =Z29-Z$62 -> 0.013167674
A30: 44344 | B30: =('Question 1 - Prices'!C31-'Question 1 - Prices'!C30)/'Question 1 - Prices'!C30 -> -0.12712623 | C30: =('Question 1 - Prices'!D31-'Question 1 - Prices'!D30)/'Question 1 - Prices'!D30 -> 0.1792 | D30: =('Question 1 - Prices'!E31-'Question 1 - Prices'!E30)/'Question 1 - Prices'!E30 -> -0.0053241173 | E30: =('Question 1 - Prices'!F31-'Question 1 - Prices'!F30)/'Question 1 - Prices'!F30 -> -0.024390244 | F30: =('Question 1 - Prices'!G31-'Question 1 - Prices'!G30)/'Question 1 - Prices'!G30 -> 0.034076848 | G30: =('Question 1 - Prices'!H31-'Question 1 - Prices'!H30)/'Question 1 - Prices'!H30 -> 0.0059447071 | H30: =('Question 1 - Prices'!I31-'Question 1 - Prices'!I30)/'Question 1 - Prices'!I30 -> 0.05643789 | I30: =('Question 1 - Prices'!J31-'Question 1 - Prices'!J30)/'Question 1 - Prices'!J30 -> 0.019935211 | ... Z30: =('Question 1 - Prices'!AA31-'Question 1 - Prices'!AA30)/'Question 1 - Prices'!AA30 -> 0.0075381869 | AC30: =B30-B$62 -> -0.12303908 | AD30: =C30-C$62 -> 0.15843606 | AE30: =D30-D$62 -> -0.0075061302 | AF30: =E30-E$62 -> -0.025685955 | AG30: =F30-F$62 -> 0.043733269 | AH30: =G30-G$62 -> -0.0033563626 | AI30: =H30-H$62 -> 0.062170107 | AJ30: =I30-I$62 -> -0.001029887 | ... BA30: =Z30-Z$62 -> -0.030378376
A31: 44377 | B31: =('Question 1 - Prices'!C32-'Question 1 - Prices'!C31)/'Question 1 - Prices'!C31 -> 0.097435897 | C31: =('Question 1 - Prices'!D32-'Question 1 - Prices'!D31)/'Question 1 - Prices'!D31 -> -0.010854817 | D31: =('Question 1 - Prices'!E32-'Question 1 - Prices'!E31)/'Question 1 - Prices'!E31 -> 0.088834632 | E31: =('Question 1 - Prices'!F32-'Question 1 - Prices'!F31)/'Question 1 - Prices'!F31 -> -0.028571429 | F31: =('Question 1 - Prices'!G32-'Question 1 - Prices'!G31)/'Question 1 - Prices'!G31 -> -0.14216415 | G31: =('Question 1 - Prices'!H32-'Question 1 - Prices'!H31)/'Question 1 - Prices'!H31 -> -0.055144179 | H31: =('Question 1 - Prices'!I32-'Question 1 - Prices'!I31)/'Question 1 - Prices'!I31 -> -0.0080536913 | I31: =('Question 1 - Prices'!J32-'Question 1 - Prices'!J31)/'Question 1 - Prices'!J31 -> 0.04568776 | ... Z31: =('Question 1 - Prices'!AA32-'Question 1 - Prices'!AA31)/'Question 1 - Prices'!AA31 -> 0.1197086 | AC31: =B31-B$62 -> 0.10152305 | AD31: =C31-C$62 -> -0.031618757 | AE31: =D31-D$62 -> 0.086652619 | AF31: =E31-E$62 -> -0.02986714 | AG31: =F31-F$62 -> -0.13250773 | AH31: =G31-G$62 -> -0.064445249 | AI31: =H31-H$62 -> -0.0023214743 | AJ31: =I31-I$62 -> 0.024722662 | ... BA31: =Z31-Z$62 -> 0.081792041
A32: 44407 | B32: =('Question 1 - Prices'!C33-'Question 1 - Prices'!C32)/'Question 1 - Prices'!C32 -> -0.098130841 | C32: =('Question 1 - Prices'!D33-'Question 1 - Prices'!D32)/'Question 1 - Prices'!D32 -> -0.10699588 | D32: =('Question 1 - Prices'!E33-'Question 1 - Prices'!E32)/'Question 1 - Prices'!E32 -> -0.12005175 | E32: =('Question 1 - Prices'!F33-'Question 1 - Prices'!F32)/'Question 1 - Prices'!F32 -> 0.042647059 | F32: =('Question 1 - Prices'!G33-'Question 1 - Prices'!G32)/'Question 1 - Prices'!G32 -> -0.098921813 | G32: =('Question 1 - Prices'!H33-'Question 1 - Prices'!H32)/'Question 1 - Prices'!H32 -> -0.028559587 | H32: =('Question 1 - Prices'!I33-'Question 1 - Prices'!I32)/'Question 1 - Prices'!I32 -> -0.092286874 | I32: =('Question 1 - Prices'!J33-'Question 1 - Prices'!J32)/'Question 1 - Prices'!J32 -> 0.0015186916 | ... Z32: =('Question 1 - Prices'!AA33-'Question 1 - Prices'!AA32)/'Question 1 - Prices'!AA32 -> -0.023034992 | AC32: =B32-B$62 -> -0.094043688 | AD32: =C32-C$62 -> -0.12775982 | AE32: =D32-D$62 -> -0.12223376 | AF32: =E32-E$62 -> 0.041351348 | AG32: =F32-F$62 -> -0.089265392 | AH32: =G32-G$62 -> -0.037860657 | AI32: =H32-H$62 -> -0.086554657 | AJ32: =I32-I$62 -> -0.019446406 | ... BA32: =Z32-Z$62 -> -0.060951555
A33: 44439 | B33: =('Question 1 - Prices'!C34-'Question 1 - Prices'!C33)/'Question 1 - Prices'!C33 -> 0.0010362694 | C33: =('Question 1 - Prices'!D34-'Question 1 - Prices'!D33)/'Question 1 - Prices'!D33 -> 0.21658986 | D33: =('Question 1 - Prices'!E34-'Question 1 - Prices'!E33)/'Question 1 - Prices'!E33 -> 0.082573753 | E33: =('Question 1 - Prices'!F34-'Question 1 - Prices'!F33)/'Question 1 - Prices'!F33 -> 0.16361072 | F33: =('Question 1 - Prices'!G34-'Question 1 - Prices'!G33)/'Question 1 - Prices'!G33 -> 0.13237386 | G33: =('Question 1 - Prices'!H34-'Question 1 - Prices'!H33)/'Question 1 - Prices'!H33 -> -0.016638871 | H33: =('Question 1 - Prices'!I34-'Question 1 - Prices'!I33)/'Question 1 - Prices'!I33 -> -0.091383423 | I33: =('Question 1 - Prices'!J34-'Question 1 - Prices'!J33)/'Question 1 - Prices'!J33 -> 0.084684475 | ... Z33: =('Question 1 - Prices'!AA34-'Question 1 - Prices'!AA33)/'Question 1 - Prices'!AA33 -> 0.022858171 | AC33: =B33-B$62 -> 0.0051234228 | AD33: =C33-C$62 -> 0.19582592 | AE33: =D33-D$62 -> 0.08039174 | AF33: =E33-E$62 -> 0.16231501 | AG33: =F33-F$62 -> 0.14203028 | AH33: =G33-G$62 -> -0.02593994 | AI33: =H33-H$62 -> -0.085651206 | AJ33: =I33-I$62 -> 0.063719377 | ... BA33: =Z33-Z$62 -> -0.015058392
A34: 44469 | B34: =('Question 1 - Prices'!C35-'Question 1 - Prices'!C34)/'Question 1 - Prices'!C34 -> -0.13664596 | C34: =('Question 1 - Prices'!D35-'Question 1 - Prices'!D34)/'Question 1 - Prices'!D34 -> 0.18939394 | D34: =('Question 1 - Prices'!E35-'Question 1 - Prices'!E34)/'Question 1 - Prices'!E34 -> -0.018514327 | E34: =('Question 1 - Prices'!F35-'Question 1 - Prices'!F34)/'Question 1 - Prices'!F34 -> -0.05030303 | F34: =('Question 1 - Prices'!G35-'Question 1 - Prices'!G34)/'Question 1 - Prices'!G34 -> -0.0033252051 | G34: =('Question 1 - Prices'!H35-'Question 1 - Prices'!H34)/'Question 1 - Prices'!H34 -> -0.056361915 | H34: =('Question 1 - Prices'!I35-'Question 1 - Prices'!I34)/'Question 1 - Prices'!I34 -> 0.032813782 | I34: =('Question 1 - Prices'!J35-'Question 1 - Prices'!J34)/'Question 1 - Prices'!J34 -> 0.068286913 | ... Z34: =('Question 1 - Prices'!AA35-'Question 1 - Prices'!AA34)/'Question 1 - Prices'!AA34 -> -0.07865564 | AC34: =B34-B$62 -> -0.13255881 | AD34: =C34-C$62 -> 0.16863 | AE34: =D34-D$62 -> -0.02069634 | AF34: =E34-E$62 -> -0.051598741 | AG34: =F34-F$62 -> 0.0063312159 | AH34: =G34-G$62 -> -0.065662985 | AI34: =H34-H$62 -> 0.038545999 | AJ34: =I34-I$62 -> 0.047321815 | ... BA34: =Z34-Z$62 -> -0.1165722
A35: 44498 | B35: =('Question 1 - Prices'!C36-'Question 1 - Prices'!C35)/'Question 1 - Prices'!C35 -> -0.092326139 | C35: =('Question 1 - Prices'!D36-'Question 1 - Prices'!D35)/'Question 1 - Prices'!D35 -> -0.016985138 | D35: =('Question 1 - Prices'!E36-'Question 1 - Prices'!E35)/'Question 1 - Prices'!E35 -> 0.13541186 | E35: =('Question 1 - Prices'!F36-'Question 1 - Prices'!F35)/'Question 1 - Prices'!F35 -> -0.017230377 | F35: =('Question 1 - Prices'!G36-'Question 1 - Prices'!G35)/'Question 1 - Prices'!G35 -> -0.077884045 | G35: =('Question 1 - Prices'!H36-'Question 1 - Prices'!H35)/'Question 1 - Prices'!H35 -> 0.22486938 | H35: =('Question 1 - Prices'!I36-'Question 1 - Prices'!I35)/'Question 1 - Prices'!I35 -> -0.012073074 | I35: =('Question 1 - Prices'!J36-'Question 1 - Prices'!J35)/'Question 1 - Prices'!J35 -> 0.10549628 | ... Z35: =('Question 1 - Prices'!AA36-'Question 1 - Prices'!AA35)/'Question 1 - Prices'!AA35 -> -0.088617265 | AC35: =B35-B$62 -> -0.088238986 | AD35: =C35-C$62 -> -0.037749078 | AE35: =D35-D$62 -> 0.13322985 | AF35: =E35-E$62 -> -0.018526088 | AG35: =F35-F$62 -> -0.068227624 | AH35: =G35-G$62 -> 0.21556831 | AI35: =H35-H$62 -> -0.0063408569 | AJ35: =I35-I$62 -> 0.084531178 | ... BA35: =Z35-Z$62 -> -0.12653383
A36: 44530 | B36: =('Question 1 - Prices'!C37-'Question 1 - Prices'!C36)/'Question 1 - Prices'!C36 -> -0.12417437 | C36: =('Question 1 - Prices'!D37-'Question 1 - Prices'!D36)/'Question 1 - Prices'!D36 -> -0.52591793 | D36: =('Question 1 - Prices'!E37-'Question 1 - Prices'!E36)/'Question 1 - Prices'!E36 -> -0.00028434479 | E36: =('Question 1 - Prices'!F37-'Question 1 - Prices'!F36)/'Question 1 - Prices'!F36 -> -0.068181818 | F36: =('Question 1 - Prices'!G37-'Question 1 - Prices'!G36)/'Question 1 - Prices'!G36 -> -0.085949749 | G36: =('Question 1 - Prices'!H37-'Question 1 - Prices'!H36)/'Question 1 - Prices'!H36 -> -0.09479611 | H36: =('Question 1 - Prices'!I37-'Question 1 - Prices'!I36)/'Question 1 - Prices'!I36 -> 0.13394436 | I36: =('Question 1 - Prices'!J37-'Question 1 - Prices'!J36)/'Question 1 - Prices'!J36 -> -0.16162812 | ... Z36: =('Question 1 - Prices'!AA37-'Question 1 - Prices'!AA36)/'Question 1 - Prices'!AA36 -> -0.087384744 | AC36: =B36-B$62 -> -0.12008722 | AD36: =C36-C$62 -> -0.54668187 | AE36: =D36-D$62 -> -0.0024663577 | AF36: =E36-E$62 -> -0.069477529 | AG36: =F36-F$62 -> -0.076293328 | AH36: =G36-G$62 -> -0.10409718 | AI36: =H36-H$62 -> 0.13967658 | AJ36: =I36-I$62 -> -0.18259322 | ... BA36: =Z36-Z$62 -> -0.12530131
A37: 44561 | B37: =('Question 1 - Prices'!C38-'Question 1 - Prices'!C37)/'Question 1 - Prices'!C37 -> -0.031674208 | C37: =('Question 1 - Prices'!D38-'Question 1 - Prices'!D37)/'Question 1 - Prices'!D37 -> 0.0022779043 | D37: =('Question 1 - Prices'!E38-'Question 1 - Prices'!E37)/'Question 1 - Prices'!E37 -> -0.038234936 | E37: =('Question 1 - Prices'!F38-'Question 1 - Prices'!F37)/'Question 1 - Prices'!F37 -> 0.017421603 | F37: =('Question 1 - Prices'!G38-'Question 1 - Prices'!G37)/'Question 1 - Prices'!G37 -> 0.098649778 | G37: =('Question 1 - Prices'!H38-'Question 1 - Prices'!H37)/'Question 1 - Prices'!H37 -> 0.1222905 | H37: =('Question 1 - Prices'!I38-'Question 1 - Prices'!I37)/'Question 1 - Prices'!I37 -> 0.033182076 | I37: =('Question 1 - Prices'!J38-'Question 1 - Prices'!J37)/'Question 1 - Prices'!J37 -> 0.014011079 | ... Z37: =('Question 1 - Prices'!AA38-'Question 1 - Prices'!AA37)/'Question 1 - Prices'!AA37 -> 0.020895522 | AC37: =B37-B$62 -> -0.027587055 | AD37: =C37-C$62 -> -0.018486035 | AE37: =D37-D$62 -> -0.040416949 | AF37: =E37-E$62 -> 0.016125892 | AG37: =F37-F$62 -> 0.1083062 | AH37: =G37-G$62 -> 0.11298943 | AI37: =H37-H$62 -> 0.038914293 | AJ37: =I37-I$62 -> -0.006954019 | ... BA37: =Z37-Z$62 -> -0.017021041
A38: 44592 | B38: =('Question 1 - Prices'!C39-'Question 1 - Prices'!C38)/'Question 1 - Prices'!C38 -> -0.19158879 | C38: =('Question 1 - Prices'!D39-'Question 1 - Prices'!D38)/'Question 1 - Prices'!D38 -> 0.056818182 | D38: =('Question 1 - Prices'!E39-'Question 1 - Prices'!E38)/'Question 1 - Prices'!E38 -> 0.11888466 | E38: =('Question 1 - Prices'!F39-'Question 1 - Prices'!F38)/'Question 1 - Prices'!F38 -> -0.1369863 | F38: =('Question 1 - Prices'!G39-'Question 1 - Prices'!G38)/'Question 1 - Prices'!G38 -> 0.055004003 | G38: =('Question 1 - Prices'!H39-'Question 1 - Prices'!H38)/'Question 1 - Prices'!H38 -> -0.086392798 | H38: =('Question 1 - Prices'!I39-'Question 1 - Prices'!I38)/'Question 1 - Prices'!I38 -> -0.23579467 | I38: =('Question 1 - Prices'!J39-'Question 1 - Prices'!J38)/'Question 1 - Prices'!J38 -> -0.088903171 | ... Z38: =('Question 1 - Prices'!AA39-'Question 1 - Prices'!AA38)/'Question 1 - Prices'!AA38 -> -0.14394962 | AC38: =B38-B$62 -> -0.18750163 | AD38: =C38-C$62 -> 0.036054242 | AE38: =D38-D$62 -> 0.11670265 | AF38: =E38-E$62 -> -0.13828201 | AG38: =F38-F$62 -> 0.064660424 | AH38: =G38-G$62 -> -0.095693868 | AI38: =H38-H$62 -> -0.23006246 | AJ38: =I38-I$62 -> -0.10986827 | ... BA38: =Z38-Z$62 -> -0.18186618
... A61: 45289 | B61: =('Question 1 - Prices'!C62-'Question 1 - Prices'!C61)/'Question 1 - Prices'!C61 -> -0.036220871 | C61: =('Question 1 - Prices'!D62-'Question 1 - Prices'!D61)/'Question 1 - Prices'!D61 -> 0.30465116 | D61: =('Question 1 - Prices'!E62-'Question 1 - Prices'!E61)/'Question 1 - Prices'!E61 -> -0.020409012 | E61: =('Question 1 - Prices'!F62-'Question 1 - Prices'!F61)/'Question 1 - Prices'!F61 -> 0.20889292 | F61: =('Question 1 - Prices'!G62-'Question 1 - Prices'!G61)/'Question 1 - Prices'!G61 -> -0.012988123 | G61: =('Question 1 - Prices'!H62-'Question 1 - Prices'!H61)/'Question 1 - Prices'!H61 -> 0.083516685 | H61: =('Question 1 - Prices'!I62-'Question 1 - Prices'!I61)/'Question 1 - Prices'!I61 -> 0.0056053812 | I61: =('Question 1 - Prices'!J62-'Question 1 - Prices'!J61)/'Question 1 - Prices'!J61 -> 0.043051599 | ... Z61: =('Question 1 - Prices'!AA62-'Question 1 - Prices'!AA61)/'Question 1 - Prices'!AA61 -> -0.014752004 | AC61: =B61-B$62 -> -0.032133718 | AD61: =C61-C$62 -> 0.28388722 | AE61: =D61-D$62 -> -0.022591024 | AF61: =E61-E$62 -> 0.20759721 | AG61: =F61-F$62 -> -0.0033317018 | AH61: =G61-G$62 -> 0.074215615 | AI61: =H61-H$62 -> 0.011337598 | AJ61: =I61-I$62 -> 0.022086501 | ... BA61: =Z61-Z$62 -> -0.052668567
A62: Average | B62: =AVERAGE(B3:B61) -> -0.0040871534 | C62: =AVERAGE(C3:C61) -> 0.02076394 | D62: =AVERAGE(D3:D61) -> 0.0021820129 | E62: =AVERAGE(E3:E61) -> 0.001295711 | F62: =AVERAGE(F3:F61) -> -0.0096564209 | G62: =AVERAGE(G3:G61) -> 0.0093010697 | H62: =AVERAGE(H3:H61) -> -0.005732217 | I62: =AVERAGE(I3:I61) -> 0.020965098 | ... Z62: =AVERAGE(Z3:Z61) -> 0.037916563
A63: STDDEV | B63: =_xlfn.STDEV.S(B3:B61) -> 0.28760977 | C63: =_xlfn.STDEV.S(C3:C61) -> 0.14585287 | D63: =_xlfn.STDEV.S(D3:D61) -> 0.08908199 | E63: =_xlfn.STDEV.S(E3:E61) -> 0.099918163 | F63: =_xlfn.STDEV.S(F3:F61) -> 0.099692901 | G63: =_xlfn.STDEV.S(G3:G61) -> 0.084319629 | H63: =_xlfn.STDEV.S(H3:H61) -> 0.14480171 | I63: =_xlfn.STDEV.S(I3:I61) -> 0.11224067 | ... Z63: =_xlfn.STDEV.S(Z3:Z61) -> 0.15099219 | AC63: 0.28760977 | AD63: 0.14585287 | AE63: 0.08908199 | AF63: 0.099918163 | AG63: 0.099692901 | AH63: 0.084319629 | AI63: 0.14480171 | AJ63: 0.11224067 | AK63: 0.18231644 | AL63: 0.081368392 | AM63: 0.23944213 | AN63: 0.10517382 | AO63: 0.22258853 | AP63: 0.09472053 | AQ63: 0.086958477 | AR63: 0.091983456 | AS63: 0.13300916 | AT63: 0.19526854 | AU63: 0.073847238 | AV63: 0.17885433 | AW63: 0.10679487 | AX63: 0.10109334 | AY63: 0.069268495 | AZ63: 0.085047327 | BA63: 0.15099219
A64: Variance | B64: =B63^2 -> 0.082719382 | C64: =C63^2 -> 0.021273059 | D64: =D63^2 -> 0.007935601 | E64: =E63^2 -> 0.0099836392 | F64: =F63^2 -> 0.0099386746 | G64: =G63^2 -> 0.0071097999 | H64: =H63^2 -> 0.020967537 | I64: =I63^2 -> 0.012597968 | ... Z64: =Z63^2 -> 0.022798642

Sheet Question 1 -Variance_Covariance
A1: XTX | B1: VFF-US | C1: FENC-US | D1: BDOUY-US | E1: SPMYY-US | F1: AHCHY-US | G1: NSC-US | H1: FQVTF-US | I1: CRAI-US | J1: CHEF-US | K1: SCGPY-US | L1: KOS-US | M1: DIISY-US | N1: TSLA-US | O1: AMZN-US | P1: AAPL-US | Q1: AVGO-US | R1: F-US | S1: SMCI-US | T1: CMCSA-US | U1: HAL-US | V1: BIRDF-US | W1: EPRT-US | X1: OTSKY-US | Y1: OHI-US | Z1: AGYS-US | AB1: Number of observations
A2: VFF-US | B2: {=MMULT(TRANSPOSE('Question 1 - Return'!AC3:BA61),'Question 1 - Return'!AC3:BA61)} -> 4.7977242 | C2: 0.1251531 | D2: 0.38507202 | E2: 0.086500691 | F2: 0.20369037 | G2: 0.52203818 | H2: 0.76666529 | I2: 0.59457758 | J2: 1.4196507 | K2: 0.22726756 | L2: 2.090559 | M2: 0.51358016 | N2: 0.87834648 | O2: 0.23706986 | P2: 0.3775484 | Q2: 0.39365575 | R2: 0.7018071 | S2: 0.51925858 | T2: 0.55771153 | U2: 1.1178414 | V2: 0.75851138 | W2: 0.71750749 | X2: 0.28078273 | Y2: 0.49111495 | Z2: 1.0656969 | AB2: 59
A3: FENC-US | B3: 0.1251531 | C3: 1.2338374 | D3: 0.1482438 | E3: 0.22777336 | F3: 0.11259304 | G3: 0.13153573 | H3: 0.015812509 | I3: 0.27473208 | J3: 0.3167119 | K3: 0.13438516 | L3: 0.23250329 | M3: 0.10692041 | N3: 0.020884376 | O3: -0.014454606 | P3: -0.056997773 | Q3: 0.084179269 | R3: 0.22366489 | S3: -0.097410878 | T3: 0.011271456 | U3: 0.34889655 | V3: 0.2741772 | W3: 0.071500153 | X3: 0.099054804 | Y3: -0.00018486179 | Z3: 0.071054407
A4: BDOUY-US | B4: 0.38507202 | C4: 0.1482438 | D4: 0.46026486 | E4: -0.017659413 | F4: 0.083748648 | G4: 0.17241015 | H4: 0.21135364 | I4: 0.13372646 | J4: 0.49112034 | K4: 0.13594987 | L4: 0.6826581 | M4: 0.094858732 | N4: 0.33625839 | O4: 0.10808552 | P4: 0.18038442 | Q4: 0.14263651 | R4: 0.37575986 | S4: 0.17399198 | T4: 0.19696722 | U4: 0.52221906 | V4: 0.1453564 | W4: 0.27269285 | X4: 0.03173333 | Y4: 0.22339754 | Z4: 0.13890042
A5: SPMYY-US | B5: 0.086500691 | C5: 0.22777336 | D5: -0.017659413 | E5: 0.57905107 | F5: 0.14205005 | G5: 0.18167564 | H5: 0.27199643 | I5: 0.22039442 | J5: 0.22086083 | K5: 0.13543516 | L5: 0.06407574 | M5: 0.15548045 | N5: 0.31347127 | O5: 0.14397586 | P5: 0.1570704 | Q5: 0.11394521 | R5: 0.10331566 | S5: 0.077440971 | T5: 0.090841683 | U5: 0.10857212 | V5: 0.20138698 | W5: 0.17256357 | X5: 0.073499796 | Y5: 0.024809441 | Z5: 0.045095606
A6: AHCHY-US | B6: 0.20369037 | C6: 0.11259304 | D6: 0.083748648 | E6: 0.14205005 | F6: 0.57644313 | G6: 0.12241195 | H6: 0.25317697 | I6: 0.16249644 | J6: 0.16258161 | K6: 0.094582192 | L6: 0.30037146 | M6: 0.10354772 | N6: 0.012309568 | O6: 0.0050218979 | P6: 0.0046771466 | Q6: 0.092397233 | R6: 0.038859671 | S6: 0.018014049 | T6: 0.17539806 | U6: 0.25064872 | V6: 0.2695617 | W6: 0.073190908 | X6: -0.013065961 | Y6: -0.0011889988 | Z6: 0.034469675
A7: NSC-US | B7: 0.52203818 | C7: 0.13153573 | D7: 0.17241015 | E7: 0.18167564 | F7: 0.12241195 | G7: 0.41236839 | H7: 0.28810649 | I7: 0.28253817 | J7: 0.53013725 | K7: 0.14839049 | L7: 0.57084277 | M7: 0.15808045 | N7: 0.54386192 | O7: 0.19631733 | P7: 0.2316862 | Q7: 0.28452734 | R7: 0.3994606 | S7: 0.27042249 | T7: 0.1815051 | U7: 0.45992337 | V7: 0.28094654 | W7: 0.32423199 | X7: 0.046558144 | Y7: 0.17246955 | Z7: 0.20090318
A8: FQVTF-US | B8: 0.76666529 | C8: 0.015812509 | D8: 0.21135364 | E8: 0.27199643 | F8: 0.25317697 | G8: 0.28810649 | H8: 1.2161171 | I8: 0.2758405 | J8: 0.69787536 | K8: 0.14051771 | L8: 0.82796537 | M8: 0.14958743 | N8: 0.24529657 | O8: 0.24899133 | P8: 0.30241847 | Q8: 0.37506202 | R8: 0.36829276 | S8: 0.33992368 | T8: 0.34027015 | U8: 0.60640132 | V8: 0.43108849 | W8: 0.26635736 | X8: 0.099696351 | Y8: 0.13740645 | Z8: 0.060466983
A9: CRAI-US | B9: 0.59457758 | C9: 0.27473208 | D9: 0.13372646 | E9: 0.22039442 | F9: 0.16249644 | G9: 0.28253817 | H9: 0.2758405 | I9: 0.73068216 | J9: 0.48072904 | K9: 0.23169915 | L9: 0.71267793 | M9: 0.1489059 | N9: 0.40974788 | O9: 0.093132585 | P9: 0.18411982 | Q9: 0.20491888 | R9: 0.28964407 | S9: 0.16710889 | T9: 0.18501824 | U9: 0.62477259 | V9: 0.3901887 | W9: 0.30142265 | X9: 0.094478558 | Y9: 0.10523411 | Z9: 0.20414765
A10: CHEF-US | B10: 1.4196507 | C10: 0.3167119 | D10: 0.49112034 | E10: 0.22086083 | F10: 0.16258161 | G10: 0.53013725 | H10: 0.69787536 | I10: 0.48072904 | J10: 1.9278786 | K10: 0.20299569 | L10: 1.5834966 | M10: 0.25691489 | N10: 0.90970869 | O10: 0.1709647 | P10: 0.33951802 | Q10: 0.40392307 | R10: 0.59601354 | S10: 0.28584586 | T10: 0.39379351 | U10: 1.1340705 | V10: 0.44508392 | W10: 0.63495747 | X10: 0.20551896 | Y10: 0.38220124 | Z10: 0.77908291
A11: SCGPY-US | B11: 0.22726756 | C11: 0.13438516 | D11: 0.13594987 | E11: 0.13543516 | F11: 0.094582192 | G11: 0.14839049 | H11: 0.14051771 | I11: 0.23169915 | J11: 0.20299569 | K11: 0.38400728 | L11: 0.34918941 | M11: 0.13842286 | N11: 0.16449565 | O11: 0.083199981 | P11: 0.15401625 | Q11: 0.12844383 | R11: 0.21664077 | S11: 0.22154164 | T11: 0.13381226 | U11: 0.32574386 | V11: 0.17745981 | W11: 0.18720398 | X11: 0.0079542788 | Y11: 0.11218906 | Z11: 0.12492331
A12: KOS-US | B12: 2.090559 | C12: 0.23250329 | D12: 0.6826581 | E12: 0.06407574 | F12: 0.30037146 | G12: 0.57084277 | H12: 0.82796537 | I12: 0.71267793 | J12: 1.5834966 | K12: 0.34918941 | L12: 3.325287 | M12: 0.25409107 | N12: 0.99397202 | O12: 0.28788911 | P12: 0.32073839 | Q12: 0.43506113 | R12: 0.81470584 | S12: 0.49895596 | T12: 0.50467672 | U12: 2.01218 | V12: 0.55794061 | W12: 0.63964231 | X12: 0.12003502 | Y12: 0.665109 | Z12: 0.88628061
A13: DIISY-US | B13: 0.51358016 | C13: 0.10692041 | D13: 0.094858732 | E13: 0.15548045 | F13: 0.10354772 | G13: 0.15808045 | H13: 0.14958743 | I13: 0.1489059 | J13: 0.25691489 | K13: 0.13842286 | L13: 0.25409107 | M13: 0.64156884 | N13: 0.037994129 | O13: -0.056425371 | P13: 0.069027741 | Q13: 0.089236778 | R13: 0.045523796 | S13: 0.14066588 | T13: 0.16722445 | U13: 0.41937231 | V13: 0.27319405 | W13: 0.14875634 | X13: 0.097552822 | Y13: 0.046221103 | Z13: 0.16128359
A14: TSLA-US | B14: 0.87834648 | C14: 0.020884376 | D14: 0.33625839 | E14: 0.31347127 | F14: 0.012309568 | G14: 0.54386192 | H14: 0.24529657 | I14: 0.40974788 | J14: 0.90970869 | K14: 0.16449565 | L14: 0.99397202 | M14: 0.037994129 | N14: 2.8736479 | O14: 0.77202879 | P14: 0.78888502 | Q14: 0.4745002 | R14: 0.58998889 | S14: 0.54116598 | T14: 0.21071581 | U14: 0.70301874 | V14: 0.33193236 | W14: 0.46703365 | X14: 0.18685908 | Y14: 0.34880882 | Z14: 0.23975123
... A26: AGYS-US | B26: 1.0656969 | C26: 0.071054407 | D26: 0.13890042 | E26: 0.045095606 | F26: 0.034469675 | G26: 0.20090318 | H26: 0.060466983 | I26: 0.20414765 | J26: 0.77908291 | K26: 0.12492331 | L26: 0.88628061 | M26: 0.16128359 | N26: 0.23975123 | O26: 0.021623171 | P26: 0.024261911 | Q26: 0.077516869 | R26: 0.073910017 | S26: 0.0009804528 | T26: 0.18866048 | U26: 0.60473085 | V26: 0.17239327 | W26: 0.48489676 | X26: 0.004311929 | Y26: 0.2913643 | Z26: 1.3223212
A29: varaiance-covariance matrix | B29: VFF-US | C29: FENC-US | D29: BDOUY-US | E29: SPMYY-US | F29: AHCHY-US | G29: NSC-US | H29: FQVTF-US | I29: CRAI-US | J29: CHEF-US | K29: SCGPY-US | L29: KOS-US | M29: DIISY-US | N29: TSLA-US | O29: AMZN-US | P29: AAPL-US | Q29: AVGO-US | R29: F-US | S29: SMCI-US | T29: CMCSA-US | U29: HAL-US | V29: BIRDF-US | W29: EPRT-US | X29: OTSKY-US | Y29: OHI-US | Z29: AGYS-US
A30: VFF-US | B30: {=(_xlfn.ANCHORARRAY(B2))/AB2} -> 0.081317359 | C30: 0.002121239 | D30: 0.0065266445 | E30: 0.0014661134 | F30: 0.0034523792 | G30: 0.0088481047 | H30: 0.012994327 | I30: 0.010077586 | J30: 0.024061877 | K30: 0.0038519926 | L30: 0.035433203 | M30: 0.0087047485 | N30: 0.014887228 | O30: 0.0040181332 | P30: 0.0063991255 | Q30: 0.0066721313 | R30: 0.011895036 | S30: 0.0088009929 | T30: 0.0094527379 | U30: 0.018946464 | V30: 0.012856125 | W30: 0.012161144 | X30: 0.0047590293 | Y30: 0.0083239822 | Z30: 0.01806266
A31: FENC-US | B31: 0.002121239 | C31: 0.020912498 | D31: 0.0025126068 | E31: 0.0038605654 | F31: 0.0019083565 | G31: 0.0022294191 | H31: 0.00026800862 | I31: 0.004656476 | J31: 0.0053679982 | K31: 0.0022777146 | L31: 0.0039407337 | M31: 0.0018122104 | N31: 0.00035397248 | O31: -0.00024499333 | P31: -0.00096606395 | Q31: 0.0014267673 | R31: 0.0037909304 | S31: -0.0016510318 | T31: 0.00019104163 | U31: 0.0059135008 | V31: 0.0046470712 | W31: 0.001211867 | X31: 0.001678895 | Y31: -3.1332506e-06 | Z31: 0.001204312
A32: BDOUY-US | B32: 0.0065266445 | C32: 0.0025126068 | D32: 0.0078010993 | E32: -0.00029931209 | F32: 0.0014194686 | G32: 0.002922206 | H32: 0.003582265 | I32: 0.0022665502 | J32: 0.0083240735 | K32: 0.0023042352 | L32: 0.011570476 | M32: 0.0016077751 | N32: 0.0056992947 | O32: 0.001831958 | P32: 0.003057363 | Q32: 0.0024175679 | R32: 0.0063688111 | S32: 0.0029490167 | T32: 0.0033384275 | U32: 0.0088511705 | V32: 0.0024636679 | W32: 0.0046219126 | X32: 0.00053785305 | Y32: 0.003786399 | Z32: 0.0023542444
A33: SPMYY-US | B33: 0.0014661134 | C33: 0.0038605654 | D33: -0.00029931209 | E33: 0.009814425 | F33: 0.0024076279 | G33: 0.0030792482 | H33: 0.004610109 | I33: 0.0037354987 | J33: 0.0037434039 | K33: 0.0022955111 | L33: 0.0010860295 | M33: 0.0026352619 | N33: 0.0053130724 | O33: 0.0024402689 | P33: 0.0026622101 | Q33: 0.0019312748 | R33: 0.0017511128 | S33: 0.0013125588 | T33: 0.0015396895 | U33: 0.0018402054 | V33: 0.0034133387 | W33: 0.0029248062 | X33: 0.0012457593 | Y33: 0.000420499 | Z33: 0.00076433231
A34: AHCHY-US | B34: 0.0034523792 | C34: 0.0019083565 | D34: 0.0014194686 | E34: 0.0024076279 | F34: 0.0097702225 | G34: 0.0020747788 | H34: 0.0042911351 | I34: 0.0027541769 | J34: 0.0027556205 | K34: 0.001603088 | L34: 0.0050910416 | M34: 0.0017550462 | N34: 0.00020863675 | O34: 8.5116914e-05 | P34: 7.9273671e-05 | Q34: 0.0015660548 | R34: 0.00065863849 | S34: 0.00030532287 | T34: 0.0029728485 | U34: 0.0042482834 | V34: 0.0045688423 | W34: 0.0012405239 | X34: -0.00022145696 | Y34: -2.0152522e-05 | Z34: 0.00058423177
A35: NSC-US | B35: 0.0088481047 | C35: 0.0022294191 | D35: 0.002922206 | E35: 0.0030792482 | F35: 0.0020747788 | G35: 0.0069892948 | H35: 0.0048831608 | I35: 0.0047887825 | J35: 0.0089853771 | K35: 0.002515093 | L35: 0.0096753012 | M35: 0.0026793296 | N35: 0.0092179986 | O35: 0.0033274124 | P35: 0.0039268848 | Q35: 0.0048224972 | R35: 0.0067705187 | S35: 0.004583432 | T35: 0.0030763577 | U35: 0.0077953113 | V35: 0.0047618057 | W35: 0.0054954575 | X35: 0.00078912109 | Y35: 0.0029232126 | Z35: 0.0034051386
A36: FQVTF-US | B36: 0.012994327 | C36: 0.00026800862 | D36: 0.003582265 | E36: 0.004610109 | F36: 0.0042911351 | G36: 0.0048831608 | H36: 0.020612155 | I36: 0.0046752626 | J36: 0.011828396 | K36: 0.0023816561 | L36: 0.014033311 | M36: 0.0025353801 | N36: 0.004157569 | O36: 0.004220192 | P36: 0.0051257368 | Q36: 0.0063569834 | R36: 0.0062422502 | S36: 0.0057614184 | T36: 0.0057672907 | U36: 0.010277988 | V36: 0.0073065846 | W36: 0.0045145315 | X36: 0.0016897687 | Y36: 0.0023289228 | Z36: 0.0010248641
A37: CRAI-US | B37: 0.010077586 | C37: 0.004656476 | D37: 0.0022665502 | E37: 0.0037354987 | F37: 0.0027541769 | G37: 0.0047887825 | H37: 0.0046752626 | I37: 0.012384443 | J37: 0.0081479498 | K37: 0.0039271042 | L37: 0.012079287 | M37: 0.0025238288 | N37: 0.0069448793 | O37: 0.0015785184 | P37: 0.0031206749 | Q37: 0.0034732014 | R37: 0.0049092215 | S37: 0.002832354 | T37: 0.0031359024 | U37: 0.010589366 | V37: 0.0066133679 | W37: 0.0051088584 | X37: 0.0016013315 | Y37: 0.001783629 | Z37: 0.0034601296
A38: CHEF-US | B38: 0.024061877 | C38: 0.0053679982 | D38: 0.0083240735 | E38: 0.0037434039 | F38: 0.0027556205 | G38: 0.0089853771 | H38: 0.011828396 | I38: 0.0081479498 | J38: 0.032675908 | K38: 0.003440605 | L38: 0.026838926 | M38: 0.0043544896 | N38: 0.015418791 | O38: 0.0028977067 | P38: 0.0057545426 | Q38: 0.0068461537 | R38: 0.010101924 | S38: 0.004844845 | T38: 0.0066744662 | U38: 0.019221534 | V38: 0.0075437952 | W38: 0.010761991 | X38: 0.0034833721 | Y38: 0.0064779871 | Z38: 0.013204795
A39: SCGPY-US | B39: 0.0038519926 | C39: 0.0022777146 | D39: 0.0023042352 | E39: 0.0022955111 | F39: 0.001603088 | G39: 0.002515093 | H39: 0.0023816561 | I39: 0.0039271042 | J39: 0.003440605 | K39: 0.006508598 | L39: 0.0059184646 | M39: 0.0023461501 | N39: 0.0027880619 | O39: 0.0014101692 | P39: 0.0026104449 | Q39: 0.002177014 | R39: 0.0036718775 | S39: 0.003754943 | T39: 0.0022680044 | U39: 0.0055210824 | V39: 0.0030077933 | W39: 0.0031729489 | X39: 0.00013481829 | Y39: 0.0019015094 | Z39: 0.0021173443
A40: KOS-US | B40: 0.035433203 | C40: 0.0039407337 | D40: 0.011570476 | E40: 0.0010860295 | F40: 0.0050910416 | G40: 0.0096753012 | H40: 0.014033311 | I40: 0.012079287 | J40: 0.026838926 | K40: 0.0059184646 | L40: 0.056360797 | M40: 0.0043066283 | N40: 0.016846983 | O40: 0.0048794764 | P40: 0.0054362438 | Q40: 0.0073739175 | R40: 0.013808574 | S40: 0.0084568807 | T40: 0.0085538427 | U40: 0.034104746 | V40: 0.0094566205 | W40: 0.010841395 | X40: 0.0020344919 | Y40: 0.011273034 | Z40: 0.015021705
A41: DIISY-US | B41: 0.0087047485 | C41: 0.0018122104 | D41: 0.0016077751 | E41: 0.0026352619 | F41: 0.0017550462 | G41: 0.0026793296 | H41: 0.0025353801 | I41: 0.0025238288 | J41: 0.0043544896 | K41: 0.0023461501 | L41: 0.0043066283 | M41: 0.010874048 | N41: 0.00064396828 | O41: -0.00095636221 | P41: 0.0011699617 | Q41: 0.0015124878 | R41: 0.00077158976 | S41: 0.0023841674 | T41: 0.0028343127 | U41: 0.0071080052 | V41: 0.0046304076 | W41: 0.002521294 | X41: 0.0016534377 | Y41: 0.00078340853 | Z41: 0.0027336201
A42: TSLA-US | B42: 0.014887228 | C42: 0.00035397248 | D42: 0.0056992947 | E42: 0.0053130724 | F42: 0.00020863675 | G42: 0.0092179986 | H42: 0.004157569 | I42: 0.0069448793 | J42: 0.015418791 | K42: 0.0027880619 | L42: 0.016846983 | M42: 0.00064396828 | N42: 0.048705896 | O42: 0.013085234 | P42: 0.013370933 | Q42: 0.0080423763 | R42: 0.0099998117 | S42: 0.0091723047 | T42: 0.0035714544 | U42: 0.011915572 | V42: 0.0056259722 | W42: 0.0079158246 | X42: 0.0031671031 | Y42: 0.0059120138 | Z42: 0.0040635801
... A54: AGYS-US | B54: 0.01806266 | C54: 0.001204312 | D54: 0.0023542444 | E54: 0.00076433231 | F54: 0.00058423177 | G54: 0.0034051386 | H54: 0.0010248641 | I54: 0.0034601296 | J54: 0.013204795 | K54: 0.0021173443 | L54: 0.015021705 | M54: 0.0027336201 | N54: 0.0040635801 | O54: 0.00036649443 | P54: 0.00041121884 | Q54: 0.0013138452 | R54: 0.0012527121 | S54: 1.6617844e-05 | T54: 0.0031976353 | U54: 0.010249675 | V54: 0.0029219199 | W54: 0.0082185891 | X54: 7.3083542e-05 | Y54: 0.004938378 | Z54: 0.022412224

Sheet Question1 - Portfolio Optimiza.
A1: STOCK | B1: Avrg monthly ret | C1: Annual return | D1: monthly ST. DEV | E1: annual st. dev | F1: annual sharpe ratio | I1: {='Question 1 -Variance_Covariance'!A29:Z29} -> varaiance-covariance matrix | J1: VFF-US | K1: FENC-US | L1: BDOUY-US | M1: SPMYY-US | N1: AHCHY-US | O1: NSC-US | P1: FQVTF-US | Q1: CRAI-US | R1: CHEF-US | S1: SCGPY-US | T1: KOS-US | U1: DIISY-US | V1: TSLA-US | W1: AMZN-US | X1: AAPL-US | Y1: AVGO-US | Z1: F-US | AA1: SMCI-US | AB1: CMCSA-US | AC1: HAL-US | AD1: BIRDF-US | AE1: EPRT-US | AF1: OTSKY-US | AG1: OHI-US | AH1: AGYS-US | AK1: varaiance-covariance matrix | AL1: VFF-US | AM1: FENC-US | AN1: BDOUY-US | AO1: SPMYY-US | AP1: AHCHY-US | AQ1: NSC-US | AR1: FQVTF-US | AS1: CRAI-US | AT1: CHEF-US | AU1: SCGPY-US | AV1: KOS-US | AW1: DIISY-US | AX1: TSLA-US | AY1: AMZN-US | AZ1: AAPL-US | BA1: AVGO-US | BB1: F-US | BC1: SMCI-US | BD1: CMCSA-US | BE1: HAL-US | BF1: BIRDF-US | BG1: EPRT-US | BH1: OTSKY-US | BI1: OHI-US | BJ1: AGYS-US | BK1: 10 & 20 yr bond
A2: VFF-US | B2: -0.0040871534 | C2: =(1+B2)^12-1 -> -0.047958206 | D2: 0.28760977 | E2: =D2*SQRT(12) -> 0.99630948 | F2: =C2/E2 -> -0.048135852 | I2: {='Question 1 -Variance_Covariance'!A30:A54} -> VFF-US | J2: {='Question 1 -Variance_Covariance'!B30:Z54} -> 0.081317359 | K2: 0.002121239 | L2: 0.0065266445 | M2: 0.0014661134 | N2: 0.0034523792 | O2: 0.0088481047 | P2: 0.012994327 | Q2: 0.010077586 | R2: 0.024061877 | S2: 0.0038519926 | T2: 0.035433203 | U2: 0.0087047485 | V2: 0.014887228 | W2: 0.0040181332 | X2: 0.0063991255 | Y2: 0.0066721313 | Z2: 0.011895036 | AA2: 0.0088009929 | AB2: 0.0094527379 | AC2: 0.018946464 | AD2: 0.012856125 | AE2: 0.012161144 | AF2: 0.0047590293 | AG2: 0.0083239822 | AH2: 0.01806266 | AK2: VFF-US | AL2: {=J2:AH26} -> 0.081317359 | AM2: 0.002121239 | AN2: 0.0065266445 | AO2: 0.0014661134 | AP2: 0.0034523792 | AQ2: 0.0088481047 | AR2: 0.012994327 | AS2: 0.010077586 | AT2: 0.024061877 | AU2: 0.0038519926 | AV2: 0.035433203 | AW2: 0.0087047485 | AX2: 0.014887228 | AY2: 0.0040181332 | AZ2: 0.0063991255 | BA2: 0.0066721313 | BB2: 0.011895036 | BC2: 0.0088009929 | BD2: 0.0094527379 | BE2: 0.018946464 | BF2: 0.012856125 | BG2: 0.012161144 | BH2: 0.0047590293 | BI2: 0.0083239822 | BJ2: 0.01806266 | BK2: 0
A3: FENC-US | B3: 0.02076394 | C3: =(1+B3)^12-1 -> 0.27968722 | D3: 0.14585287 | E3: =D3*SQRT(12) -> 0.50524915 | F3: =C3/E3 -> 0.55356297 | I3: FENC-US | J3: 0.002121239 | K3: 0.020912498 | L3: 0.0025126068 | M3: 0.0038605654 | N3: 0.0019083565 | O3: 0.0022294191 | P3: 0.00026800862 | Q3: 0.004656476 | R3: 0.0053679982 | S3: 0.0022777146 | T3: 0.0039407337 | U3: 0.0018122104 | V3: 0.00035397248 | W3: -0.00024499333 | X3: -0.00096606395 | Y3: 0.0014267673 | Z3: 0.0037909304 | AA3: -0.0016510318 | AB3: 0.00019104163 | AC3: 0.0059135008 | AD3: 0.0046470712 | AE3: 0.001211867 | AF3: 0.001678895 | AG3: -3.1332506e-06 | AH3: 0.001204312 | AK3: FENC-US | AL3: 0.002121239 | AM3: 0.020912498 | AN3: 0.0025126068 | AO3: 0.0038605654 | AP3: 0.0019083565 | AQ3: 0.0022294191 | AR3: 0.00026800862 | AS3: 0.004656476 | AT3: 0.0053679982 | AU3: 0.0022777146 | AV3: 0.0039407337 | AW3: 0.0018122104 | AX3: 0.00035397248 | AY3: -0.00024499333 | AZ3: -0.00096606395 | BA3: 0.0014267673 | BB3: 0.0037909304 | BC3: -0.0016510318 | BD3: 0.00019104163 | BE3: 0.0059135008 | BF3: 0.0046470712 | BG3: 0.001211867 | BH3: 0.001678895 | BI3: -3.1332506e-06 | BJ3: 0.001204312 | BK3: 0
A4: BDOUY-US | B4: 0.0021820129 | C4: =(1+B4)^12-1 -> 0.02650069 | D4: 0.08908199 | E4: =D4*SQRT(12) -> 0.30858907 | F4: =C4/E4 -> 0.085876956 | I4: BDOUY-US | J4: 0.0065266445 | K4: 0.0025126068 | L4: 0.0078010993 | M4: -0.00029931209 | N4: 0.0014194686 | O4: 0.002922206 | P4: 0.003582265 | Q4: 0.0022665502 | R4: 0.0083240735 | S4: 0.0023042352 | T4: 0.011570476 | U4: 0.0016077751 | V4: 0.0056992947 | W4: 0.001831958 | X4: 0.003057363 | Y4: 0.0024175679 | Z4: 0.0063688111 | AA4: 0.0029490167 | AB4: 0.0033384275 | AC4: 0.0088511705 | AD4: 0.0024636679 | AE4: 0.0046219126 | AF4: 0.00053785305 | AG4: 0.003786399 | AH4: 0.0023542444 | AK4: BDOUY-US | AL4: 0.0065266445 | AM4: 0.0025126068 | AN4: 0.0078010993 | AO4: -0.00029931209 | AP4: 0.0014194686 | AQ4: 0.002922206 | AR4: 0.003582265 | AS4: 0.0022665502 | AT4: 0.0083240735 | AU4: 0.0023042352 | AV4: 0.011570476 | AW4: 0.0016077751 | AX4: 0.0056992947 | AY4: 0.001831958 | AZ4: 0.003057363 | BA4: 0.0024175679 | BB4: 0.0063688111 | BC4: 0.0029490167 | BD4: 0.0033384275 | BE4: 0.0088511705 | BF4: 0.0024636679 | BG4: 0.0046219126 | BH4: 0.00053785305 | BI4: 0.003786399 | BJ4: 0.0023542444 | BK4: 0
A5: SPMYY-US | B5: 0.001295711 | C5: =(1+B5)^12-1 -> 0.015659818 | D5: 0.099918163 | E5: =D5*SQRT(12) -> 0.34612667 | F5: =C5/E5 -> 0.045243026 | I5: SPMYY-US | J5: 0.0014661134 | K5: 0.0038605654 | L5: -0.00029931209 | M5: 0.009814425 | N5: 0.0024076279 | O5: 0.0030792482 | P5: 0.004610109 | Q5: 0.0037354987 | R5: 0.0037434039 | S5: 0.0022955111 | T5: 0.0010860295 | U5: 0.0026352619 | V5: 0.0053130724 | W5: 0.0024402689 | X5: 0.0026622101 | Y5: 0.0019312748 | Z5: 0.0017511128 | AA5: 0.0013125588 | AB5: 0.0015396895 | AC5: 0.0018402054 | AD5: 0.0034133387 | AE5: 0.0029248062 | AF5: 0.0012457593 | AG5: 0.000420499 | AH5: 0.00076433231 | AK5: SPMYY-US | AL5: 0.0014661134 | AM5: 0.0038605654 | AN5: -0.00029931209 | AO5: 0.009814425 | AP5: 0.0024076279 | AQ5: 0.0030792482 | AR5: 0.004610109 | AS5: 0.0037354987 | AT5: 0.0037434039 | AU5: 0.0022955111 | AV5: 0.0010860295 | AW5: 0.0026352619 | AX5: 0.0053130724 | AY5: 0.0024402689 | AZ5: 0.0026622101 | BA5: 0.0019312748 | BB5: 0.0017511128 | BC5: 0.0013125588 | BD5: 0.0015396895 | BE5: 0.0018402054 | BF5: 0.0034133387 | BG5: 0.0029248062 | BH5: 0.0012457593 | BI5: 0.000420499 | BJ5: 0.00076433231 | BK5: 0
A6: AHCHY-US | B6: -0.0096564209 | C6: =(1+B6)^12-1 -> -0.10991664 | D6: 0.099692901 | E6: =D6*SQRT(12) -> 0.34534634 | F6: =C6/E6 -> -0.31827944 | I6: AHCHY-US | J6: 0.0034523792 | K6: 0.0019083565 | L6: 0.0014194686 | M6: 0.0024076279 | N6: 0.0097702225 | O6: 0.0020747788 | P6: 0.0042911351 | Q6: 0.0027541769 | R6: 0.0027556205 | S6: 0.001603088 | T6: 0.0050910416 | U6: 0.0017550462 | V6: 0.00020863675 | W6: 8.5116914e-05 | X6: 7.9273671e-05 | Y6: 0.0015660548 | Z6: 0.00065863849 | AA6: 0.00030532287 | AB6: 0.0029728485 | AC6: 0.0042482834 | AD6: 0.0045688423 | AE6: 0.0012405239 | AF6: -0.00022145696 | AG6: -2.0152522e-05 | AH6: 0.00058423177 | AK6: AHCHY-US | AL6: 0.0034523792 | AM6: 0.0019083565 | AN6: 0.0014194686 | AO6: 0.0024076279 | AP6: 0.0097702225 | AQ6: 0.0020747788 | AR6: 0.0042911351 | AS6: 0.0027541769 | AT6: 0.0027556205 | AU6: 0.001603088 | AV6: 0.0050910416 | AW6: 0.0017550462 | AX6: 0.00020863675 | AY6: 8.5116914e-05 | AZ6: 7.9273671e-05 | BA6: 0.0015660548 | BB6: 0.00065863849 | BC6: 0.00030532287 | BD6: 0.0029728485 | BE6: 0.0042482834 | BF6: 0.0045688423 | BG6: 0.0012405239 | BH6: -0.00022145696 | BI6: -2.0152522e-05 | BJ6: 0.00058423177 | BK6: 0
A7: NSC-US | B7: 0.0093010697 | C7: =(1+B7)^12-1 -> 0.11750327 | D7: 0.084319629 | E7: =D7*SQRT(12) -> 0.29209176 | F7: =C7/E7 -> 0.40228204 | I7: NSC-US | J7: 0.0088481047 | K7: 0.0022294191 | L7: 0.002922206 | M7: 0.0030792482 | N7: 0.0020747788 | O7: 0.0069892948 | P7: 0.0048831608 | Q7: 0.0047887825 | R7: 0.0089853771 | S7: 0.002515093 | T7: 0.0096753012 | U7: 0.0026793296 | V7: 0.0092179986 | W7: 0.0033274124 | X7: 0.0039268848 | Y7: 0.0048224972 | Z7: 0.0067705187 | AA7: 0.004583432 | AB7: 0.0030763577 | AC7: 0.0077953113 | AD7: 0.0047618057 | AE7: 0.0054954575 | AF7: 0.00078912109 | AG7: 0.0029232126 | AH7: 0.0034051386 | AK7: NSC-US | AL7: 0.0088481047 | AM7: 0.0022294191 | AN7: 0.002922206 | AO7: 0.0030792482 | AP7: 0.0020747788 | AQ7: 0.0069892948 | AR7: 0.0048831608 | AS7: 0.0047887825 | AT7: 0.0089853771 | AU7: 0.002515093 | AV7: 0.0096753012 | AW7: 0.0026793296 | AX7: 0.0092179986 | AY7: 0.0033274124 | AZ7: 0.0039268848 | BA7: 0.0048224972 | BB7: 0.0067705187 | BC7: 0.004583432 | BD7: 0.0030763577 | BE7: 0.0077953113 | BF7: 0.0047618057 | BG7: 0.0054954575 | BH7: 0.00078912109 | BI7: 0.0029232126 | BJ7: 0.0034051386 | BK7: 0
A8: FQVTF-US | B8: -0.005732217 | C8: =(1+B8)^12-1 -> -0.066658863 | D8: 0.14480171 | E8: =D8*SQRT(12) -> 0.50160785 | F8: =C8/E8 -> -0.13289039 | I8: FQVTF-US | J8: 0.012994327 | K8: 0.00026800862 | L8: 0.003582265 | M8: 0.004610109 | N8: 0.0042911351 | O8: 0.0048831608 | P8: 0.020612155 | Q8: 0.0046752626 | R8: 0.011828396 | S8: 0.0023816561 | T8: 0.014033311 | U8: 0.0025353801 | V8: 0.004157569 | W8: 0.004220192 | X8: 0.0051257368 | Y8: 0.0063569834 | Z8: 0.0062422502 | AA8: 0.0057614184 | AB8: 0.0057672907 | AC8: 0.010277988 | AD8: 0.0073065846 | AE8: 0.0045145315 | AF8: 0.0016897687 | AG8: 0.0023289228 | AH8: 0.0010248641 | AK8: FQVTF-US | AL8: 0.012994327 | AM8: 0.00026800862 | AN8: 0.003582265 | AO8: 0.004610109 | AP8: 0.0042911351 | AQ8: 0.0048831608 | AR8: 0.020612155 | AS8: 0.0046752626 | AT8: 0.011828396 | AU8: 0.0023816561 | AV8: 0.014033311 | AW8: 0.0025353801 | AX8: 0.004157569 | AY8: 0.004220192 | AZ8: 0.0051257368 | BA8: 0.0063569834 | BB8: 0.0062422502 | BC8: 0.0057614184 | BD8: 0.0057672907 | BE8: 0.010277988 | BF8: 0.0073065846 | BG8: 0.0045145315 | BH8: 0.0016897687 | BI8: 0.0023289228 | BJ8: 0.0010248641 | BK8: 0
A9: CRAI-US | B9: 0.020965098 | C9: =(1+B9)^12-1 -> 0.2827167 | D9: 0.11224067 | E9: =D9*SQRT(12) -> 0.38881309 | F9: =C9/E9 -> 0.72712752 | I9: CRAI-US | J9: 0.010077586 | K9: 0.004656476 | L9: 0.0022665502 | M9: 0.0037354987 | N9: 0.0027541769 | O9: 0.0047887825 | P9: 0.0046752626 | Q9: 0.012384443 | R9: 0.0081479498 | S9: 0.0039271042 | T9: 0.012079287 | U9: 0.0025238288 | V9: 0.0069448793 | W9: 0.0015785184 | X9: 0.0031206749 | Y9: 0.0034732014 | Z9: 0.0049092215 | AA9: 0.002832354 | AB9: 0.0031359024 | AC9: 0.010589366 | AD9: 0.0066133679 | AE9: 0.0051088584 | AF9: 0.0016013315 | AG9: 0.001783629 | AH9: 0.0034601296 | AK9: CRAI-US | AL9: 0.010077586 | AM9: 0.004656476 | AN9: 0.0022665502 | AO9: 0.0037354987 | AP9: 0.0027541769 | AQ9: 0.0047887825 | AR9: 0.0046752626 | AS9: 0.012384443 | AT9: 0.0081479498 | AU9: 0.0039271042 | AV9: 0.012079287 | AW9: 0.0025238288 | AX9: 0.0069448793 | AY9: 0.0015785184 | AZ9: 0.0031206749 | BA9: 0.0034732014 | BB9: 0.0049092215 | BC9: 0.002832354 | BD9: 0.0031359024 | BE9: 0.010589366 | BF9: 0.0066133679 | BG9: 0.0051088584 | BH9: 0.0016013315 | BI9: 0.001783629 | BJ9: 0.0034601296 | BK9: 0
A10: CHEF-US | B10: 0.016838104 | C10: =(1+B10)^12-1 -> 0.22186084 | D10: 0.18231644 | E10: =D10*SQRT(12) -> 0.63156269 | F10: =C10/E10 -> 0.35128871 | I10: CHEF-US | J10: 0.024061877 | K10: 0.0053679982 | L10: 0.0083240735 | M10: 0.0037434039 | N10: 0.0027556205 | O10: 0.0089853771 | P10: 0.011828396 | Q10: 0.0081479498 | R10: 0.032675908 | S10: 0.003440605 | T10: 0.026838926 | U10: 0.0043544896 | V10: 0.015418791 | W10: 0.0028977067 | X10: 0.0057545426 | Y10: 0.0068461537 | Z10: 0.010101924 | AA10: 0.004844845 | AB10: 0.0066744662 | AC10: 0.019221534 | AD10: 0.0075437952 | AE10: 0.010761991 | AF10: 0.0034833721 | AG10: 0.0064779871 | AH10: 0.013204795 | AK10: CHEF-US | AL10: 0.024061877 | AM10: 0.0053679982 | AN10: 0.0083240735 | AO10: 0.0037434039 | AP10: 0.0027556205 | AQ10: 0.0089853771 | AR10: 0.011828396 | AS10: 0.0081479498 | AT10: 0.032675908 | AU10: 0.003440605 | AV10: 0.026838926 | AW10: 0.0043544896 | AX10: 0.015418791 | AY10: 0.0028977067 | AZ10: 0.0057545426 | BA10: 0.0068461537 | BB10: 0.010101924 | BC10: 0.004844845 | BD10: 0.0066744662 | BE10: 0.019221534 | BF10: 0.0075437952 | BG10: 0.010761991 | BH10: 0.0034833721 | BI10: 0.0064779871 | BJ10: 0.013204795 | BK10: 0
A11: SCGPY-US | B11: 0.0092466204 | C11: =(1+B11)^12-1 -> 0.11678005 | D11: 0.081368392 | E11: =D11*SQRT(12) -> 0.28186838 | F11: =C11/E11 -> 0.41430701 | I11: SCGPY-US | J11: 0.0038519926 | K11: 0.0022777146 | L11: 0.0023042352 | M11: 0.0022955111 | N11: 0.001603088 | O11: 0.002515093 | P11: 0.0023816561 | Q11: 0.0039271042 | R11: 0.003440605 | S11: 0.006508598 | T11: 0.0059184646 | U11: 0.0023461501 | V11: 0.0027880619 | W11: 0.0014101692 | X11: 0.0026104449 | Y11: 0.002177014 | Z11: 0.0036718775 | AA11: 0.003754943 | AB11: 0.0022680044 | AC11: 0.0055210824 | AD11: 0.0030077933 | AE11: 0.0031729489 | AF11: 0.00013481829 | AG11: 0.0019015094 | AH11: 0.0021173443 | AK11: SCGPY-US | AL11: 0.0038519926 | AM11: 0.0022777146 | AN11: 0.0023042352 | AO11: 0.0022955111 | AP11: 0.001603088 | AQ11: 0.002515093 | AR11: 0.0023816561 | AS11: 0.0039271042 | AT11: 0.003440605 | AU11: 0.006508598 | AV11: 0.0059184646 | AW11: 0.0023461501 | AX11: 0.0027880619 | AY11: 0.0014101692 | AZ11: 0.0026104449 | BA11: 0.002177014 | BB11: 0.0036718775 | BC11: 0.003754943 | BD11: 0.0022680044 | BE11: 0.0055210824 | BF11: 0.0030077933 | BG11: 0.0031729489 | BH11: 0.00013481829 | BI11: 0.0019015094 | BJ11: 0.0021173443 | BK11: 0
A12: KOS-US | B12: 0.034084137 | C12: =(1+B12)^12-1 -> 0.49510093 | D12: 0.23944213 | E12: =D12*SQRT(12) -> 0.82945188 | F12: =C12/E12 -> 0.59690133 | I12: KOS-US | J12: 0.035433203 | K12: 0.0039407337 | L12: 0.011570476 | M12: 0.0010860295 | N12: 0.0050910416 | O12: 0.0096753012 | P12: 0.014033311 | Q12: 0.012079287 | R12: 0.026838926 | S12: 0.0059184646 | T12: 0.056360797 | U12: 0.0043066283 | V12: 0.016846983 | W12: 0.0048794764 | X12: 0.0054362438 | Y12: 0.0073739175 | Z12: 0.013808574 | AA12: 0.0084568807 | AB12: 0.0085538427 | AC12: 0.034104746 | AD12: 0.0094566205 | AE12: 0.010841395 | AF12: 0.0020344919 | AG12: 0.011273034 | AH12: 0.015021705 | AK12: KOS-US | AL12: 0.035433203 | AM12: 0.0039407337 | AN12: 0.011570476 | AO12: 0.0010860295 | AP12: 0.0050910416 | AQ12: 0.0096753012 | AR12: 0.014033311 | AS12: 0.012079287 | AT12: 0.026838926 | AU12: 0.0059184646 | AV12: 0.056360797 | AW12: 0.0043066283 | AX12: 0.016846983 | AY12: 0.0048794764 | AZ12: 0.0054362438 | BA12: 0.0073739175 | BB12: 0.013808574 | BC12: 0.0084568807 | BD12: 0.0085538427 | BE12: 0.034104746 | BF12: 0.0094566205 | BG12: 0.010841395 | BH12: 0.0020344919 | BI12: 0.011273034 | BJ12: 0.015021705 | BK12: 0
A13: DIISY-US | B13: -0.0055428915 | C13: =(1+B13)^12-1 -> -0.06452394 | D13: 0.10517382 | E13: =D13*SQRT(12) -> 0.36433279 | F13: =C13/E13 -> -0.17710166 | I13: DIISY-US | J13: 0.0087047485 | K13: 0.0018122104 | L13: 0.0016077751 | M13: 0.0026352619 | N13: 0.0017550462 | O13: 0.0026793296 | P13: 0.0025353801 | Q13: 0.0025238288 | R13: 0.0043544896 | S13: 0.0023461501 | T13: 0.0043066283 | U13: 0.010874048 | V13: 0.00064396828 | W13: -0.00095636221 | X13: 0.0011699617 | Y13: 0.0015124878 | Z13: 0.00077158976 | AA13: 0.0023841674 | AB13: 0.0028343127 | AC13: 0.0071080052 | AD13: 0.0046304076 | AE13: 0.002521294 | AF13: 0.0016534377 | AG13: 0.00078340853 | AH13: 0.0027336201 | AK13: DIISY-US | AL13: 0.0087047485 | AM13: 0.0018122104 | AN13: 0.0016077751 | AO13: 0.0026352619 | AP13: 0.0017550462 | AQ13: 0.0026793296 | AR13: 0.0025353801 | AS13: 0.0025238288 | AT13: 0.0043544896 | AU13: 0.0023461501 | AV13: 0.0043066283 | AW13: 0.010874048 | AX13: 0.00064396828 | AY13: -0.00095636221 | AZ13: 0.0011699617 | BA13: 0.0015124878 | BB13: 0.00077158976 | BC13: 0.0023841674 | BD13: 0.0028343127 | BE13: 0.0071080052 | BF13: 0.0046304076 | BG13: 0.002521294 | BH13: 0.0016534377 | BI13: 0.00078340853 | BJ13: 0.0027336201 | BK13: 0
A14: TSLA-US | B14: 0.064784255 | C14: =(1+B14)^12-1 -> 1.1239263 | D14: 0.22258853 | E14: =D14*SQRT(12) -> 0.77106928 | F14: =C14/E14 -> 1.4576204 | I14: TSLA-US | J14: 0.014887228 | K14: 0.00035397248 | L14: 0.0056992947 | M14: 0.0053130724 | N14: 0.00020863675 | O14: 0.0092179986 | P14: 0.004157569 | Q14: 0.0069448793 | R14: 0.015418791 | S14: 0.0027880619 | T14: 0.016846983 | U14: 0.00064396828 | V14: 0.048705896 | W14: 0.013085234 | X14: 0.013370933 | Y14: 0.0080423763 | Z14: 0.0099998117 | AA14: 0.0091723047 | AB14: 0.0035714544 | AC14: 0.011915572 | AD14: 0.0056259722 | AE14: 0.0079158246 | AF14: 0.0031671031 | AG14: 0.0059120138 | AH14: 0.0040635801 | AK14: TSLA-US | AL14: 0.014887228 | AM14: 0.00035397248 | AN14: 0.0056992947 | AO14: 0.0053130724 | AP14: 0.00020863675 | AQ14: 0.0092179986 | AR14: 0.004157569 | AS14: 0.0069448793 | AT14: 0.015418791 | AU14: 0.0027880619 | AV14: 0.016846983 | AW14: 0.00064396828 | AX14: 0.048705896 | AY14: 0.013085234 | AZ14: 0.013370933 | BA14: 0.0080423763 | BB14: 0.0099998117 | BC14: 0.0091723047 | BD14: 0.0035714544 | BE14: 0.011915572 | BF14: 0.0056259722 | BG14: 0.0079158246 | BH14: 0.0031671031 | BI14: 0.0059120138 | BJ14: 0.0040635801 | BK14: 0
... A26: AGYS-US | B26: 0.037916563 | C26: =(1+B26)^12-1 -> 0.5629652 | D26: 0.15099219 | E26: =D26*SQRT(12) -> 0.52305229 | F26: =C26/E26 -> 1.0763077 | I26: AGYS-US | J26: 0.01806266 | K26: 0.001204312 | L26: 0.0023542444 | M26: 0.00076433231 | N26: 0.00058423177 | O26: 0.0034051386 | P26: 0.0010248641 | Q26: 0.0034601296 | R26: 0.013204795 | S26: 0.0021173443 | T26: 0.015021705 | U26: 0.0027336201 | V26: 0.0040635801 | W26: 0.00036649443 | X26: 0.00041121884 | Y26: 0.0013138452 | Z26: 0.0012527121 | AA26: 1.6617844e-05 | AB26: 0.0031976353 | AC26: 0.010249675 | AD26: 0.0029219199 | AE26: 0.0082185891 | AF26: 7.3083542e-05 | AG26: 0.004938378 | AH26: 0.022412224 | AK26: AGYS-US | AL26: 0.01806266 | AM26: 0.001204312 | AN26: 0.0023542444 | AO26: 0.00076433231 | AP26: 0.00058423177 | AQ26: 0.0034051386 | AR26: 0.0010248641 | AS26: 0.0034601296 | AT26: 0.013204795 | AU26: 0.0021173443 | AV26: 0.015021705 | AW26: 0.0027336201 | AX26: 0.0040635801 | AY26: 0.00036649443 | AZ26: 0.00041121884 | BA26: 0.0013138452 | BB26: 0.0012527121 | BC26: 1.6617844e-05 | BD26: 0.0031976353 | BE26: 0.010249675 | BF26: 0.0029219199 | BG26: 0.0082185891 | BH26: 7.3083542e-05 | BI26: 0.004938378 | BJ26: 0.022412224 | BK26: 0
AK27: 10 & 20 year bond | AL27: 0 | AM27: 0 | AN27: 0 | AO27: 0 | AP27: 0 | AQ27: 0 | AR27: 0 | AS27: 0 | AT27: 0 | AU27: 0 | AV27: 0 | AW27: 0 | AX27: 0 | AY27: 0 | AZ27: 0 | BA27: 0 | BB27: 0 | BC27: 0 | BD27: 0 | BE27: 0 | BF27: 0 | BG27: 0 | BH27: 0 | BI27: 0 | BJ27: 0 | BK27: 0
A28: PORTFOLIOS | J28: HELPER COLUNMS
B29: PORTFOLIO 1 (EQUAL WEIGHTS) | C29: PORTFOLIO 2 (SHARPE RATIO WEIGHTED) | D29: PORTFOLIO 3 (MAX SHARPE RATIO) | E29: PORTFOLIO 4 (HIGHER RISK PORTFOLIO LREVERAGED WITH BONDS) | F29: PORTFOLIO 5 (LOWER RISK LEVERAGED WITH 20 YR BOND) | J29: PORTFOLIO 2 | L29: PORTFOLIO 3 | N29: PORTFOLIO 4 | R29: PORTFOLIO 5
A30: Constraining Variable | B30: NONE | C30: HIGHER SR | E30: HIGHER ST. DEV | F30: LOWER ST. DEV | J30: POSITIVE SR | K30: PRPORTIONAL | L30: ASSUMPTIONS | N30: unscaled stocks | R30: unscaled stocks
A31: Value of Constraint | B31: N/A | E31: st.dev >D63 | F31: st. dev< D63 | K31: WEIGHTS | L31: TICKER | M31: SHARPRE RATIO | N31: from portfolio 3 | O31: v=Σ×w | R31: from portfolio 3 | S31: v=Σ×w
A32: VFF-US | B32: =1/25 -> 0.04 | C32: =K32 -> 0 | D32: 0 | E32: =N32*$Q$33 -> 0 | F32: =R32*$U$33 -> 0 | J32: =IF(F2>0,F2,0) -> 0 | K32: =J32/SUM($J$32:$J$56) -> 0 | L32: SMCI-US | M32: 1.6786307 | N32: =D32 -> 0 | O32: {=MMULT(AL2:BK27, E32:E57)} -> 0.015196264 | P32: RETURN OF 10 YR BOND | Q32: 0.0405 | R32: =D32 -> 0 | S32: {=MMULT(AL2:BK27, F32:F57)} -> 0.0084423686 | T32: RETURN OF 20 YR BOND | U32: 0.0436
A33: FENC-US | B33: =1/25 -> 0.04 | C33: =K33 -> 0.042617048 | D33: 0.10258487 | E33: =N33*$Q$33 -> 0.13848957 | F33: =R33*$U$33 -> 0.07693865 | J33: =IF(F3>0,F3,0) -> 0.55356297 | K33: =J33/SUM($J$32:$J$56) -> 0.042617048 | L33: TSLA-US | M33: 1.4576204 | N33: =D33 -> 0.10258487 | O33: 0.0034775847 | P33: TOTAL WEIGHT OF STOCK PORTFOLIO | Q33: 1.35 | R33: =D33 -> 0.10258487 | S33: 0.0019319915 | T33: TOTAL WEIGHT OF STOCK PORTFOLIO | U33: 0.75
A34: BDOUY-US | B34: =1/25 -> 0.04 | C34: =K34 -> 0.006611393 | D34: 0.01 | E34: =N34*$Q$33 -> 0.0135 | F34: =R34*$U$33 -> 0.0075 | J34: =IF(F4>0,F4,0) -> 0.085876956 | K34: =J34/SUM($J$32:$J$56) -> 0.006611393 | L34: AAPL-US | M34: 1.411256 | N34: =D34 -> 0.01 | O34: 0.0046190869 | P34: TOTAL WEIGHT OF BOND | Q34: -0.35 | R34: =D34 -> 0.01 | S34: 0.0025661594 | T34: TOTAL WEIGHT OF BOND | U34: 0.25
A35: SPMYY-US | B35: =1/25 -> 0.04 | C35: =K35 -> 0.0034831163 | D35: 0.01 | E35: =N35*$Q$33 -> 0.0135 | F35: =R35*$U$33 -> 0.0075 | J35: =IF(F5>0,F5,0) -> 0.045243026 | K35: =J35/SUM($J$32:$J$56) -> 0.0034831163 | L35: AVGO-US | M35: 1.2618496 | N35: =D35 -> 0.01 | O35: 0.0033280873 | P35: PORTFOLIO VARIANCE | Q35: {=MMULT(TRANSPOSE(E32:E57), O32:O57)} -> 0.016017754 | R35: =D35 -> 0.01 | S35: 0.0018489374 | T35: PORTFOLIO VARIANCE | U35: {=MMULT(TRANSPOSE(F32:F57), S32:S57)} -> 0.0049437511
A36: AHCHY-US | B36: =1/25 -> 0.04 | C36: =K36 -> 0 | D36: 0 | E36: =N36*$Q$33 -> 0 | F36: =R36*$U$33 -> 0 | J36: =IF(F6>0,F6,0) -> 0 | K36: =J36/SUM($J$32:$J$56) -> 0 | L36: AGYS-US | M36: 1.0763077 | N36: =D36 -> 0 | O36: 0.0012870206 | R36: =D36 -> 0 | S36: 0.00071501145
A37: NSC-US | B37: =1/25 -> 0.04 | C37: =K37 -> 0.030970411 | D37: 0.1 | E37: =N37*$Q$33 -> 0.135 | F37: =R37*$U$33 -> 0.075 | J37: =IF(F7>0,F7,0) -> 0.40228204 | K37: =J37/SUM($J$32:$J$56) -> 0.030970411 | L37: CRAI-US | M37: 0.72712752 | N37: =D37 -> 0.1 | O37: 0.006893369 | R37: =D37 -> 0.1 | S37: 0.0038296494
A38: FQVTF-US | B38: =1/25 -> 0.04 | C38: =K38 -> 0 | D38: 0 | E38: =N38*$Q$33 -> 0 | F38: =R38*$U$33 -> 0 | J38: =IF(F8>0,F8,0) -> 0 | K38: =J38/SUM($J$32:$J$56) -> 0 | L38: BIRDF-US | M38: 0.7194728 | N38: =D38 -> 0 | O38: 0.0053843783 | R38: =D38 -> 0 | S38: 0.0029913213
A39: CRAI-US | B39: =1/25 -> 0.04 | C39: =K39 -> 0.055979229 | D39: 0.01 | E39: =N39*$Q$33 -> 0.0135 | F39: =R39*$U$33 -> 0.0075 | J39: =IF(F9>0,F9,0) -> 0.72712752 | K39: =J39/SUM($J$32:$J$56) -> 0.055979229 | L39: KOS-US | M39: 0.59690133 | N39: =D39 -> 0.01 | O39: 0.0059087642 | R39: =D39 -> 0.01 | S39: 0.0032826468
A40: CHEF-US | B40: =1/25 -> 0.04 | C40: =K40 -> 0.027044598 | D40: 0.01 | E40: =N40*$Q$33 -> 0.0135 | F40: =R40*$U$33 -> 0.0075 | J40: =IF(F10>0,F10,0) -> 0.35128871 | K40: =J40/SUM($J$32:$J$56) -> 0.027044598 | L40: FENC-US | M40: 0.55356297 | N40: =D40 -> 0.01 | O40: 0.012739395 | R40: =D40 -> 0.01 | S40: 0.0070774415
A41: SCGPY-US | B41: =1/25 -> 0.04 | C41: =K41 -> 0.031896176 | D41: 0.01 | E41: =N41*$Q$33 -> 0.0135 | F41: =R41*$U$33 -> 0.0075 | J41: =IF(F11>0,F11,0) -> 0.41430701 | K41: =J41/SUM($J$32:$J$56) -> 0.031896176 | L41: AMZN-US | M41: 0.55326733 | N41: =D41 -> 0.01 | O41: 0.0039513313 | R41: =D41 -> 0.01 | S41: 0.002195184
A42: KOS-US | B42: =1/25 -> 0.04 | C42: =K42 -> 0.04595353 | D42: 0.01 | E42: =N42*$Q$33 -> 0.0135 | F42: =R42*$U$33 -> 0.0075 | J42: =IF(F12>0,F12,0) -> 0.59690133 | K42: =J42/SUM($J$32:$J$56) -> 0.04595353 | L42: EPRT-US | M42: 0.50795874 | N42: =D42 -> 0.01 | O42: 0.015584792 | R42: =D42 -> 0.01 | S42: 0.0086582175
A43: DIISY-US | B43: =1/25 -> 0.04 | C43: =K43 -> 0 | D43: 0 | E43: =N43*$Q$33 -> 0 | F43: =R43*$U$33 -> 0 | J43: =IF(F13>0,F13,0) -> 0 | K43: =J43/SUM($J$32:$J$56) -> 0 | L43: HAL-US | M43: 0.41746139 | N43: =D43 -> 0 | O43: 0.0029531692 | R43: =D43 -> 0 | S43: 0.0016406495
A44: TSLA-US | B44: =1/25 -> 0.04 | C44: =K44 -> 0.11221755 | D44: 0.1546201 | E44: =N44*$Q$33 -> 0.20873713 | F44: =R44*$U$33 -> 0.11596507 | J44: =IF(F14>0,F14,0) -> 1.4576204 | K44: =J44/SUM($J$32:$J$56) -> 0.11221755 | L44: SCGPY-US | M44: 0.41430701 | N44: =D44 -> 0.1546201 | O44: 0.01795107 | R44: =D44 -> 0.1546201 | S44: 0.0099728167
A45: AMZN-US | B45: =1/25 -> 0.04 | C45: =K45 -> 0.042594287 | D45: 0.01 | E45: =N45*$Q$33 -> 0.0135 | F45: =R45*$U$33 -> 0.0075 | J45: =IF(F15>0,F15,0) -> 0.55326733 | K45: =J45/SUM($J$32:$J$56) -> 0.042594287 | L45: F-US | M45: 0.40419554 | N45: =D45 -> 0.01 | O45: 0.0054448696 | R45: =D45 -> 0.01 | S45: 0.0030249275
A46: AAPL-US | B46: =1/25 -> 0.04 | C46: =K46 -> 0.1086481 | D46: 0.01 | E46: =N46*$Q$33 -> 0.0135 | F46: =R46*$U$33 -> 0.0075 | J46: =IF(F16>0,F16,0) -> 1.411256 | K46: =J46/SUM($J$32:$J$56) -> 0.1086481 | L46: NSC-US | M46: 0.40228204 | N46: =D46 -> 0.01 | O46: 0.0060111087 | R46: =D46 -> 0.01 | S46: 0.0033395048
A47: AVGO-US | B47: =1/25 -> 0.04 | C47: =K47 -> 0.097145777 | D47: 0.01 | E47: =N47*$Q$33 -> 0.0135 | F47: =R47*$U$33 -> 0.0075 | J47: =IF(F17>0,F17,0) -> 1.2618496 | K47: =J47/SUM($J$32:$J$56) -> 0.097145777 | L47: CHEF-US | M47: 0.35128871 | N47: =D47 -> 0.01 | O47: 0.0076491348 | R47: =D47 -> 0.01 | S47: 0.0042495194
... A56: AGYS-US | B56: =1/25 -> 0.04 | C56: =K56 -> 0.082861497 | D56: 0.19751752 | E56: =N56*$Q$33 -> 0.26664866 | F56: =R56*$U$33 -> 0.14813814 | J56: =IF(F26>0,F26,0) -> 1.0763077 | K56: =J56/SUM($J$32:$J$56) -> 0.082861497 | L56: AHCHY-US | M56: -0.31827944 | N56: =D56 -> 0.19751752 | O56: 0.0083340365 | R56: =D56 -> 0.19751752 | S56: 0.0046300203
A57: 10-yr boond | E57: -0.35 | F57: 0.25 | O57: 0 | S57: 0
A58: SUM W | B58: =SUM(B32:B56) -> 1 | C58: =SUM(C32:C56) -> 1 | D58: =SUM(D32:D56) -> 1.000001 | E58: =SUM(E32:E57) -> 1.0000013 | F58: =SUM(F32:F57) -> 1.0000007 | L58: =SUM(L32:L56) -> 0 | N58: =SUM(N32:N56) -> 1.000001
A59: Mean portfolio return (Monthly) | B59: {=MMULT(TRANSPOSE($B$2:$B$26),B32:B56)} -> 0.01613206 | C59: {=MMULT(TRANSPOSE($B$2:$B$26),C32:C56)} -> 0.032987983 | D59: {=MMULT(TRANSPOSE($B$2:$B$26),D32:D56)} -> 0.042148738 | E59: {=Q33*(MMULT(TRANSPOSE($B$2:$B$26),E32:E56))+(Q34*Q32)} -> 0.062641074 | F59: {=U33*(MMULT(TRANSPOSE($B$2:$B$26),F32:F56))+(U34*U32)} -> 0.034608665
A60: Mean portfolio return (Annual) | B60: {=MMULT(TRANSPOSE($C$2:$C$26),B32:B56)} -> 0.24238207 | C60: {=MMULT(TRANSPOSE($C$2:$C$26),C32:C56)} -> 0.51397743 | D60: {=MMULT(TRANSPOSE($C$2:$C$26),D32:D56)} -> 0.69208716 | E60: {=Q33*(MMULT(TRANSPOSE($C$2:$C$26),E32:E56))+(Q34*Q32)} -> 1.2471538 | F60: {=U33*(MMULT(TRANSPOSE($C$2:$C$26),F32:F56))+(U34*U32)} -> 0.40019903
A61: Std Deviation Portfolio (Monthly) | B61: {=SQRT(MMULT(MMULT(TRANSPOSE(B32:B56),$J$2:$AH$26),B32:B56))} -> 0.074326772 | C61: {=SQRT(MMULT(MMULT(TRANSPOSE(C32:C56),$J$2:$AH$26),C32:C56))} -> 0.084088147 | D61: {=SQRT(MMULT(MMULT(TRANSPOSE(D32:D56),$J$2:$AH$26),D32:D56))} -> 0.093749085 | E61: {=SQRT(MMULT(MMULT(TRANSPOSE(E32:E57),$AL$2:$BK$27),E32:E57))} -> 0.12656126 | F61: {=SQRT(MMULT(MMULT(TRANSPOSE(F32:F57),$AL$2:$BK$27),F32:F57))} -> 0.070311813
A62: Std Deviation Portfolio Annual) | B62: =B61*SQRT(12) -> 0.25747549 | C62: =C61*SQRT(12) -> 0.29128988 | D62: =D61*SQRT(12) -> 0.32475636 | E62: =E61*SQRT(12) -> 0.43842108 | F62: =F61*SQRT(12) -> 0.24356727
A63: Mean/Std Dev | B63: =B60/B62 -> 0.94137919 | C63: =C60/C62 -> 1.7644877 | D63: =D60/D62 -> 2.1310966 | E63: =E60/E62 -> 2.8446485 | F63: =F60/F62 -> 1.6430739

Sheet Question 1 - Dollar Investment
A1: PORTFOLIO 1 = $5MILLION | G1: PORTFOLIO 2 = $5MILLION | M1: PORTFOLIO 3 = $5MILLION | S1: PORTFOLIO 4 = $5MILLION | Y1: PORTFOLIO 4 = $5MILLION
A2: STOCK | B2: WEIGHT | C2: VALUE INVESTED IN 25 STOCKS | D2: CURRENT SHARE PRICE @ DEC 2023 | E2: SHARES BOUGHT /SOLD | G2: STOCK | H2: WEIGHT | I2: VALUE INVESTED IN 25 STOCKS | J2: CURRENT SHARE PRICE @ DEC 2023 | K2: SHARES BOUGHT /SOLD | M2: STOCK | N2: WEIGHT | O2: VALUE INVESTED IN STOCKS | P2: CURRENT SHARE PRICE @ DEC 2023 | Q2: SHARES BOUGHT /SOLD | S2: STOCK | T2: WEIGHT | U2: VALUE INVESTED IN STOCKS AND 10 YEAR BOND | V2: CURRENT SHARE PRICE @ DEC 2023 | W2: SHARES BOUGHT /SOLD | Y2: STOCK | Z2: WEIGHT | AA2: VALUE INVESTED IN STOCKS AND 20 YEAR BOND | AB2: CURRENT SHARE PRICE @ DEC 2023 | AC2: SHARES BOUGHT /SOLD
A3: VFF-US | B3: =1/25 -> 0.04 | C3: =B3*5000000 -> 200000 | D3: 0.761 | E3: =C3/D3 -> 262812.09 | G3: VFF-US | H3: 0 | I3: =H3*5000000 -> 0 | J3: 0.761 | K3: =I3/J3 -> 0 | M3: VFF-US | N3: 0 | O3: =N3*5000000 -> 0 | P3: 0.761 | Q3: =O3/P3 -> 0 | S3: VFF-US | T3: 0 | U3: =T3*5000000 -> 0 | V3: 0.761 | W3: =U3/V3 -> 0 | Y3: VFF-US | Z3: 0 | AA3: =Z3*5000000 -> 0 | AB3: 0.761 | AC3: =AA3/AB3 -> 0
A4: FENC-US | B4: =1/25 -> 0.04 | C4: =B4*5000000 -> 200000 | D4: 11.22 | E4: =C4/D4 -> 17825.312 | G4: FENC-US | H4: 0.042617048 | I4: =H4*5000000 -> 213085.24 | J4: 11.22 | K4: =I4/J4 -> 18991.554 | M4: FENC-US | N4: 0.10258487 | O4: =N4*5000000 -> 512924.33 | P4: 11.22 | Q4: =O4/P4 -> 45715.181 | S4: FENC-US | T4: 0.13848957 | U4: =T4*5000000 -> 692447.85 | V4: 11.22 | W4: =U4/V4 -> 61715.495 | Y4: FENC-US | Z4: 0.07693865 | AA4: =Z4*5000000 -> 384693.25 | AB4: 11.22 | AC4: =AA4/AB4 -> 34286.386
A5: BDOUY-US | B5: =1/25 -> 0.04 | C5: =B5*5000000 -> 200000 | D5: 23.567 | E5: =C5/D5 -> 8486.4429 | G5: BDOUY-US | H5: 0.006611393 | I5: =H5*5000000 -> 33056.965 | J5: 23.567 | K5: =I5/J5 -> 1402.6802 | M5: BDOUY-US | N5: 0.01 | O5: =N5*5000000 -> 50000 | P5: 23.567 | Q5: =O5/P5 -> 2121.6107 | S5: BDOUY-US | T5: 0.0135 | U5: =T5*5000000 -> 67500 | V5: 23.567 | W5: =U5/V5 -> 2864.1745 | Y5: BDOUY-US | Z5: 0.0075 | AA5: =Z5*5000000 -> 37500 | AB5: 23.567 | AC5: =AA5/AB5 -> 1591.208
A6: SPMYY-US | B6: =1/25 -> 0.04 | C6: =B6*5000000 -> 200000 | D6: 6.4 | E6: =C6/D6 -> 31250 | G6: SPMYY-US | H6: 0.0034831163 | I6: =H6*5000000 -> 17415.581 | J6: 6.4 | K6: =I6/J6 -> 2721.1846 | M6: SPMYY-US | N6: 0.01 | O6: =N6*5000000 -> 50000 | P6: 6.4 | Q6: =O6/P6 -> 7812.5 | S6: SPMYY-US | T6: 0.0135 | U6: =T6*5000000 -> 67500 | V6: 6.4 | W6: =U6/V6 -> 10546.875 | Y6: SPMYY-US | Z6: 0.0075 | AA6: =Z6*5000000 -> 37500 | AB6: 6.4 | AC6: =AA6/AB6 -> 5859.375
A7: AHCHY-US | B7: =1/25 -> 0.04 | C7: =B7*5000000 -> 200000 | D7: 11.551 | E7: =C7/D7 -> 17314.518 | G7: AHCHY-US | H7: 0 | I7: =H7*5000000 -> 0 | J7: 11.551 | K7: =I7/J7 -> 0 | M7: AHCHY-US | N7: 0 | O7: =N7*5000000 -> 0 | P7: 11.551 | Q7: =O7/P7 -> 0 | S7: AHCHY-US | T7: 0 | U7: =T7*5000000 -> 0 | V7: 11.551 | W7: =U7/V7 -> 0 | Y7: AHCHY-US | Z7: 0 | AA7: =Z7*5000000 -> 0 | AB7: 11.551 | AC7: =AA7/AB7 -> 0
A8: NSC-US | B8: =1/25 -> 0.04 | C8: =B8*5000000 -> 200000 | D8: 236.38 | E8: =C8/D8 -> 846.09527 | G8: NSC-US | H8: 0.030970411 | I8: =H8*5000000 -> 154852.06 | J8: 236.38 | K8: =I8/J8 -> 655.09796 | M8: NSC-US | N8: 0.1 | O8: =N8*5000000 -> 500000 | P8: 236.38 | Q8: =O8/P8 -> 2115.2382 | S8: NSC-US | T8: 0.135 | U8: =T8*5000000 -> 675000 | V8: 236.38 | W8: =U8/V8 -> 2855.5715 | Y8: NSC-US | Z8: 0.075 | AA8: =Z8*5000000 -> 375000 | AB8: 236.38 | AC8: =AA8/AB8 -> 1586.4286
A9: FQVTF-US | B9: =1/25 -> 0.04 | C9: =B9*5000000 -> 200000 | D9: 13.455 | E9: =C9/D9 -> 14864.363 | G9: FQVTF-US | H9: 0 | I9: =H9*5000000 -> 0 | J9: 13.455 | K9: =I9/J9 -> 0 | M9: FQVTF-US | N9: 0 | O9: =N9*5000000 -> 0 | P9: 13.455 | Q9: =O9/P9 -> 0 | S9: FQVTF-US | T9: 0 | U9: =T9*5000000 -> 0 | V9: 13.455 | W9: =U9/V9 -> 0 | Y9: FQVTF-US | Z9: 0 | AA9: =Z9*5000000 -> 0 | AB9: 13.455 | AC9: =AA9/AB9 -> 0
A10: CRAI-US | B10: =1/25 -> 0.04 | C10: =B10*5000000 -> 200000 | D10: 98.85 | E10: =C10/D10 -> 2023.2676 | G10: CRAI-US | H10: 0.055979229 | I10: =H10*5000000 -> 279896.14 | J10: 98.85 | K10: =I10/J10 -> 2831.524 | M10: CRAI-US | N10: 0.01 | O10: =N10*5000000 -> 50000 | P10: 98.85 | Q10: =O10/P10 -> 505.81689 | S10: CRAI-US | T10: 0.0135 | U10: =T10*5000000 -> 67500 | V10: 98.85 | W10: =U10/V10 -> 682.85281 | Y10: CRAI-US | Z10: 0.0075 | AA10: =Z10*5000000 -> 37500 | AB10: 98.85 | AC10: =AA10/AB10 -> 379.36267
A11: CHEF-US | B11: =1/25 -> 0.04 | C11: =B11*5000000 -> 200000 | D11: 29.43 | E11: =C11/D11 -> 6795.7866 | G11: CHEF-US | H11: 0.027044598 | I11: =H11*5000000 -> 135222.99 | J11: 29.43 | K11: =I11/J11 -> 4594.7329 | M11: CHEF-US | N11: 0.01 | O11: =N11*5000000 -> 50000 | P11: 29.43 | Q11: =O11/P11 -> 1698.9467 | S11: CHEF-US | T11: 0.0135 | U11: =T11*5000000 -> 67500 | V11: 29.43 | W11: =U11/V11 -> 2293.578 | Y11: CHEF-US | Z11: 0.0075 | AA11: =Z11*5000000 -> 37500 | AB11: 29.43 | AC11: =AA11/AB11 -> 1274.21
A12: SCGPY-US | B12: =1/25 -> 0.04 | C12: =B12*5000000 -> 200000 | D12: 2.066 | E12: =C12/D12 -> 96805.421 | G12: SCGPY-US | H12: 0.031896176 | I12: =H12*5000000 -> 159480.88 | J12: 2.066 | K12: =I12/J12 -> 77193.068 | M12: SCGPY-US | N12: 0.01 | O12: =N12*5000000 -> 50000 | P12: 2.066 | Q12: =O12/P12 -> 24201.355 | S12: SCGPY-US | T12: 0.0135 | U12: =T12*5000000 -> 67500 | V12: 2.066 | W12: =U12/V12 -> 32671.83 | Y12: SCGPY-US | Z12: 0.0075 | AA12: =Z12*5000000 -> 37500 | AB12: 2.066 | AC12: =AA12/AB12 -> 18151.016
A13: KOS-US | B13: =1/25 -> 0.04 | C13: =B13*5000000 -> 200000 | D13: 6.71 | E13: =C13/D13 -> 29806.259 | G13: KOS-US | H13: 0.04595353 | I13: =H13*5000000 -> 229767.65 | J13: 6.71 | K13: =I13/J13 -> 34242.571 | M13: KOS-US | N13: 0.01 | O13: =N13*5000000 -> 50000 | P13: 6.71 | Q13: =O13/P13 -> 7451.5648 | S13: KOS-US | T13: 0.0135 | U13: =T13*5000000 -> 67500 | V13: 6.71 | W13: =U13/V13 -> 10059.613 | Y13: KOS-US | Z13: 0.0075 | AA13: =Z13*5000000 -> 37500 | AB13: 6.71 | AC13: =AA13/AB13 -> 5588.6736
A14: DIISY-US | B14: =1/25 -> 0.04 | C14: =B14*5000000 -> 200000 | D14: 9.278 | E14: =C14/D14 -> 21556.37 | G14: DIISY-US | H14: 0 | I14: =H14*5000000 -> 0 | J14: 9.278 | K14: =I14/J14 -> 0 | M14: DIISY-US | N14: 0 | O14: =N14*5000000 -> 0 | P14: 9.278 | Q14: =O14/P14 -> 0 | S14: DIISY-US | T14: 0 | U14: =T14*5000000 -> 0 | V14: 9.278 | W14: =U14/V14 -> 0 | Y14: DIISY-US | Z14: 0 | AA14: =Z14*5000000 -> 0 | AB14: 9.278 | AC14: =AA14/AB14 -> 0
... A27: AGYS-US | B27: =1/25 -> 0.04 | C27: =B27*5000000 -> 200000 | D27: 84.82 | E27: =C27/D27 -> 2357.9344 | G27: AGYS-US | H27: 0.082861497 | I27: =H27*5000000 -> 414307.49 | J27: 84.82 | K27: =I27/J27 -> 4884.5495 | M27: AGYS-US | N27: 0.19751752 | O27: =N27*5000000 -> 987587.62 | P27: 84.82 | Q27: =O27/P27 -> 11643.334 | S27: AGYS-US | T27: 0.26664866 | U27: =T27*5000000 -> 1333243.3 | V27: 84.82 | W27: =U27/V27 -> 15718.501 | Y27: AGYS-US | Z27: 0.14813814 | AA27: =Z27*5000000 -> 740690.72 | AB27: 84.82 | AC27: =AA27/AB27 -> 8732.5008
B28: =SUM(B3:B27) -> 1 | C28: =SUM(C3:C27) -> 5000000 | H28: =SUM(H3:H27) -> 1 | I28: =SUM(I3:I27) -> 5000000 | N28: =SUM(N3:N27) -> 1.000001 | O28: =SUM(O3:O27) -> 5000005 | S28: 10 YR BOND | T28: -0.35 | U28: =T28*5000000 -> -1750000 | V28: 100 | W28: =U28/V28 -> -17500 | Y28: 20 YR BOND | Z28: 0.25 | AA28: =Z28*5000000 -> 1250000 | AB28: 100 | AC28: =AA28/AB28 -> 12500
T29: =SUM(T3:T28) -> 1.0000013 | U29: =SUM(U3:U28) -> 5000006.7 | Z29: =SUM(Z3:Z28) -> 1.0000007 | AA29: =SUM(AA3:AA28) -> 5000003.7

Sheet Question1-JAN 2024 TIL DEC 2024
A1: PRICES | AC1: st.dev | AD1: annual stock return | AE1: annual sharpe ratio | AF1: st. dev of downside risk | AG1: average monthly return | AH1: sortino ratio
A2: DATE | B2: VFF-US | C2: FENC-US | D2: BDOUY-US | E2: SPMYY-US | F2: AHCHY-US | G2: NSC-US | H2: FQVTF-US | I2: CRAI-US | J2: CHEF-US | K2: SCGPY-US | L2: KOS-US | M2: DIISY-US | N2: TSLA-US | O2: AMZN-US | P2: AAPL-US | Q2: AVGO-US | R2: F-US | S2: SMCI-US | T2: CMCSA-US | U2: HAL-US | V2: BIRDF-US | W2: EPRT-US | X2: OTSKY-US | Y2: OHI-US | Z2: AGYS-US | AB2: VFF-US | AC2: 0.24501904 | AD2: =(1+$B30)^12-1 -> 0.17035396 | AE2: =AD2/AC2 -> 0.69526826 | AF2: 0.059747282 | AG2: 0.01319515 | AH2: =AG2/AF2 -> 0.22084938
A3: 45322 | B3: 0.85 | C3: 9.99 | D3: 25.757 | E3: 6.11 | F3: 10.029 | G3: 235.24 | H3: 12.915 | I3: 107.24 | J3: 31.82 | K3: 2.209 | L3: 6.06 | M3: 8.629 | N3: 187.29 | O3: 155.2 | P3: 184.4 | Q3: 118 | R3: 11.72 | S3: 52.961 | T3: 46.54 | U3: 35.65 | V3: 11.4 | W3: 24.91 | X3: 19.921 | Y3: 29 | Z3: 83.71 | AB3: FENC-US | AC3: 0.18371372 | AD3: =(1+C$30)^12-1 -> -0.27448888 | AE3: =AD3/AC3 -> -1.494112 | AF3: 0.073170081 | AG3: -0.02638556 | AH3: =AG3/AF3 -> -0.36060586
A4: 45351 | B4: 0.7525 | C4: 9.47 | D4: 27.217 | E4: 5.47 | F4: 10.934 | G4: 253.38 | H4: 14.77 | I4: 132.54 | J4: 38.01 | K4: 2.369 | L4: 6.14 | M4: 10.221 | N4: 201.88 | O4: 176.76 | P4: 180.75 | Q4: 130.049 | R4: 12.44 | S4: 86.612 | T4: 42.85 | U4: 35.07 | V4: 12.6 | W4: 23.89 | X4: 20.318 | Y4: 31.12 | Z4: 77.8 | AB4: BDOUY-US | AC4: 0.081001147 | AD4: =(1+D$30)^12-1 -> -0.001651809 | AE4: =AD4/AC4 -> -0.020392415 | AF4: 0.047130419 | AG4: -0.00013775507 | AH4: =AG4/AF4 -> -0.0029228484
A5: 45379 | B5: 1.24 | C5: 11.12 | D5: 27.484 | E5: 10.097 | F5: 10.401 | G5: 254.87 | H5: 15.38 | I5: 149.58 | J5: 37.66 | K5: 2.396 | L5: 5.96 | M5: 9.856 | N5: 175.79 | O5: 180.38 | P5: 171.48 | Q5: 132.541 | R5: 13.28 | S5: 101.00301 | T5: 43.35 | U5: 39.42 | V5: 13.765 | W5: 26.66 | X5: 20.718 | Y5: 31.67 | Z5: 84.26 | AB5: SPMYY-US | AC5: 0.26508099 | AD5: =(1+E$30)^12-1 -> 1.0414234 | AE5: =AD5/AC5 -> 3.928699 | AF5: 0.034404526 | AG5: 0.061274569 | AH5: =AG5/AF5 -> 1.7810031
A6: 45412 | B6: 1.53 | C6: 9.18 | D6: 25.654 | E6: 9.64 | F6: 11.673 | G6: 230.32 | H6: 14.005 | I6: 145.09 | J6: 33.08 | K6: 2.294 | L6: 5.67 | M6: 9.306 | N6: 183.28 | O6: 175 | P6: 170.33 | Q6: 130.02701 | R6: 12.15 | S6: 85.88 | T6: 38.11 | U6: 37.47 | V6: 13.85 | W6: 26.34 | X6: 21.422 | Y6: 30.41 | Z6: 83.05 | AB6: AHCHY-US | AC6: 0.13212584 | AD6: =(1+F$30)^12-1 -> 0.416124 | AE6: =AD6/AC6 -> 3.149452 | AF6: 0.040684012 | AG6: 0.029418037 | AH6: =AG6/AF6 -> 0.72308595
A7: 45443 | B7: 1.19 | C7: 6.78 | D7: 22.215 | E7: 9.3223 | F7: 12.36 | G7: 224.8 | H7: 13.625 | I7: 175.97 | J7: 39.42 | K7: 2.266 | L7: 6.1 | M7: 10.919 | N7: 178.08 | O7: 176.44 | P7: 192.25 | Q7: 132.85501 | R7: 12.13 | S7: 78.451004 | T7: 40.03 | U7: 36.7 | V7: 15.57 | W7: 26.78 | X7: 20.599 | Y7: 32.33 | Z7: 95.47 | AB7: NSC-US | AC7: 0.088500865 | AD7: =(1+G$30)^12-1 -> 0.04088109 | AE7: =AD7/AC7 -> 0.4619287 | AF7: 0.053170512 | AG7: 0.0033445436 | AH7: =AG7/AF7 -> 0.062902226
A8: 45471 | B8: 1.02 | C8: 6.11 | D8: 21.874 | E8: 8.8 | F8: 11.912 | G8: 214.69 | H8: 13.565 | I8: 172.22 | J8: 39.11 | K8: 2.272 | L8: 5.54 | M8: 10.153 | N8: 197.88 | O8: 193.25 | P8: 210.62 | Q8: 160.55301 | R8: 12.54 | S8: 81.935 | T8: 39.16 | U8: 33.78 | V8: 19.75 | W8: 27.71 | X8: 21.043 | Y8: 34.25 | Z8: 104.14 | AB8: FQVTF-US | AC8: 0.076368837 | AD8: =(1+H$30)^12-1 -> -0.34626334 | AE8: =AD8/AC8 -> -4.5340921 | AF8: 0.041850159 | AG8: -0.034800911 | AH8: =AG8/AF8 -> -0.83155985
A9: 45504 | B9: 1.135 | C9: 6.47 | D9: 23.469 | E9: 9 | F9: 12.212 | G9: 249.56 | H9: 12.02 | I9: 174.8 | J9: 41.59 | K9: 2.46 | L9: 5.53 | M9: 9.685 | N9: 232.07 | O9: 186.98 | P9: 222.08 | Q9: 160.68 | R9: 10.82 | S9: 70.165 | T9: 41.27 | U9: 34.68 | V9: 18.72 | W9: 29.59 | X9: 25.798 | Y9: 36.4 | Z9: 112.09 | AB9: CRAI-US | AC9: 0.097813006 | AD9: =(1+I$30)^12-1 -> 0.92072539 | AE9: =AD9/AC9 -> 9.4131182 | AF9: 0.0080898703 | AG9: 0.055898338 | AH9: =AG9/AF9 -> 6.9096705
A10: 45534 | B10: 1.03 | C10: 5.57 | D10: 27.213 | E10: 9.2 | F10: 10.82 | G10: 256.16 | H10: 11.605 | I10: 168.6 | J10: 42.83 | K10: 2.295 | L10: 4.87 | M10: 9.999 | N10: 214.11 | O10: 178.5 | P10: 229 | Q10: 162.82 | R10: 11.19 | S10: 43.77 | T10: 39.57 | U10: 31.09 | V10: 16.85 | W10: 31.91 | X10: 29.374 | Y10: 39.54 | Z10: 113.1 | AB10: CHEF-US | AC10: 0.10001165 | AD10: =(1+J$30)^12-1 -> 0.69575909 | AE10: =AD10/AC10 -> 6.9567804 | AF10: 0.1043727 | AG10: 0.044993717 | AH10: =AG10/AF10 -> 0.43108704
A11: 45565 | B11: 0.93 | C11: 5 | D11: 28.195 | E11: 9.19 | F11: 14.709 | G11: 248.5 | H11: 10.9 | I11: 175.32 | J11: 42.01 | K11: 2.388 | L11: 4.03 | M11: 10.049 | N11: 261.63 | O11: 186.33 | P11: 233 | Q11: 172.5 | R11: 10.56 | S11: 41.64 | T11: 41.77 | U11: 29.05 | V11: 17.84 | W11: 34.15 | X11: 28.254 | Y11: 40.7 | Z11: 108.97 | AB11: SCGPY-US | AC11: 0.061335133 | AD11: =(1+K$30)^12-1 -> -0.13603978 | AE11: =AD11/AC11 -> -2.2179748 | AF11: 0.035345283 | AG11: -0.012111768 | AH11: =AG11/AF11 -> -0.34266998
A12: 45596 | B12: 0.8767 | C12: 4.36 | D12: 26.295 | E12: 8.744 | F12: 14.535 | G12: 250.43 | H12: 9.535 | I12: 182.14 | J12: 39.92 | K12: 2.251 | L12: 3.76 | M12: 8.449 | N12: 249.85 | O12: 186.4 | P12: 225.91 | Q12: 169.77 | R12: 10.29 | S12: 29.11 | T12: 43.67 | U12: 27.74 | V12: 21.75 | W12: 31.69 | X12: 30.435 | Y12: 42.47 | Z12: 100.04 | AB12: KOS-US | AC12: 0.077894245 | AD12: =(1+L$30)^12-1 -> -0.44422804 | AE12: =AD12/AC12 -> -5.7029635 | AF12: 0.054550014 | AG12: -0.047771039 | AH12: =AG12/AF12 -> -0.87572918
A13: 45625 | B13: 0.7867 | C13: 6.06 | D13: 26.349 | E13: 8.6092 | F13: 13.044 | G13: 275.85 | H13: 8.82 | I13: 195.03 | J13: 44.71 | K13: 1.992 | L13: 3.94 | M13: 11.938 | N13: 345.16 | O13: 207.89 | P13: 237.33 | Q13: 162.08 | R13: 11.13 | S13: 32.64 | T13: 43.19 | U13: 31.86 | V13: 22.04 | W13: 34.1 | X13: 28.914 | Y13: 40.61 | Z13: 134.3 | AB13: DIISY-US | AC13: 0.15926628 | AD13: =(1+M$30)^12-1 -> 0.72651419 | AE13: =AD13/AC13 -> 4.5616321 | AF13: 0.053554575 | AG13: 0.046560114 | AH13: =AG13/AF13 -> 0.86939564
A14: 45657 | B14: 0.771 | C14: 6.32 | D14: 24.894 | E14: 9.36 | F14: 12.796 | G14: 234.7 | H14: 8.49 | I14: 187.2 | J14: 49.32 | K14: 1.895 | L14: 3.42 | M14: 12.785 | N14: 403.84 | O14: 219.39 | P14: 250.42 | Q14: 231.84 | R14: 9.9 | S14: 30.48 | T14: 37.53 | U14: 27.19 | V14: 18.075 | W14: 31.28 | X14: 27.361 | Y14: 37.85 | Z14: 131.71 | AB14: TSLA-US | AC14: 0.1503376 | AD14: =(1+N$30)^12-1 -> 1.5640068 | AE14: =AD14/AC14 -> 10.403298 | AF14: 0.044422425 | AG14: 0.081624705 | AH14: =AG14/AF14 -> 1.8374662
AB15: AMZN-US | AC15: 0.062196119 | AD15: =(1+O$30)^12-1 -> 0.4875457 | AE15: =AD15/AC15 -> 7.8388445 | AF15: 0.0083119807 | AG15: 0.033647662 | AH15: =AG15/AF15 -> 4.0480919
A16: RETURN | AB16: AAPL-US | AC16: 0.054708345 | AD16: =(1+P$30)^12-1 -> 0.41788719 | AE16: =AD16/AC16 -> 7.6384544 | AF16: 0.018844391 | AG16: 0.029524786 | AH16: =AG16/AF16 -> 1.5667678
A17: DATE | B17: VFF-US | C17: FENC-US | D17: BDOUY-US | E17: SPMYY-US | F17: AHCHY-US | G17: NSC-US | H17: FQVTF-US | I17: CRAI-US | J17: CHEF-US | K17: SCGPY-US | L17: KOS-US | M17: DIISY-US | N17: TSLA-US | O17: AMZN-US | P17: AAPL-US | Q17: AVGO-US | R17: F-US | S17: SMCI-US | T17: CMCSA-US | U17: HAL-US | V17: BIRDF-US | W17: EPRT-US | X17: OTSKY-US | Y17: OHI-US | Z17: AGYS-US | AB17: AVGO-US | AC17: 0.13845532 | AD17: =(1+Q$30)^12-1 -> 1.2645771 | AE17: =AD17/AC17 -> 9.1334668 | AF17: 0.016184314 | AG17: 0.070489124 | AH17: =AG17/AF17 -> 4.3553977
A18: 45322 | AB18: F-US | AC18: 0.075946287 | AD18: =(1+R$30)^12-1 -> -0.14028721 | AE18: =AD18/AC18 -> -1.8471898 | AF18: 0.051612008 | AG18: -0.012517407 | AH18: =AG18/AF18 -> -0.24252896
A19: 45351 | B19: =(B4-B3)/B3 -> -0.11470588 | C19: =(C4-C3)/C3 -> -0.052052052 | D19: =(D4-D3)/D3 -> 0.05668362 | E19: =(E4-E3)/E3 -> -0.10474632 | F19: =(F4-F3)/F3 -> 0.090238309 | G19: =(G4-G3)/G3 -> 0.077112736 | H19: =(H4-H3)/H3 -> 0.14363144 | I19: =(I4-I3)/I3 -> 0.23591943 | ... Z19: =(Z4-Z3)/Z3 -> -0.070600884 | AB19: SMCI-US | AC19: 0.27084129 | AD19: =(1+S$30)^12-1 -> -0.20172424 | AE19: =AD19/AC19 -> -0.74480608 | AF19: 0.1268048 | AG19: -0.018599944 | AH19: =AG19/AF19 -> -0.1466817
A20: 45379 | B20: =(B5-B4)/B4 -> 0.64784053 | C20: =(C5-C4)/C4 -> 0.17423442 | D20: =(D5-D4)/D4 -> 0.0098100452 | E20: =(E5-E4)/E4 -> 0.84588665 | F20: =(F5-F4)/F4 -> -0.048747028 | G20: =(G5-G4)/G4 -> 0.0058804957 | H20: =(H5-H4)/H4 -> 0.041299932 | I20: =(I5-I4)/I4 -> 0.12856496 | ... Z20: =(Z5-Z4)/Z4 -> 0.083033419 | AB20: CMCSA-US | AC20: 0.069196854 | AD20: =(1+T$30)^12-1 -> -0.18697242 | AE20: =AD20/AC20 -> -2.7020364 | AF20: 0.050307948 | AG20: -0.017101271 | AH20: =AG20/AF20 -> -0.3399318
A21: 45412 | B21: =(B6-B5)/B5 -> 0.23387097 | C21: =(C6-C5)/C5 -> -0.17446043 | D21: =(D6-D5)/D5 -> -0.066584194 | E21: =(E6-E5)/E5 -> -0.045260969 | F21: =(F6-F5)/F5 -> 0.12229593 | G21: =(G6-G5)/G5 -> -0.096323616 | H21: =(H6-H5)/H5 -> -0.089401821 | I21: =(I6-I5)/I5 -> -0.030017382 | ... Z21: =(Z6-Z5)/Z5 -> -0.014360313 | AB21: HAL-US | AC21: 0.090252653 | AD21: =(1+U$30)^12-1 -> -0.22177072 | AE21: =AD21/AC21 -> -2.4572211 | AF21: 0.04351156 | AG21: -0.02067773 | AH21: =AG21/AF21 -> -0.47522383
A22: 45443 | B22: =(B7-B6)/B6 -> -0.22222222 | C22: =(C7-C6)/C6 -> -0.26143791 | D22: =(D7-D6)/D6 -> -0.13405317 | E22: =(E7-E6)/E6 -> -0.032956432 | F22: =(F7-F6)/F6 -> 0.058853765 | G22: =(G7-G6)/G6 -> -0.023966655 | H22: =(H7-H6)/H6 -> -0.027133167 | I22: =(I7-I6)/I6 -> 0.21283341 | ... Z22: =(Z7-Z6)/Z6 -> 0.14954846 | AB22: BIRDF-US | AC22: 0.13259032 | AD22: =(1+V$30)^12-1 -> 0.80682716 | AE22: =AD22/AC22 -> 6.0851136 | AF22: 0.06454969 | AG22: 0.050533044 | AH22: =AG22/AF22 -> 0.78285494
A23: 45471 | B23: =(B8-B7)/B7 -> -0.14285714 | C23: =(C8-C7)/C7 -> -0.098820059 | D23: =(D8-D7)/D7 -> -0.015349989 | E23: =(E8-E7)/E7 -> -0.056026946 | F23: =(F8-F7)/F7 -> -0.036245955 | G23: =(G8-G7)/G7 -> -0.04497331 | H23: =(H8-H7)/H7 -> -0.0044036697 | I23: =(I8-I7)/I7 -> -0.021310451 | ... Z23: =(Z8-Z7)/Z7 -> 0.090813868 | AB23: EPRT-US | AC23: 0.066676314 | AD23: =(1+W$30)^12-1 -> 0.31260537 | AE23: =AD23/AC23 -> 4.6884021 | AF23: 0.03196699 | AG23: 0.0229267 | AH23: =AG23/AF23 -> 0.71719922
A24: 45504 | B24: =(B9-B8)/B8 -> 0.1127451 | C24: =(C9-C8)/C8 -> 0.058919804 | D24: =(D9-D8)/D8 -> 0.072917619 | E24: =(E9-E8)/E8 -> 0.022727273 | F24: =(F9-F8)/F8 -> 0.025184688 | G24: =(G9-G8)/G8 -> 0.16242023 | H24: =(H9-H8)/H8 -> -0.11389606 | I24: =(I9-I8)/I8 -> 0.014980838 | ... Z24: =(Z9-Z8)/Z8 -> 0.076339543 | AB24: OTSKY-US | AC24: 0.086823671 | AD24: =(1+X$30)^12-1 -> 0.46659163 | AE24: =AD24/AC24 -> 5.3740141 | AF24: 0.0079822757 | AG24: 0.032426397 | AH24: =AG24/AF24 -> 4.0622999
A25: 45534 | B25: =(B10-B9)/B9 -> -0.092511013 | C25: =(C10-C9)/C9 -> -0.13910355 | D25: =(D10-D9)/D9 -> 0.15952959 | E25: =(E10-E9)/E9 -> 0.022222222 | F25: =(F10-F9)/F9 -> -0.11398624 | G25: =(G10-G9)/G9 -> 0.026446546 | H25: =(H10-H9)/H9 -> -0.03452579 | I25: =(I10-I9)/I9 -> -0.035469108 | ... Z25: =(Z10-Z9)/Z9 -> 0.0090106165 | AB25: OHI-US | AC25: 0.053019576 | AD25: =(1+Y$30)^12-1 -> 0.35728064 | AE25: =AD25/AC25 -> 6.7386552 | AF25: 0.015243506 | AG25: 0.025783726 | AH25: =AG25/AF25 -> 1.6914564
A26: 45565 | B26: =(B11-B10)/B10 -> -0.097087379 | C26: =(C11-C10)/C10 -> -0.10233393 | D26: =(D11-D10)/D10 -> 0.036085694 | E26: =(E11-E10)/E10 -> -0.0010869565 | F26: =(F11-F10)/F10 -> 0.35942699 | G26: =(G11-G10)/G10 -> -0.029903186 | H26: =(H11-H10)/H10 -> -0.060749677 | I26: =(I11-I10)/I10 -> 0.039857651 | ... Z26: =(Z11-Z10)/Z10 -> -0.036516357 | AB26: AGYS-US | AC26: 0.12203126 | AD26: =(1+Z$30)^12-1 -> 0.75614383 | AE26: =AD26/AC26 -> 6.1963127 | AF26: 0.030379323 | AG26: 0.048045184 | AH26: =AG26/AF26 -> 1.5815094
A27: 45596 | B27: =(B12-B11)/B11 -> -0.057311828 | C27: =(C12-C11)/C11 -> -0.128 | D27: =(D12-D11)/D11 -> -0.067387835 | E27: =(E12-E11)/E11 -> -0.048531012 | F27: =(F12-F11)/F11 -> -0.011829492 | G27: =(G12-G11)/G11 -> 0.0077665996 | H27: =(H12-H11)/H11 -> -0.12522936 | I27: =(I12-I11)/I11 -> 0.038900297 | ... Z27: =(Z12-Z11)/Z11 -> -0.08194916
A28: 45625 | B28: =(B13-B12)/B12 -> -0.10265769 | C28: =(C13-C12)/C12 -> 0.38990826 | D28: =(D13-D12)/D12 -> 0.0020536224 | E28: =(E13-E12)/E12 -> -0.015416285 | F28: =(F13-F12)/F12 -> -0.10257998 | G28: =(G13-G12)/G12 -> 0.10150541 | H28: =(H13-H12)/H12 -> -0.07498689 | I28: =(I13-I12)/I12 -> 0.070769738 | ... Z28: =(Z13-Z12)/Z12 -> 0.34246301
A29: 45657 | B29: =(B14-B13)/B13 -> -0.019956781 | C29: =(C14-C13)/C13 -> 0.04290429 | D29: =(D14-D13)/D13 -> -0.055220312 | E29: =(E14-E13)/E13 -> 0.087209032 | F29: =(F14-F13)/F13 -> -0.019012573 | G29: =(G14-G13)/G13 -> -0.14917528 | H29: =(H14-H13)/H13 -> -0.037414966 | I29: =(I14-I13)/I13 -> -0.04014767 | ... Z29: =(Z14-Z13)/Z13 -> -0.019285182
A30: average mean | B30: =AVERAGE(B19:B29) -> 0.01319515 | C30: =AVERAGE(C19:C29) -> -0.02638556 | D30: =AVERAGE(D19:D29) -> -0.00013775507 | E30: =AVERAGE(E19:E29) -> 0.061274569 | F30: =AVERAGE(F19:F29) -> 0.029418037 | G30: =AVERAGE(G19:G29) -> 0.0033445436 | H30: =AVERAGE(H19:H29) -> -0.034800911 | I30: =AVERAGE(I19:I29) -> 0.055898338 | ... Z30: =AVERAGE(Z19:Z29) -> 0.048045184
A31: st.dev | B31: =_xlfn.STDEV.S(B19:B29) -> 0.24501904 | C31: =_xlfn.STDEV.S(C19:C29) -> 0.18371372 | D31: =_xlfn.STDEV.S(D19:D29) -> 0.081001147 | E31: =_xlfn.STDEV.S(E19:E29) -> 0.26508099 | F31: =_xlfn.STDEV.S(F19:F29) -> 0.13212584 | G31: =_xlfn.STDEV.S(G19:G29) -> 0.088500865 | H31: =_xlfn.STDEV.S(H19:H29) -> 0.076368837 | I31: =_xlfn.STDEV.S(I19:I29) -> 0.097813006 | ... Z31: =_xlfn.STDEV.S(Z19:Z29) -> 0.12203126
A32: variance | B32: =B31^2 -> 0.06003433 | C32: =C31^2 -> 0.03375073 | D32: =D31^2 -> 0.0065611858 | E32: =E31^2 -> 0.07026793 | F32: =F31^2 -> 0.017457238 | G32: =G31^2 -> 0.0078324031 | H32: =H31^2 -> 0.0058321993 | I32: =I31^2 -> 0.0095673842 | ... Z32: =Z31^2 -> 0.014891628
A33: st. dev of -ve returns | B33: =_xlfn.STDEV.S(B19,B22,B23,B25,B26,B27,B28,B29) -> 0.059747282 | C33: =_xlfn.STDEV.S(C19,C21,C22,C23,C25,C26,C27,C30) -> 0.073170081 | D33: =_xlfn.STDEV.S(D21,D22,D23,D27,D29,D30) -> 0.047130419 | E33: =_xlfn.STDEV.S(E19,E21,E22,E23,E26,E27,E28,) -> 0.034404526 | F33: =_xlfn.STDEV.S(F20,F23,F25,F27,F29) -> 0.040684012 | G33: =_xlfn.STDEV.S(G22,G21,G23,G26,G29) -> 0.053170512 | H33: =_xlfn.STDEV.S(H21,H23,H22,H25,,H24,H26,H27,H28,H29,H30) -> 0.041850159 | I33: =_xlfn.STDEV.S(I21,I23,I25,I29) -> 0.0080898703 | J33: =_xlfn.STDEV.S(J20:J23,J26:J27) -> 0.1043727 | K33: =_xlfn.STDEV.S(K21,K22,K25,K27:K30) -> 0.035345283 | L33: =_xlfn.STDEV.S(L20:L21,L23:L27,L29,L30) -> 0.054550014 | M33: =_xlfn.STDEV.S(M20,M21,M23,M24,M27,) -> 0.053554575 | N33: =_xlfn.STDEV.S(N20,N22,N25,N27) -> 0.044422425 | O33: =_xlfn.STDEV.S(O21,O24,O25) -> 0.0083119807 | P33: =_xlfn.STDEV.S(P19:P21,P27) -> 0.018844391 | Q33: =_xlfn.STDEV.S(Q21,Q27,Q28) -> 0.016184314 | R33: =_xlfn.STDEV.S(R21,R22,R24,R26,R27,R29,R30) -> 0.051612008 | S33: =_xlfn.STDEV.S(S21,S22,S24:S27,S29,S30) -> 0.1268048 | T33: =_xlfn.STDEV.S(T19,T21,T23,T25,T28:T30) -> 0.050307948 | U33: =_xlfn.STDEV.S(U19,U21:U23,U25:U27,U29,U30) -> 0.04351156 | V33: =_xlfn.STDEV.S(V24,V25,V29) -> 0.06454969 | W33: =_xlfn.STDEV.S(W19,W21,W27,W29) -> 0.03196699 | X33: =_xlfn.STDEV.S(X22,X26,X28,X29) -> 0.0079822757 | Y33: =_xlfn.STDEV.S(Y21,Y28,Y29) -> 0.015243506 | Z33: =_xlfn.STDEV.S(Z19,Z21,Z26:Z27,Z29) -> 0.030379323
A36: EXCESS RETURN
A37: DATE | B37: VFF-US | C37: FENC-US | D37: BDOUY-US | E37: SPMYY-US | F37: AHCHY-US | G37: NSC-US | H37: FQVTF-US | I37: CRAI-US | J37: CHEF-US | K37: SCGPY-US | L37: KOS-US | M37: DIISY-US | N37: TSLA-US | O37: AMZN-US | P37: AAPL-US | Q37: AVGO-US | R37: F-US | S37: SMCI-US | T37: CMCSA-US | U37: HAL-US | V37: BIRDF-US | W37: EPRT-US | X37: OTSKY-US | Y37: OHI-US | Z37: AGYS-US
A38: 45322
A39: 45351 | B39: =B19-B$30 -> -0.12790103 | C39: =C19-C$30 -> -0.025666492 | D39: =D19-D$30 -> 0.056821375 | E39: =E19-E$30 -> -0.16602089 | F39: =F19-F$30 -> 0.060820271 | G39: =G19-G$30 -> 0.073768192 | H39: =H19-H$30 -> 0.17843235 | I39: =I19-I$30 -> 0.18002109 | ... Z39: =Z19-Z$30 -> -0.11864607
A40: 45379 | B40: =B20-B$30 -> 0.63464538 | C40: =C20-C$30 -> 0.20061998 | D40: =D20-D$30 -> 0.0099478003 | E40: =E20-E$30 -> 0.78461209 | F40: =F20-F$30 -> -0.078165065 | G40: =G20-G$30 -> 0.0025359521 | H40: =H20-H$30 -> 0.076100844 | I40: =I20-I$30 -> 0.072666623 | ... Z40: =Z20-Z$30 -> 0.034988235
A41: 45412 | B41: =B21-B$30 -> 0.22067582 | C41: =C21-C$30 -> -0.14807487 | D41: =D21-D$30 -> -0.066446439 | E41: =E21-E$30 -> -0.10653554 | F41: =F21-F$30 -> 0.092877896 | G41: =G21-G$30 -> -0.09966816 | H41: =H21-H$30 -> -0.054600909 | I41: =I21-I$30 -> -0.08591572 | ... Z41: =Z21-Z$30 -> -0.062405498
A42: 45443 | B42: =B22-B$30 -> -0.23541737 | C42: =C22-C$30 -> -0.23505235 | D42: =D22-D$30 -> -0.13391541 | E42: =E22-E$30 -> -0.094231001 | F42: =F22-F$30 -> 0.029435728 | G42: =G22-G$30 -> -0.027311199 | H42: =H22-H$30 -> 0.0076677447 | I42: =I22-I$30 -> 0.15693508 | ... Z42: =Z22-Z$30 -> 0.10150328
A43: 45471 | B43: =B23-B$30 -> -0.15605229 | C43: =C23-C$30 -> -0.072434499 | D43: =D23-D$30 -> -0.015212234 | E43: =E23-E$30 -> -0.11730152 | F43: =F23-F$30 -> -0.065663992 | G43: =G23-G$30 -> -0.048317853 | H43: =H23-H$30 -> 0.030397242 | I43: =I23-I$30 -> -0.077208789 | ... Z43: =Z23-Z$30 -> 0.042768684
A44: 45504 | B44: =B24-B$30 -> 0.099549948 | C44: =C24-C$30 -> 0.085305364 | D44: =D24-D$30 -> 0.073055374 | E44: =E24-E$30 -> -0.038547297 | F44: =F24-F$30 -> -0.0042333498 | G44: =G24-G$30 -> 0.15907569 | H44: =H24-H$30 -> -0.079095145 | I44: =I24-I$30 -> -0.0409175 | ... Z44: =Z24-Z$30 -> 0.028294358
A45: 45534 | B45: =B25-B$30 -> -0.10570616 | C45: =C25-C$30 -> -0.11271799 | D45: =D25-D$30 -> 0.15966735 | E45: =E25-E$30 -> -0.039052347 | F45: =F25-F$30 -> -0.14340428 | G45: =G25-G$30 -> 0.023102002 | H45: =H25-H$30 -> 0.00027512109 | I45: =I25-I$30 -> -0.091367446 | ... Z45: =Z25-Z$30 -> -0.039034568
A46: 45565 | B46: =B26-B$30 -> -0.11028253 | C46: =C26-C$30 -> -0.075948372 | D46: =D26-D$30 -> 0.036223449 | E46: =E26-E$30 -> -0.062361526 | F46: =F26-F$30 -> 0.33000895 | G46: =G26-G$30 -> -0.033247729 | H46: =H26-H$30 -> -0.025948765 | I46: =I26-I$30 -> -0.016040687 | ... Z46: =Z26-Z$30 -> -0.084561542
A47: 45596 | B47: =B27-B$30 -> -0.070506978 | C47: =C27-C$30 -> -0.10161444 | D47: =D27-D$30 -> -0.06725008 | E47: =E27-E$30 -> -0.10980558 | F47: =F27-F$30 -> -0.04124753 | G47: =G27-G$30 -> 0.004422056 | H47: =H27-H$30 -> -0.090428446 | I47: =I27-I$30 -> -0.016998042 | ... Z47: =Z27-Z$30 -> -0.12999434
A48: 45625 | B48: =B28-B$30 -> -0.11585284 | C48: =C28-C$30 -> 0.41629382 | D48: =D28-D$30 -> 0.0021913774 | E48: =E28-E$30 -> -0.076690855 | F48: =F28-F$30 -> -0.13199802 | G48: =G28-G$30 -> 0.098160867 | H48: =H28-H$30 -> -0.040185979 | I48: =I28-I$30 -> 0.014871399 | ... Z48: =Z28-Z$30 -> 0.29441783
A49: 45657 | B49: =B29-B$30 -> -0.033151932 | C49: =C29-C$30 -> 0.069289851 | D49: =D29-D$30 -> -0.055082557 | E49: =E29-E$30 -> 0.025934463 | F49: =F29-F$30 -> -0.04843061 | G49: =G29-G$30 -> -0.15251982 | H49: =H29-H$30 -> -0.0026140545 | I49: =I29-I$30 -> -0.096046008 | ... Z49: =Z29-Z$30 -> -0.067330367
A51: xtx
B52: VFF-US | C52: FENC-US | D52: BDOUY-US | E52: SPMYY-US | F52: AHCHY-US | G52: NSC-US | H52: FQVTF-US | I52: CRAI-US | J52: CHEF-US | K52: SCGPY-US | L52: KOS-US | M52: DIISY-US | N52: TSLA-US | O52: AMZN-US | P52: AAPL-US | Q52: AVGO-US | R52: F-US | S52: SMCI-US | T52: CMCSA-US | U52: HAL-US | V52: BIRDF-US | W52: EPRT-US | X52: OTSKY-US | Y52: OHI-US | Z52: AGYS-US
A53: VFF-US | B53: {=MMULT(TRANSPOSE(B39:Z49), B39:Z49)} -> 0.6003433 | C53: 0.14998927 | D53: 0.010996448 | E53: 0.55909886 | F53: -0.035423615 | G53: -0.0054173863 | H53: 0.012954441 | I53: -0.010750031 | J53: -0.10999352 | K53: 0.020882899 | L53: 0.00045260472 | M53: -0.13596689 | N53: -0.13900223 | O53: -0.046647413 | P53: -0.082047335 | Q53: -0.058529815 | R53: -0.0037191576 | S53: 0.044767981 | T53: -0.011599641 | U53: 0.098801707 | V53: -0.036697201 | W53: 0.056557165 | X53: 0.037299825 | Y53: -0.032888572 | Z53: -0.013404041
A54: FENC-US | B54: 0.14998927 | C54: 0.3375073 | D54: 0.032368087 | E54: 0.19496994 | F54: -0.096532888 | G54: 0.066630634 | H54: 0.0022395591 | I54: 0.00067408967 | J54: 0.03234156 | K54: -0.0244934 | L54: 0.033799417 | M54: 0.14574017 | N54: 0.14614401 | O54: 0.046926337 | P54: -0.018198003 | Q54: -0.0095563742 | R54: 0.040152983 | S54: 0.16663072 | T54: -0.0012543189 | U54: 0.11839949 | V54: -0.060540346 | W54: 0.044514973 | X54: -0.019946898 | Y54: -0.045538486 | Z54: 0.13669292
A55: BDOUY-US | B55: 0.010996448 | C55: 0.032368087 | D55: 0.065611858 | E55: 0.014331355 | F55: -0.01253595 | G55: 0.037656372 | H55: 0.012497499 | I55: -0.014873316 | J55: 0.00012525235 | K55: 0.011743752 | L55: -0.018623411 | M55: 0.0013863227 | N55: 0.005222549 | O55: -0.0033144992 | P55: -0.011174621 | Q55: -0.01723596 | R55: 0.010908527 | S55: 0.010440024 | T55: 0.00073525019 | U55: 0.0020318346 | V55: -0.036655978 | W55: 0.026443215 | X55: 0.038804321 | Y55: 0.017759949 | Z55: -0.010622977
A56: SPMYY-US | B56: 0.55909886 | C56: 0.19496994 | D56: 0.014331355 | E56: 0.7026793 | F56: -0.077812935 | G56: -0.008327675 | H56: 0.049214916 | I56: 0.034930257 | J56: -0.047182335 | K56: 0.013055608 | L56: -0.00063782871 | M56: -0.07295508 | N56: -0.1666213 | O56: -0.022930126 | P56: -0.063083011 | Q56: -0.014285962 | R56: 0.049180119 | S56: 0.089060939 | T56: 0.021512244 | U56: 0.11342934 | V56: -0.016288837 | W56: 0.083281555 | X56: -0.0081725363 | Y56: -0.017744306 | Z56: 0.034872613
A57: AHCHY-US | B57: -0.035423615 | C57: -0.096532888 | D57: -0.01253595 | E57: -0.077812935 | F57: 0.17457238 | G57: -0.02331098 | H57: -0.0010445609 | I57: 0.018350434 | J57: -0.022228326 | K57: 0.041580935 | L57: -0.030126702 | M57: -0.03564309 | N57: 0.037540833 | O57: 0.0012687589 | P57: -0.0073273698 | Q57: -0.006605158 | R57: -0.03898391 | S57: 0.044393796 | T57: 0.015897195 | U57: -0.028227133 | V57: 0.017623167 | W57: -0.0058839545 | X57: -0.027120619 | Y57: 0.0016523144 | Z57: -0.068235469
A58: NSC-US | B58: -0.0054173863 | C58: 0.066630634 | D58: 0.037656372 | E58: -0.008327675 | F58: -0.02331098 | G58: 0.078324031 | H58: 0.0014605508 | I58: 0.029418758 | J58: 0.028838219 | K58: 0.015965362 | L58: 0.03533646 | M58: 0.039997096 | N58: 0.026209823 | O58: 0.0036583717 | P58: -0.0038435769 | Q58: -0.072900635 | R58: 0.017193876 | S58: 0.05317498 | T58: 0.030783358 | U58: 0.04921448 | V58: 0.0081798007 | W58: 0.026365134 | X58: 0.042184476 | Y58: 0.022071345 | Z58: 0.037722926
A59: FQVTF-US | B59: 0.012954441 | C59: 0.0022395591 | D59: 0.012497499 | E59: 0.049214916 | F59: -0.0010445609 | G59: 0.0014605508 | H59: 0.058321993 | I59: 0.046017087 | J59: 0.036777683 | K59: 0.018426842 | L59: 0.0096376516 | M59: 0.033588452 | N59: -0.026248262 | O59: 0.02753747 | P59: -0.0073495972 | Q59: 0.027742434 | R59: 0.033400781 | S59: 0.16991321 | T59: -0.015978529 | U59: 0.0047206092 | V59: 0.01728244 | W59: -0.00013564453 | X59: -0.018117573 | Y59: 0.011153 | Z59: -0.012976609
A60: CRAI-US | B60: -0.010750031 | C60: 0.00067408967 | D60: -0.014873316 | E60: 0.034930257 | F60: 0.018350434 | G60: 0.029418758 | H60: 0.046017087 | I60: 0.095673842 | J60: 0.063199357 | K60: 0.021438393 | L60: 0.051688431 | M60: 0.068906799 | N60: -0.025514286 | O60: 0.024156979 | P60: -0.0032772509 | Q60: -0.035225593 | R60: 0.036062479 | S60: 0.17662123 | T60: 0.018861514 | U60: 0.039726743 | V60: 0.047969355 | W60: 0.0012581718 | X60: -0.023790523 | Y60: 0.017402073 | Z60: 0.015992649
A61: CHEF-US | B61: -0.10999352 | C61: 0.03234156 | D61: 0.00012525235 | E61: -0.047182335 | F61: -0.022228326 | G61: 0.028838219 | H61: 0.036777683 | I61: 0.063199357 | J61: 0.1000233 | K61: 0.0092954513 | L61: 0.042754121 | M61: 0.11646702 | N61: 0.034393299 | O61: 0.029906412 | P61: 0.024049006 | Q61: 0.028675389 | R61: 0.020363429 | S61: 0.1358647 | T61: 0.001489662 | U61: 0.013440498 | V61: -0.019708877 | W61: -0.0065143559 | X61: -0.020201933 | Y61: 0.0093336644 | Z61: 0.040405631
A62: SCGPY-US | B62: 0.020882899 | C62: -0.0244934 | D62: 0.011743752 | E62: 0.013055608 | F62: 0.041580935 | G62: 0.015965362 | H62: 0.018426842 | I62: 0.021438393 | J62: 0.0092954513 | K62: 0.037619985 | L62: 0.00078859775 | M62: -0.028386869 | N62: -0.0072344194 | O62: 0.0023540643 | P62: -0.0027532425 | Q62: 0.0048422094 | R62: -0.01118556 | S62: 0.070891775 | T62: 0.011095984 | U62: -0.0012488644 | V62: 0.013760614 | W62: 0.0044182994 | X62: 0.016859883 | Y62: 0.016462625 | Z62: -0.028270416
A63: KOS-US | B63: 0.00045260472 | C63: 0.033799417 | D63: -0.018623411 | E63: -0.00063782871 | F63: -0.030126702 | G63: 0.03533646 | H63: 0.0096376516 | I63: 0.051688431 | J63: 0.042754121 | K63: 0.00078859775 | L63: 0.060675134 | M63: 0.0666728 | N63: 0.0027610187 | O63: 0.0083420457 | P63: 0.0084202067 | Q63: -0.048498489 | R63: 0.019249844 | S63: 0.078641084 | T63: 0.010273689 | U63: 0.046537088 | V63: 0.021284683 | W63: 0.0045639524 | X63: -0.00067054045 | Y63: 0.0037583917 | Z63: 0.055099223
A64: DIISY-US | B64: -0.13596689 | C64: 0.14574017 | D64: 0.0013863227 | E64: -0.07295508 | F64: -0.03564309 | G64: 0.039997096 | H64: 0.033588452 | I64: 0.068906799 | J64: 0.11646702 | K64: -0.028386869 | L64: 0.0666728 | M64: 0.25365748 | N64: 0.12948125 | O64: 0.055790208 | P64: 0.027257766 | Q64: -0.012700308 | R64: 0.054515281 | S64: 0.19853861 | T64: -0.013904019 | U64: 0.06113921 | V64: -0.050110458 | W64: 0.014463746 | X64: -0.066552242 | Y64: -0.02113365 | Z64: 0.12944391
A65: TSLA-US | B65: -0.13900223 | C65: 0.14614401 | D65: 0.005222549 | E65: -0.1666213 | F65: 0.037540833 | G65: 0.026209823 | H65: -0.026248262 | I65: -0.025514286 | J65: 0.034393299 | K65: -0.0072344194 | L65: 0.0027610187 | M65: 0.12948125 | N65: 0.22601394 | O65: 0.048059069 | P65: 0.026160739 | Q65: 0.032849499 | R65: -0.017859573 | S65: 0.087786373 | T65: -0.0050091708 | U65: 0.022716596 | V65: -0.046138717 | W65: 0.0035451292 | X65: -0.036990352 | Y65: -0.036160916 | Z65: 0.081311646
... A77: AGYS-US | B77: -0.013404041 | C77: 0.13669292 | D77: -0.010622977 | E77: 0.034872613 | F77: -0.068235469 | G77: 0.037722926 | H77: -0.012976609 | I77: 0.015992649 | J77: 0.040405631 | K77: -0.028270416 | L77: 0.055099223 | M77: 0.12944391 | N77: 0.081311646 | O77: 0.018318678 | P77: 0.032093113 | Q77: -0.044919664 | R77: 0.036006117 | S77: 0.026899155 | T77: 0.019648361 | U77: 0.073670441 | V77: -0.00054925855 | W77: 0.043090577 | X77: -0.023698787 | Y77: -0.014667154 | Z77: 0.14891628
A79: variance covariance matrix | AA79: observations
B80: VFF-US | C80: FENC-US | D80: BDOUY-US | E80: SPMYY-US | F80: AHCHY-US | G80: NSC-US | H80: FQVTF-US | I80: CRAI-US | J80: CHEF-US | K80: SCGPY-US | L80: KOS-US | M80: DIISY-US | N80: TSLA-US | O80: AMZN-US | P80: AAPL-US | Q80: AVGO-US | R80: F-US | S80: SMCI-US | T80: CMCSA-US | U80: HAL-US | V80: BIRDF-US | W80: EPRT-US | X80: OTSKY-US | Y80: OHI-US | Z80: AGYS-US | AA80: 11
A81: VFF-US | B81: {=(_xlfn.ANCHORARRAY(B53))/AA80} -> 0.054576663 | C81: 0.013635388 | D81: 0.00099967705 | E81: 0.050827169 | F81: -0.0032203286 | G81: -0.00049248967 | H81: 0.0011776765 | I81: -0.00097727558 | J81: -0.0099994106 | K81: 0.0018984454 | L81: 4.1145884e-05 | M81: -0.012360627 | N81: -0.012636566 | O81: -0.0042406739 | P81: -0.0074588486 | Q81: -0.0053208923 | R81: -0.00033810523 | S81: 0.0040698165 | T81: -0.0010545128 | U81: 0.0089819734 | V81: -0.0033361092 | W81: 0.0051415605 | X81: 0.0033908932 | Y81: -0.0029898702 | Z81: -0.0012185491 | AA81: 0
A82: FENC-US | B82: 0.013635388 | C82: 0.030682482 | D82: 0.0029425534 | E82: 0.01772454 | F82: -0.0087757171 | G82: 0.0060573303 | H82: 0.00020359628 | I82: 6.1280879e-05 | J82: 0.0029401418 | K82: -0.0022266728 | L82: 0.0030726742 | M82: 0.013249107 | N82: 0.01328582 | O82: 0.0042660307 | P82: -0.0016543639 | Q82: -0.00086876129 | R82: 0.0036502711 | S82: 0.015148248 | T82: -0.00011402899 | U82: 0.01076359 | V82: -0.0055036678 | W82: 0.0040468157 | X82: -0.0018133544 | Y82: -0.0041398624 | Z82: 0.01242663 | AA82: 0
A83: BDOUY-US | B83: 0.00099967705 | C83: 0.0029425534 | D83: 0.0059647144 | E83: 0.0013028505 | F83: -0.0011396318 | G83: 0.0034233066 | H83: 0.0011361363 | I83: -0.0013521197 | J83: 1.1386577e-05 | K83: 0.0010676138 | L83: -0.0016930374 | M83: 0.00012602934 | N83: 0.00047477718 | O83: -0.00030131811 | P83: -0.0010158747 | Q83: -0.0015669054 | R83: 0.00099168431 | S83: 0.00094909311 | T83: 6.6840927e-05 | U83: 0.00018471223 | V83: -0.0033323617 | W83: 0.0024039287 | X83: 0.0035276655 | Y83: 0.0016145409 | Z83: -0.00096572518 | AA83: 0
A84: SPMYY-US | B84: 0.050827169 | C84: 0.01772454 | D84: 0.0013028505 | E84: 0.063879936 | F84: -0.0070739032 | G84: -0.00075706136 | H84: 0.0044740833 | I84: 0.0031754779 | J84: -0.0042893032 | K84: 0.0011868734 | L84: -5.7984428e-05 | M84: -0.00663228 | N84: -0.015147391 | O84: -0.0020845569 | P84: -0.0057348192 | Q84: -0.0012987238 | R84: 0.0044709199 | S84: 0.008096449 | T84: 0.0019556586 | U84: 0.010311758 | V84: -0.0014808034 | W84: 0.0075710504 | X84: -0.00074295784 | Y84: -0.0016131187 | Z84: 0.0031702376 | AA84: 0
A85: AHCHY-US | B85: -0.0032203286 | C85: -0.0087757171 | D85: -0.0011396318 | E85: -0.0070739032 | F85: 0.015870217 | G85: -0.00211918 | H85: -9.4960078e-05 | I85: 0.0016682213 | J85: -0.0020207569 | K85: 0.003780085 | L85: -0.0027387911 | M85: -0.0032402809 | N85: 0.003412803 | O85: 0.00011534172 | P85: -0.00066612452 | Q85: -0.00060046891 | R85: -0.0035439918 | S85: 0.0040357997 | T85: 0.0014451996 | U85: -0.002566103 | V85: 0.0016021061 | W85: -0.00053490495 | X85: -0.0024655108 | Y85: 0.0001502104 | Z85: -0.0062032245 | AA85: 0
A86: NSC-US | B86: -0.00049248967 | C86: 0.0060573303 | D86: 0.0034233066 | E86: -0.00075706136 | F86: -0.00211918 | G86: 0.0071203664 | H86: 0.00013277734 | I86: 0.0026744326 | J86: 0.0026216563 | K86: 0.0014513965 | L86: 0.0032124054 | M86: 0.0036360996 | N86: 0.0023827112 | O86: 0.00033257925 | P86: -0.00034941608 | Q86: -0.0066273305 | R86: 0.0015630796 | S86: 0.0048340891 | T86: 0.0027984871 | U86: 0.0044740437 | V86: 0.00074361825 | W86: 0.0023968303 | X86: 0.0038349524 | Y86: 0.0020064859 | Z86: 0.0034293569 | AA86: 0
A87: FQVTF-US | B87: 0.0011776765 | C87: 0.00020359628 | D87: 0.0011361363 | E87: 0.0044740833 | F87: -9.4960078e-05 | G87: 0.00013277734 | H87: 0.0053019994 | I87: 0.0041833715 | J87: 0.0033434257 | K87: 0.0016751675 | L87: 0.00087615015 | M87: 0.0030534957 | N87: -0.0023862057 | O87: 0.0025034063 | P87: -0.0006681452 | Q87: 0.0025220395 | R87: 0.0030364347 | S87: 0.015446656 | T87: -0.0014525936 | U87: 0.00042914629 | V87: 0.001571131 | W87: -1.2331321e-05 | X87: -0.0016470521 | Y87: 0.0010139091 | Z87: -0.0011796917 | AA87: 0
A88: CRAI-US | B88: -0.00097727558 | C88: 6.1280879e-05 | D88: -0.0013521197 | E88: 0.0031754779 | F88: 0.0016682213 | G88: 0.0026744326 | H88: 0.0041833715 | I88: 0.008697622 | J88: 0.0057453961 | K88: 0.0019489448 | L88: 0.0046989482 | M88: 0.0062642545 | N88: -0.0023194806 | O88: 0.002196089 | P88: -0.0002979319 | Q88: -0.0032023266 | R88: 0.0032784072 | S88: 0.016056476 | T88: 0.0017146831 | U88: 0.0036115221 | V88: 0.0043608504 | W88: 0.00011437925 | X88: -0.0021627748 | Y88: 0.0015820067 | Z88: 0.0014538771 | AA88: 0
A89: CHEF-US | B89: -0.0099994106 | C89: 0.0029401418 | D89: 1.1386577e-05 | E89: -0.0042893032 | F89: -0.0020207569 | G89: 0.0026216563 | H89: 0.0033434257 | I89: 0.0057453961 | J89: 0.0090930274 | K89: 0.00084504103 | L89: 0.0038867383 | M89: 0.010587911 | N89: 0.0031266635 | O89: 0.0027187647 | P89: 0.0021862733 | Q89: 0.0026068535 | R89: 0.0018512209 | S89: 0.012351336 | T89: 0.00013542382 | U89: 0.0012218634 | V89: -0.0017917161 | W89: -0.00059221417 | X89: -0.0018365394 | Y89: 0.00084851495 | Z89: 0.0036732392 | AA89: 0
A90: SCGPY-US | B90: 0.0018984454 | C90: -0.0022266728 | D90: 0.0010676138 | E90: 0.0011868734 | F90: 0.003780085 | G90: 0.0014513965 | H90: 0.0016751675 | I90: 0.0019489448 | J90: 0.00084504103 | K90: 0.0034199986 | L90: 7.1690705e-05 | M90: -0.0025806244 | N90: -0.00065767449 | O90: 0.00021400584 | P90: -0.00025029478 | Q90: 0.00044020086 | R90: -0.0010168691 | S90: 0.0064447068 | T90: 0.0010087258 | U90: -0.00011353313 | V90: 0.0012509649 | W90: 0.00040166358 | X90: 0.0015327166 | Y90: 0.0014966023 | Z90: -0.0025700378 | AA90: 0
A91: KOS-US | B91: 4.1145884e-05 | C91: 0.0030726742 | D91: -0.0016930374 | E91: -5.7984428e-05 | F91: -0.0027387911 | G91: 0.0032124054 | H91: 0.00087615015 | I91: 0.0046989482 | J91: 0.0038867383 | K91: 7.1690705e-05 | L91: 0.0055159213 | M91: 0.0060611636 | N91: 0.0002510017 | O91: 0.00075836779 | P91: 0.00076547334 | Q91: -0.0044089535 | R91: 0.0017499858 | S91: 0.0071491894 | T91: 0.00093397174 | U91: 0.0042306443 | V91: 0.0019349711 | W91: 0.00041490476 | X91: -6.0958222e-05 | Y91: 0.00034167197 | Z91: 0.0050090203 | AA91: 0
A92: DIISY-US | B92: -0.012360627 | C92: 0.013249107 | D92: 0.00012602934 | E92: -0.00663228 | F92: -0.0032402809 | G92: 0.0036360996 | H92: 0.0030534957 | I92: 0.0062642545 | J92: 0.010587911 | K92: -0.0025806244 | L92: 0.0060611636 | M92: 0.023059771 | N92: 0.011771022 | O92: 0.0050718371 | P92: 0.0024779787 | Q92: -0.0011545735 | R92: 0.0049559346 | S92: 0.018048964 | T92: -0.0012640017 | U92: 0.00555811 | V92: -0.0045554962 | W92: 0.001314886 | X92: -0.0060502038 | Y92: -0.0019212409 | Z92: 0.011767628 | AA92: 0
A93: TSLA-US | B93: -0.012636566 | C93: 0.01328582 | D93: 0.00047477718 | E93: -0.015147391 | F93: 0.003412803 | G93: 0.0023827112 | H93: -0.0023862057 | I93: -0.0023194806 | J93: 0.0031266635 | K93: -0.00065767449 | L93: 0.0002510017 | M93: 0.011771022 | N93: 0.020546722 | O93: 0.0043690063 | P93: 0.002378249 | Q93: 0.0029863181 | R93: -0.0016235976 | S93: 0.0079805794 | T93: -0.00045537916 | U93: 0.0020651451 | V93: -0.0041944288 | W93: 0.00032228447 | X93: -0.0033627593 | Y93: -0.003287356 | Z93: 0.0073919678 | AA93: 0
... A106: 10&20 YR BOND | B106: 0 | C106: 0 | D106: 0 | E106: 0 | F106: 0 | G106: 0 | H106: 0 | I106: 0 | J106: 0 | K106: 0 | L106: 0 | M106: 0 | N106: 0 | O106: 0 | P106: 0 | Q106: 0 | R106: 0 | S106: 0 | T106: 0 | U106: 0 | V106: 0 | W106: 0 | X106: 0 | Y106: 0 | Z106: 0 | AA106: 0
B107: PORTFOLIO 1 (EQUAL WEIGHTS) | C107: PORTFOLIO 2 (SHARPE RATIO WEIGHTED) | D107: PORTFOLIO 3 (MAX SHARPE RATIO) | E107: PORTFOLIO 4 (HIGHER RISK PORTFOLIO LREVERAGED WITH BONDS) | F107: PORTFOLIO 5 (LOWER RISK LEVERAGED WITH 20 YR BOND) | K107: HELPER PORTFOLIO 2 | M107: HELPER PORTFOLIO 3
A108: Constraining Variable | B108: NONE | C108: HIGHER SR | E108: HIGHER ST. DEV | F108: LOWER ST. DEV | K108: POSITIVE SR | L108: PROPORTIONAL WEIGHTS | M108: TICKER | N108: HIGHER
A109: Value of Constraint | B109: N/A | E109: st.dev >D63 | F109: st. dev< D63 | N109: SR
A110: VFF-US | B110: =1/25 -> 0.04 | C110: =L110 -> 0.0074548854 | D110: 0.052631632 | E110: =D110*'Question1 - Portfolio Optimiza.'!Q32 -> 0.0021315811 | F110: =D110*0.75 -> 0.039473724 | K110: =IF(AE2>0,AE2,0) -> 0.69526826 | L110: =K110/SUM(K$110:K$134) -> 0.0074548854 | M110: TSLA-US | N110: 10.403298
A111: FENC-US | B111: =1/25 -> 0.04 | C111: =L111 -> 0 | D111: 0 | E111: =D111*1.35 -> 0 | F111: =D111*0.75 -> 0 | K111: =IF(AE3>0,AE3,0) -> 0 | L111: =K111/SUM(K$110:K$134) -> 0 | M111: CRAI-US | N111: 9.4131182
A112: BDOUY-US | B112: =1/25 -> 0.04 | C112: =L112 -> 0 | D112: 0.052631632 | E112: =D112*1.35 -> 0.071052703 | F112: =D112*0.75 -> 0.039473724 | K112: =IF(AE4>0,AE4,0) -> 0 | L112: =K112/SUM(K$110:K$134) -> 0 | M112: AVGO-US | N112: 9.1334668
A113: SPMYY-US | B113: =1/25 -> 0.04 | C113: =L113 -> 0.042124749 | D113: 0.052631632 | E113: =D113*1.35 -> 0.071052703 | F113: =D113*0.75 -> 0.039473724 | K113: =IF(AE5>0,AE5,0) -> 3.928699 | L113: =K113/SUM(K$110:K$134) -> 0.042124749 | M113: AMZN-US | N113: 7.8388445
A114: AHCHY-US | B114: =1/25 -> 0.04 | C114: =L114 -> 0.033769417 | D114: 0.052631632 | E114: =D114*1.35 -> 0.071052703 | F114: =D114*0.75 -> 0.039473724 | K114: =IF(AE6>0,AE6,0) -> 3.149452 | L114: =K114/SUM(K$110:K$134) -> 0.033769417 | M114: AAPL-US | N114: 7.6384544
A115: NSC-US | B115: =1/25 -> 0.04 | C115: =L115 -> 0.0049529451 | D115: 0.052631632 | E115: =D115*1.35 -> 0.071052703 | F115: =D115*0.75 -> 0.039473724 | K115: =IF(AE7>0,AE7,0) -> 0.4619287 | L115: =K115/SUM(K$110:K$134) -> 0.0049529451 | M115: CHEF-US | N115: 6.9567804
A116: FQVTF-US | B116: =1/25 -> 0.04 | C116: =L116 -> 0 | D116: 0 | E116: =D116*1.35 -> 0 | F116: =D116*0.75 -> 0 | K116: =IF(AE8>0,AE8,0) -> 0 | L116: =K116/SUM(K$110:K$134) -> 0 | M116: OHI-US | N116: 6.7386552
A117: CRAI-US | B117: =1/25 -> 0.04 | C117: =L117 -> 0.10093042 | D117: 0.052631632 | E117: =D117*1.35 -> 0.071052703 | F117: =D117*0.75 -> 0.039473724 | K117: =IF(AE9>0,AE9,0) -> 9.4131182 | L117: =K117/SUM(K$110:K$134) -> 0.10093042 | M117: AGYS-US | N117: 6.1963127
A118: CHEF-US | B118: =1/25 -> 0.04 | C118: =L118 -> 0.074592793 | D118: 0.052631632 | E118: =D118*1.35 -> 0.071052703 | F118: =D118*0.75 -> 0.039473724 | K118: =IF(AE10>0,AE10,0) -> 6.9567804 | L118: =K118/SUM(K$110:K$134) -> 0.074592793 | M118: BIRDF-US | N118: 6.0851136
A119: SCGPY-US | B119: =1/25 -> 0.04 | C119: =L119 -> 0 | D119: 0 | E119: =D119*1.35 -> 0 | F119: =D119*0.75 -> 0 | K119: =IF(AE11>0,AE11,0) -> 0 | L119: =K119/SUM(K$110:K$134) -> 0 | M119: OTSKY-US | N119: 5.3740141
A120: KOS-US | B120: =1/25 -> 0.04 | C120: =L120 -> 0 | D120: 0 | E120: =D120*1.35 -> 0 | F120: =D120*0.75 -> 0 | K120: =IF(AE12>0,AE12,0) -> 0 | L120: =K120/SUM(K$110:K$134) -> 0 | M120: EPRT-US | N120: 4.6884021
A121: DIISY-US | B121: =1/25 -> 0.04 | C121: =L121 -> 0.048911257 | D121: 0.052631632 | E121: =D121*1.35 -> 0.071052703 | F121: =D121*0.75 -> 0.039473724 | K121: =IF(AE13>0,AE13,0) -> 4.5616321 | L121: =K121/SUM(K$110:K$134) -> 0.048911257 | M121: DIISY-US | N121: 4.5616321
A122: TSLA-US | B122: =1/25 -> 0.04 | C122: =L122 -> 0.11154744 | D122: 0.052631632 | E122: =D122*1.35 -> 0.071052703 | F122: =D122*0.75 -> 0.039473724 | K122: =IF(AE14>0,AE14,0) -> 10.403298 | L122: =K122/SUM(K$110:K$134) -> 0.11154744 | M122: SPMYY-US | N122: 3.928699
... A134: AGYS-US | B134: =1/25 -> 0.04 | C134: =L134 -> 0.066438818 | D134: 0.052631632 | E134: =D134*1.35 -> 0.071052703 | F134: =D134*0.75 -> 0.039473724 | K134: =IF(AE26>0,AE26,0) -> 6.1963127 | L134: =K134/SUM(K$110:K$134) -> 0.066438818 | M134: KOS-US | N134: -5.7029635
A135: 10-yr boond | E135: -0.35 | F135: 0.25
A136: SUM W | B136: =SUM(B110:B134) -> 1 | C136: =SUM(C110:C134) -> 1 | D136: =SUM(D110:D134) -> 1.000001 | E136: =SUM(E110:E135) -> 0.93108023 | F136: =SUM(F110:F135) -> 1.0000007
A137: mean monthly return | B137: {=MMULT(TRANSPOSE(AG$2:AG$26), B110:B134)} -> 0.018383297 | C137: {=MMULT(TRANSPOSE(AG$2:AG$26), C110:C134)} -> 0.047592459 | D137: {=MMULT(TRANSPOSE(AG$2:AG$26), D110:D134)} -> 0.032119525 | E137: {=MMULT(TRANSPOSE(AG$2:AG$26), E110:E134)} -> 0.042451935 | F137: {=MMULT(TRANSPOSE(AG$2:AG$26), F110:F134)} -> 0.024089644
A138: RETURN | B138: {=MMULT(TRANSPOSE(AD$2:AD$26), B110:B134)} -> 0.33967281 | C138: {=MMULT(TRANSPOSE(AD$2:AD$26), C110:C134)} -> 0.78456024 | D138: {=MMULT(TRANSPOSE(AD$2:AD$26), D110:D134)} -> 0.5273742 | E138: {=1.35*(MMULT(TRANSPOSE(AD2:AD26),D110:D134))+(-0.35*4.05%)} -> 0.69778017 | F138: {=0.75*(MMULT(TRANSPOSE(AD2:AD26),F110:F134))+(0.25*4.36%)} -> 0.30754799
...

Sheet Question 1 - ALPHA
B1: PORTFOLIO MONTHLY RETURN | C1: RISK FREE RATE AVERAGE | D1: PORTFOLIO EXCESS RETURN | E1: AVERAGE MARKET EXCESS RETURN 2019-2024 | F1: AVERAGE SMB 2019-2024 | G1: AVERAGE HMML 2019-2024 | H1: AVERAGE MOM 2019-2024
A2: PORTFOLIO 1 2019-2023 | B2: 0.01613206 | C2: 0.14683333 | D2: =B2-C2 -> -0.13070127 | E2: 1.1956667 | F2: -0.045166667 | G2: -0.044166667 | H2: -0.12
A3: PORTFOLIO 2 2019-2023 | B3: 0.032987983 | C3: 0.14683333 | D3: =B3-C3 -> -0.11384535 | E3: 1.1956667 | F3: -0.045166667 | G3: -0.044166667 | H3: 0.12
A4: PORTFOLIO 3 2019-2023 | B4: 0.042148738 | C4: 0.14683333 | D4: =B4-C4 -> -0.1046846 | E4: 1.1956667 | F4: -0.045166667 | G4: -0.044166667 | H4: 0.12
A5: PORTFOLIO 1 2024 | B5: 0.33967281 | C5: 0.4275 | D5: =B5-C5 -> -0.087827194 | E5: 1.4983333 | F5: -0.69833333 | G5: -0.57916667 | H5: 1.2916667
A6: PORTFOLIO 2 2024 | B6: 0.78456024 | C6: 0.4275 | D6: =B6-C6 -> 0.35706024 | E6: 1.4983333 | F6: -0.69833333 | G6: -0.57916667 | H6: 1.2916667
A7: PORTFOLIO 3 2024 | B7: 0.5273742 | C7: 0.4275 | D7: =B7-C7 -> 0.099874202 | E7: 1.4983333 | F7: -0.69833333 | G7: -0.57916667 | H7: 1.2916667
B8: ALPHA
A9: portfolio 1 | B9: -0.13070127
A10: portfolio 2 | B10: -0.11384535
A11: PORTFOLIO 3 | B11: -0.1046846
A12: PORTFOLIO 1 2024 | B12: -0.087827194
A13: PORTFOLIO 2 2024 | B13: 0.35706024
A14: PORTFOLIO 3 2024 | B14: 0.099874202

Sheet Question 2A
A1: Part A | AV1: 2 years | BB1: 3 years | BH1: 5 years | BN1: 7 years | BT1: 10 years | CA1: United States 7-Year Bond Yield | CI1: United States 20-Year Bond Yield | CR1: 30 years
A2: All bonds face value | B2: $100 | AV2: Date | AW2: Yield | BB2: Date | BC2: Yield | BH2: Date | BI2: Yield | BN2: Date | BO2: Yield | BT2: Date | BU2: Yield | CA2: Date | CB2: Yield | CC2: Open | CD2: High | CE2: Low | CI2: Date | CJ2: Yield | CK2: Open | CL2: High | CM2: Low | CR2: Date | CS2: Yield
A3: Information as per | B3: 9.06.2025 | L3: Coupon | Q3: Coupon | V3: Coupon | AA3: Coupon | AG3: Coupon | AM3: Coupon | AV3: 1 | AW3: 1.924 | AX3: =AW4-AW3 -> -0.073 | BB3: 1 | BC3: 1.879 | BD3: =BC4-BC3 -> -0.06 | BH3: 1 | BI3: 1.916 | BJ3: =BI4-BI3 -> -0.065 | BN3: 1 | BO3: 2.024 | BP3: =BO4-BO3 -> -0.056 | BT3: 1 | BU3: 2.133 | BV3: =BU4-BU3 -> -0.049 | CA3: 1 | CB3: 0.5 | CC3: 4.424 | CD3: 4.459 | CE3: 4.408 | CF3: =CB4-CB3 -> 0.201 | CI3: 1 | CJ3: 1.179 | CK3: 4.658 | CL3: 4.695 | CM3: 4.643 | CN3: =CJ4-CJ3 -> 0.271 | CR3: 1 | CS3: 2.571 | CT3: =CS4-CS3 -> 0.004
K4: Bond 3 yr | L4: =(100*C6)/2 -> 1.875 | P4: Bond 5 yr | Q4: =(100*D6)/2 -> 2 | U4: Bond 7 yr | V4: =(100*E6)/2 -> 2.0625 | Z4: Bond 10 yr | AA4: =(100*F6)/2 -> 2.125 | AF4: Bond 20 yr | AG4: =(100*G6)/2 -> 2.5 | AL4: Bond 30 yr | AM4: =(100*H6)/2 -> 2.375 | AV4: 2 | AW4: 1.851 | AX4: =AW5-AW4 -> -0.006 | BB4: 2 | BC4: 1.819 | BD4: =BC5-BC4 -> -0.029 | BH4: 2 | BI4: 1.851 | BJ4: =BI5-BI4 -> -0.015 | BN4: 2 | BO4: 1.968 | BP4: =BO5-BO4 -> -0.017 | BT4: 2 | BU4: 2.084 | BV4: =BU5-BU4 -> 0 | CA4: 2 | CB4: 0.701 | CC4: 4.499 | CD4: 4.507 | CE4: 4.309 | CF4: =CB5-CB4 -> -0.157 | CI4: 2 | CJ4: 1.45 | CK4: 4.735 | CL4: 4.742 | CM4: 4.567 | CN4: =CJ5-CJ4 -> -0.208 | CR4: 2 | CS4: 2.575 | CT4: =CS5-CS4 -> 0.013
B5: 2-Year Bond Yield | C5: 3-Year Bond Yield | D5: 5-Year Bond Yield | E5: 7-Year Bond Yield | F5: 10-Year Bond Yield | G5: 20-Year Bond Yield | H5: 30-Year Bond Yield | L5: PV | M5: Weights | Q5: PV | R5: Weights | V5: PV | W5: Weights | AA5: PV | AB5: Weights | AG5: PV | AH5: Weights | AM5: PV | AN5: Weights | AV5: 3 | AW5: 1.845 | AX5: =AW6-AW5 -> -0.073 | BB5: 3 | BC5: 1.79 | BD5: =BC6-BC5 -> -0.059 | BH5: 3 | BI5: 1.836 | BJ5: =BI6-BI5 -> -0.039 | BN5: 3 | BO5: 1.951 | BP5: =BO6-BO5 -> -0.029 | BT5: 3 | BU5: 2.084 | BV5: =BU6-BU5 -> -0.025 | CA5: 3 | CB5: 0.544 | CC5: 4.467 | CD5: 4.514 | CE5: 4.446 | CF5: =CB6-CB5 -> -0.019 | CI5: 3 | CJ5: 1.242 | CK5: 4.752 | CL5: 4.77 | CM5: 4.668 | CN5: =CJ6-CJ5 -> -0.018 | CR5: 3 | CS5: 2.588 | CT5: =CS6-CS5 -> -0.002
A6: Coupon | B6: 0.03875 | C6: 0.0375 | D6: 0.04 | E6: 0.04125 | F6: 0.0425 | G6: 0.05 | H6: 0.0475 | K6: 1 | L6: =$L$4/((1+$C$10)^K6) -> 1.8380551 | M6: =L6/$L$12 -> 0.018520555 | N6: =M6*K6 -> 0.018520555 | P6: 1 | Q6: =$Q$4/(1+$D$10)^P6 -> 1.9599196 | R6: =Q6/$Q$16 -> 0.019678553 | S6: =R6*P6 -> 0.019678553 | U6: 1 | V6: =$V$4/(1+$E$10)^U6 -> 2.0189907 | W6: =V6/$V$20 -> 0.020416058 | X6: =W6*U6 -> 0.020416058 | Z6: 1 | AA6: =$AA$4/(1+$F$10)^Z6 -> 2.0785445 | AB6: =AA6/$AA$26 -> 0.021157506 | AC6: =AB6*Z6 -> 0.021157506 | AF6: 1 | AG6: =$AG$4/(1+$G$10)^AF6 -> 2.4391434 | AH6: =AG6/$AG$46 -> 0.024360832 | AI6: =AH6*AF6 -> 0.024360832 | AL6: 1 | AM6: =$AM$4/(1+$H$10)^AL6 -> 2.3174123 | AN6: =AM6/$AM$66 -> 0.023992657 | AO6: =AN6*AL6 -> 0.023992657 | AV6: 4 | AW6: 1.772 | AX6: =AW7-AW6 -> -0.015 | BB6: 4 | BC6: 1.731 | BD6: =BC7-BC6 -> -0.019 | BH6: 4 | BI6: 1.797 | BJ6: =BI7-BI6 -> -0.029 | BN6: 4 | BO6: 1.922 | BP6: =BO7-BO6 -> -0.045 | BT6: 4 | BU6: 2.059 | BV6: =BU7-BU6 -> -0.052 | CA6: 4 | CB6: 0.525 | CC6: 4.683 | CD6: 4.739 | CE6: 4.429 | CF6: =CB7-CB6 -> -0.036 | CI6: 4 | CJ6: 1.224 | CK6: 4.892 | CL6: 4.914 | CM6: 4.72 | CN6: =CJ7-CJ6 -> -0.081 | CR6: 4 | CS6: 2.586 | CT6: =CS7-CS6 -> -0.053
A7: Maturity | B7: 31.05.2027 | C7: 15.05.2028 | D7: 31.05.2030 | E7: 31.05.2032 | F7: 15.05.2035 | G7: 15.05.20245 | H7: 15.05.2055 | K7: 2 | L7: =$L$4/((1+$C$10)^K7) -> 1.8018381 | M7: =L7/$L$12 -> 0.018155627 | N7: =M7*K7 -> 0.036311253 | P7: 2 | Q7: =$Q$4/(1+$D$10)^P7 -> 1.9206425 | R7: =Q7/$Q$16 -> 0.019284192 | S7: =R7*P7 -> 0.038568383 | U7: 2 | V7: =$V$4/(1+$E$10)^U7 -> 1.9763993 | W7: =V7/$V$20 -> 0.019985373 | X7: =W7*U7 -> 0.039970746 | Z7: 2 | AA7: =$AA$4/(1+$F$10)^Z7 -> 2.0331046 | AB7: =AA7/$AA$26 -> 0.020694973 | AC7: =AB7*Z7 -> 0.041389946 | AF7: 2 | AG7: =$AG$4/(1+$G$10)^AF7 -> 2.3797682 | AH7: =AG7/$AG$46 -> 0.023767825 | AI7: =AH7*AF7 -> 0.047535649 | AL7: 2 | AM7: =$AM$4/(1+$H$10)^AL7 -> 2.261221 | AN7: =AM7/$AM$66 -> 0.023410896 | AO7: =AN7*AL7 -> 0.046821792 | AV7: 5 | AW7: 1.757 | AX7: =AW8-AW7 -> 0.11 | BB7: 5 | BC7: 1.712 | BD7: =BC8-BC7 -> 0.109 | BH7: 5 | BI7: 1.768 | BJ7: =BI8-BI7 -> 0.069 | BN7: 5 | BO7: 1.877 | BP7: =BO8-BO7 -> 0.046 | BT7: 5 | BU7: 2.007 | BV7: =BU8-BU7 -> 0.032 | CA7: 5 | CB7: 0.489 | CC7: 4.654 | CD7: 4.753 | CE7: 4.592 | CF7: =CB8-CB7 -> 0.009 | CI7: 5 | CJ7: 1.143 | CK7: 4.843 | CL7: 4.965 | CM7: 4.814 | CN7: =CJ8-CJ7 -> 0.048 | CR7: 5 | CS7: 2.533 | CT7: =CS8-CS7 -> 0.011
A8: Price (USD) | B8: 99.76 | C8: 99.57 | D8: 99.56 | E8: 98.78 | F8: 98.31 | G8: 100.08 | H8: 96.59 | K8: 3 | L8: =$L$4/((1+$C$10)^K8) -> 1.7663348 | M8: =L8/$L$12 -> 0.017797889 | N8: =M8*K8 -> 0.053393668 | P8: 3 | Q8: =$Q$4/(1+$D$10)^P8 -> 1.8821525 | R8: =Q8/$Q$16 -> 0.018897733 | S8: =R8*P8 -> 0.056693199 | U8: 3 | V8: =$V$4/(1+$E$10)^U8 -> 1.9347064 | W8: =V8/$V$20 -> 0.019563774 | X8: =W8*U8 -> 0.058691321 | Z8: 3 | AA8: =$AA$4/(1+$F$10)^Z8 -> 1.9886581 | AB8: =AA8/$AA$26 -> 0.020242552 | AC8: =AB8*Z8 -> 0.060727655 | AF8: 3 | AG8: =$AG$4/(1+$G$10)^AF8 -> 2.3218383 | AH8: =AG8/$AG$46 -> 0.023189253 | AI8: =AH8*AF8 -> 0.069567758 | AL8: 3 | AM8: =$AM$4/(1+$H$10)^AL8 -> 2.2063921 | AN8: =AM8/$AM$66 -> 0.022843242 | AO8: =AN8*AL8 -> 0.068529725 | AV8: 6 | AW8: 1.867 | AX8: =AW9-AW8 -> -0.022 | BB8: 6 | BC8: 1.821 | BD8: =BC9-BC8 -> 0.004 | BH8: 6 | BI8: 1.837 | BJ8: =BI9-BI8 -> 0.034 | BN8: 6 | BO8: 1.923 | BP8: =BO9-BO8 -> 0.063 | BT8: 6 | BU8: 2.039 | BV8: =BU9-BU8 -> 0.085 | CA8: 6 | CB8: 0.498 | CC8: 4.553 | CD8: 4.721 | CE8: 4.516 | CF8: =CB9-CB8 -> -0.007 | CI8: 6 | CJ8: 1.191 | CK8: 4.767 | CL8: 4.925 | CM8: 4.736 | CN8: =CJ9-CJ8 -> -0.079 | CR8: 6 | CS8: 2.544 | CT8: =CS9-CS8 -> 0.104
A9: Yield | B9: 0.0404 | C9: 0.0402 | D9: 0.0409 | E9: 0.0431 | F9: 0.0447 | G9: 0.0499 | H9: 0.0497 | K9: 4 | L9: =$L$4/((1+$C$10)^K9) -> 1.731531 | M9: =L9/$L$12 -> 0.0174472 | N9: =M9*K9 -> 0.069788802 | P9: 4 | Q9: =$Q$4/(1+$D$10)^P9 -> 1.8444338 | R9: =Q9/$Q$16 -> 0.018519019 | S9: =R9*P9 -> 0.074076076 | U9: 4 | V9: =$V$4/(1+$E$10)^U9 -> 1.893893 | W9: =V9/$V$20 -> 0.019151068 | X9: =W9*U9 -> 0.076604273 | Z9: 4 | AA9: =$AA$4/(1+$F$10)^Z9 -> 1.9451833 | AB9: =AA9/$AA$26 -> 0.019800021 | AC9: =AB9*Z9 -> 0.079200085 | AF9: 4 | AG9: =$AG$4/(1+$G$10)^AF9 -> 2.2653186 | AH9: =AG9/$AG$46 -> 0.022624765 | AI9: =AH9*AF9 -> 0.090499059 | AL9: 4 | AM9: =$AM$4/(1+$H$10)^AL9 -> 2.1528927 | AN9: =AM9/$AM$66 -> 0.022289351 | AO9: =AN9*AL9 -> 0.089157405 | AV9: 7 | AW9: 1.845 | AX9: =AW10-AW9 -> -0.021 | BB9: 7 | BC9: 1.825 | BD9: =BC10-BC9 -> -0.034 | BH9: 7 | BI9: 1.871 | BJ9: =BI10-BI9 -> -0.055 | BN9: 7 | BO9: 1.986 | BP9: =BO10-BO9 -> -0.058 | BT9: 7 | BU9: 2.124 | BV9: =BU10-BU9 -> -0.067 | CA9: 7 | CB9: 0.491 | CC9: 4.414 | CD9: 4.644 | CE9: 4.352 | CF9: =CB10-CB9 -> -0.028 | CI9: 7 | CJ9: 1.112 | CK9: 4.672 | CL9: 4.805 | CM9: 4.576 | CN9: =CJ10-CJ9 -> -0.01 | CR9: 7 | CS9: 2.648 | CT9: =CS10-CS9 -> -0.067
B10: =B9/2 -> 0.0202 | C10: =C9/2 -> 0.0201 | D10: =D9/2 -> 0.02045 | E10: =E9/2 -> 0.02155 | F10: =F9/2 -> 0.02235 | G10: =G9/2 -> 0.02495 | H10: =H9/2 -> 0.02485 | K10: 5 | L10: =$L$4/((1+$C$10)^K10) -> 1.697413 | M10: =L10/$L$12 -> 0.017103422 | N10: =M10*K10 -> 0.085517108 | P10: 5 | Q10: =$Q$4/(1+$D$10)^P10 -> 1.807471 | R10: =Q10/$Q$16 -> 0.018147895 | S10: =R10*P10 -> 0.090739473 | U10: 5 | V10: =$V$4/(1+$E$10)^U10 -> 1.8539406 | W10: =V10/$V$20 -> 0.018747069 | X10: =W10*U10 -> 0.093735345 | Z10: 5 | AA10: =$AA$4/(1+$F$10)^Z10 -> 1.9026589 | AB10: =AA10/$AA$26 -> 0.019367165 | AC10: =AB10*Z10 -> 0.096835826 | AF10: 5 | AG10: =$AG$4/(1+$G$10)^AF10 -> 2.2101747 | AH10: =AG10/$AG$46 -> 0.022074018 | AI10: =AH10*AF10 -> 0.11037009 | AL10: 5 | AM10: =$AM$4/(1+$H$10)^AL10 -> 2.1006906 | AN10: =AM10/$AM$66 -> 0.021748891 | AO10: =AN10*AL10 -> 0.10874446 | AV10: 8 | AW10: 1.824 | AX10: =AW11-AW10 -> 0.036 | BB10: 8 | BC10: 1.791 | BD10: =BC11-BC10 -> 0.032 | BH10: 8 | BI10: 1.816 | BJ10: =BI11-BI10 -> 0.038 | BN10: 8 | BO10: 1.928 | BP10: =BO11-BO10 -> 0.024 | BT10: 8 | BU10: 2.057 | BV10: =BU11-BU10 -> 0.017 | CA10: 8 | CB10: 0.463 | CC10: 4.198 | CD10: 4.431 | CE10: 4.193 | CF10: =CB11-CB10 -> -0.02 | CI10: 8 | CJ10: 1.102 | CK10: 4.452 | CL10: 4.702 | CM10: 4.448 | CN10: =CJ11-CJ10 -> -0.088 | CR10: 8 | CS10: 2.581 | CT10: =CS11-CS10 -> 0.015
K11: 6 | L11: =(100+$L$4)/((1+$C$10)^K11) -> 90.40889 | M11: =L11/$L$12 -> 0.91097531 | N11: =M11*K11 -> 5.4658518 | P11: 6 | Q11: =$Q$4/(1+$D$10)^P11 -> 1.771249 | R11: =Q11/$Q$16 -> 0.017784208 | S11: =R11*P11 -> 0.10670525 | U11: 6 | V11: =$V$4/(1+$E$10)^U11 -> 1.814831 | W11: =V11/$V$20 -> 0.018351592 | X11: =W11*U11 -> 0.11010955 | Z11: 6 | AA11: =$AA$4/(1+$F$10)^Z11 -> 1.8610641 | AB11: =AA11/$AA$26 -> 0.018943772 | AC11: =AB11*Z11 -> 0.11366263 | AF11: 6 | AG11: =$AG$4/(1+$G$10)^AF11 -> 2.1563732 | AH11: =AG11/$AG$46 -> 0.021536678 | AI11: =AH11*AF11 -> 0.12922007 | AL11: 6 | AM11: =$AM$4/(1+$H$10)^AL11 -> 2.0497542 | AN11: =AM11/$AM$66 -> 0.021221536 | AO11: =AN11*AL11 -> 0.12732922 | AV11: 9 | AW11: 1.86 | AX11: =AW12-AW11 -> -0.15 | BB11: 9 | BC11: 1.823 | BD11: =BC12-BC11 -> -0.152 | BH11: 9 | BI11: 1.854 | BJ11: =BI12-BI11 -> -0.193 | BN11: 9 | BO11: 1.952 | BP11: =BO12-BO11 -> -0.214 | BT11: 9 | BU11: 2.074 | BV11: =BU12-BU11 -> -0.231 | CA11: 9 | CB11: 0.443 | CC11: 4.198 | CD11: 4.276 | CE11: 4.187 | CF11: =CB12-CB11 -> -0.056 | CI11: 9 | CJ11: 1.014 | CK11: 4.46 | CL11: 4.537 | CM11: 4.431 | CN11: =CJ12-CJ11 -> -0.043 | CR11: 9 | CS11: 2.596 | CT11: =CS12-CS11 -> -0.22
L12: =SUM(L6:L11) -> 99.244062 | M12: =L12/$L$12 -> 1 | N12: =SUM(N6:N11) -> 5.7293832 | P12: 7 | Q12: =$Q$4/(1+$D$10)^P12 -> 1.7357528 | R12: =Q12/$Q$16 -> 0.017427809 | S12: =R12*P12 -> 0.12199466 | U12: 7 | V12: =$V$4/(1+$E$10)^U12 -> 1.7765464 | W12: =V12/$V$20 -> 0.017964458 | X12: =W12*U12 -> 0.12575121 | Z12: 7 | AA12: =$AA$4/(1+$F$10)^Z12 -> 1.8203786 | AB12: =AA12/$AA$26 -> 0.018529635 | AC12: =AB12*Z12 -> 0.12970744 | AF12: 7 | AG12: =$AG$4/(1+$G$10)^AF12 -> 2.1038814 | AH12: =AG12/$AG$46 -> 0.021012418 | AI12: =AH12*AF12 -> 0.14708693 | AL12: 7 | AM12: =$AM$4/(1+$H$10)^AL12 -> 2.0000529 | AN12: =AM12/$AM$66 -> 0.020706968 | AO12: =AN12*AL12 -> 0.14494878 | AV12: 10 | AW12: 1.71 | AX12: =AW13-AW12 -> -0.061 | BB12: 10 | BC12: 1.671 | BD12: =BC13-BC12 -> -0.08 | BH12: 10 | BI12: 1.661 | BJ12: =BI13-BI12 -> -0.082 | BN12: 10 | BO12: 1.738 | BP12: =BO13-BO12 -> -0.085 | BT12: 10 | BU12: 1.843 | BV12: =BU13-BU12 -> -0.098 | CA12: 10 | CB12: 0.387 | CC12: 4.33 | CD12: 4.371 | CE12: 4.202 | CF12: =CB13-CB12 -> 0.02 | CI12: 10 | CJ12: 0.971 | CK12: 4.548 | CL12: 4.593 | CM12: 4.462 | CN12: =CJ13-CJ12 -> 0.036 | CR12: 10 | CS12: 2.376 | CT12: =CS13-CS12 -> -0.117
P13: 8 | Q13: =$Q$4/(1+$D$10)^P13 -> 1.700968 | R13: =Q13/$Q$16 -> 0.017078553 | S13: =R13*P13 -> 0.13662842 | U13: 8 | V13: =$V$4/(1+$E$10)^U13 -> 1.7390695 | W13: =V13/$V$20 -> 0.017585491 | X13: =W13*U13 -> 0.14068393 | Z13: 8 | AA13: =$AA$4/(1+$F$10)^Z13 -> 1.7805826 | AB13: =AA13/$AA$26 -> 0.018124551 | AC13: =AB13*Z13 -> 0.14499641 | AF13: 8 | AG13: =$AG$4/(1+$G$10)^AF13 -> 2.0526673 | AH13: =AG13/$AG$46 -> 0.02050092 | AI13: =AH13*AF13 -> 0.16400736 | AL13: 8 | AM13: =$AM$4/(1+$H$10)^AL13 -> 1.9515567 | AN13: =AM13/$AM$66 -> 0.020204877 | AO13: =AN13*AL13 -> 0.16163901 | AV13: 11 | AW13: 1.649 | AX13: =AW14-AW13 -> -0.162 | BB13: 11 | BC13: 1.591 | BD13: =BC14-BC13 -> -0.153 | BH13: 11 | BI13: 1.579 | BJ13: =BI14-BI13 -> -0.156 | BN13: 11 | BO13: 1.653 | BP13: =BO14-BO13 -> -0.156 | BT13: 11 | BU13: 1.745 | BV13: =BU14-BU13 -> -0.183 | CA13: 11 | CB13: 0.407 | CC13: 4.08 | CD13: 4.343 | CE13: 4.046 | CF13: =CB14-CB13 -> 0.094 | CI13: 11 | CJ13: 1.007 | CK13: 4.357 | CL13: 4.565 | CM13: 4.326 | CN13: =CJ14-CJ13 -> 0.193 | CR13: 11 | CS13: 2.259 | CT13: =CS14-CS13 -> -0.215
A14: Modified Duration bond 2 | B14: =N21/2/(1+B10) -> 1.9051138 | P14: 9 | Q14: =$Q$4/(1+$D$10)^P14 -> 1.6668803 | R14: =Q14/$Q$16 -> 0.016736295 | S14: =R14*P14 -> 0.15062666 | U14: 9 | V14: =$V$4/(1+$E$10)^U14 -> 1.7023831 | W14: =V14/$V$20 -> 0.017214518 | X14: =W14*U14 -> 0.15493066 | Z14: 9 | AA14: =$AA$4/(1+$F$10)^Z14 -> 1.7416566 | AB14: =AA14/$AA$26 -> 0.017728323 | AC14: =AB14*Z14 -> 0.15955491 | AF14: 9 | AG14: =$AG$4/(1+$G$10)^AF14 -> 2.0027 | AH14: =AG14/$AG$46 -> 0.020001873 | AI14: =AH14*AF14 -> 0.18001686 | AL14: 9 | AM14: =$AM$4/(1+$H$10)^AL14 -> 1.9042364 | AN14: =AM14/$AM$66 -> 0.01971496 | AO14: =AN14*AL14 -> 0.17743464 | AV14: 12 | AW14: 1.487 | AX14: =AW15-AW14 -> 0.044 | BB14: 12 | BC14: 1.438 | BD14: =BC15-BC14 -> 0.013 | BH14: 12 | BI14: 1.423 | BJ14: =BI15-BI14 -> -0.009 | BN14: 12 | BO14: 1.497 | BP14: =BO15-BO14 -> -0.021 | BT14: 12 | BU14: 1.562 | BV14: =BU15-BU14 -> -0.029 | CA14: 12 | CB14: 0.501 | CC14: 4.203 | CD14: 4.245 | CE14: 4.022 | CF14: =CB15-CB14 -> -0.053 | CI14: 12 | CJ14: 1.2 | CK14: 4.465 | CL14: 4.508 | CM14: 4.3 | CN14: =CJ15-CJ14 -> -0.071 | CR14: 12 | CS14: 2.044 | CT14: =CS15-CS14 -> -0.017
A15: Modified Duration bond 3 | B15: =N12/2/(1+C10) -> 2.8082459 | L15: Coupon | P15: 10 | Q15: =(100+$Q$4)/(1+$D$10)^P15 -> 83.307264 | R15: =Q15/$Q$16 -> 0.83644574 | S15: =R15*P15 -> 8.3644574 | U15: 10 | V15: =$V$4/(1+$E$10)^U15 -> 1.6664707 | W15: =V15/$V$20 -> 0.016851371 | X15: =W15*U15 -> 0.16851371 | Z15: 10 | AA15: =$AA$4/(1+$F$10)^Z15 -> 1.7035815 | AB15: =AA15/$AA$26 -> 0.017340757 | AC15: =AB15*Z15 -> 0.17340757 | AF15: 10 | AG15: =$AG$4/(1+$G$10)^AF15 -> 1.9539489 | AH15: =AG15/$AG$46 -> 0.019514975 | AI15: =AH15*AF15 -> 0.19514975 | AL15: 10 | AM15: =$AM$4/(1+$H$10)^AL15 -> 1.8580635 | AN15: =AM15/$AM$66 -> 0.019236922 | AO15: =AN15*AL15 -> 0.19236922 | AV15: 13 | AW15: 1.531 | AX15: =AW16-AW15 -> -0.021 | BB15: 13 | BC15: 1.451 | BD15: =BC16-BC15 -> -0.019 | BH15: 13 | BI15: 1.414 | BJ15: =BI16-BI15 -> -0.023 | BN15: 13 | BO15: 1.476 | BP15: =BO16-BO15 -> -0.021 | BT15: 13 | BU15: 1.533 | BV15: =BU16-BU15 -> -0.034 | CA15: 13 | CB15: 0.448 | CC15: 4.293 | CD15: 4.35 | CE15: 4.186 | CF15: =CB16-CB15 -> 0.052 | CI15: 13 | CJ15: 1.129 | CK15: 4.518 | CL15: 4.619 | CM15: 4.45 | CN15: =CJ16-CJ15 -> 0.147 | CR15: 13 | CS15: 2.027 | CT15: =CS16-CS15 -> -0.064
A16: Modified Duration bond 5 | B16: =S16/2/(1+D10) -> 4.4882984 | K16: Bond 2 yr | L16: =(100*B6)/2 -> 1.9375 | Q16: =SUM(Q6:Q15) -> 99.596734 | R16: =Q16/$Q$16 -> 1 | S16: =SUM(S6:S15) -> 9.1601681 | U16: 11 | V16: =$V$4/(1+$E$10)^U16 -> 1.6313158 | W16: =V16/$V$20 -> 0.016495884 | X16: =W16*U16 -> 0.18145473 | Z16: 11 | AA16: =$AA$4/(1+$F$10)^Z16 -> 1.6663388 | AB16: =AA16/$AA$26 -> 0.016961664 | AC16: =AB16*Z16 -> 0.1865783 | AF16: 11 | AG16: =$AG$4/(1+$G$10)^AF16 -> 1.9063846 | AH16: =AG16/$AG$46 -> 0.019039929 | AI16: =AH16*AF16 -> 0.20943921 | AL16: 11 | AM16: =$AM$4/(1+$H$10)^AL16 -> 1.8130102 | AN16: =AM16/$AM$66 -> 0.018770476 | AO16: =AN16*AL16 -> 0.20647524 | AV16: 14 | AW16: 1.51 | AX16: =AW17-AW16 -> 0.03 | BB16: 14 | BC16: 1.432 | BD16: =BC17-BC16 -> 0.043 | BH16: 14 | BI16: 1.391 | BJ16: =BI17-BI16 -> 0.04 | BN16: 14 | BO16: 1.455 | BP16: =BO17-BO16 -> 0.053 | BT16: 14 | BU16: 1.499 | BV16: =BU17-BU16 -> 0.061 | CA16: 14 | CB16: 0.5 | CC16: 4.328 | CD16: 4.401 | CE16: 4.249 | CF16: =CB17-CB16 -> 0.005 | CI16: 14 | CJ16: 1.276 | CK16: 4.601 | CL16: 4.662 | CM16: 4.503 | CN16: =CJ17-CJ16 -> -0.016 | CR16: 14 | CS16: 1.963 | CT16: =CS17-CS16 -> 0.062
A17: Modified Duration bond 7 | B17: =X20/2/(1+E10) -> 6.0154595 | K17: 1 | L17: =$L$16/((1+$B$10)^K17) -> 1.8991374 | M17: =L17/$L$21 -> 0.019051192 | N17: =M17*K17 -> 0.019051192 | U17: 12 | V17: =$V$4/(1+$E$10)^U17 -> 1.5969026 | W17: =V17/$V$20 -> 0.016147897 | X17: =W17*U17 -> 0.19377477 | Z17: 12 | AA17: =$AA$4/(1+$F$10)^Z17 -> 1.6299104 | AB17: =AA17/$AA$26 -> 0.016590858 | AC17: =AB17*Z17 -> 0.1990903 | AF17: 12 | AG17: =$AG$4/(1+$G$10)^AF17 -> 1.8599782 | AH17: =AG17/$AG$46 -> 0.018576446 | AI17: =AH17*AF17 -> 0.22291735 | AL17: 12 | AM17: =$AM$4/(1+$H$10)^AL17 -> 1.7690494 | AN17: =AM17/$AM$66 -> 0.01831534 | AO17: =AN17*AL17 -> 0.21978408 | AV17: 15 | AW17: 1.54 | AX17: =AW18-AW17 -> 0.264 | BB17: 15 | BC17: 1.475 | BD17: =BC18-BC17 -> 0.291 | BH17: 15 | BI17: 1.431 | BJ17: =BI18-BI17 -> 0.326 | BN17: 15 | BO17: 1.508 | BP17: =BO18-BO17 -> 0.328 | BT17: 15 | BU17: 1.56 | BV17: =BU18-BU17 -> 0.341 | CA17: 15 | CB17: 0.505 | CC17: 4.193 | CD17: 4.355 | CE17: 4.135 | CF17: =CB18-CB17 -> -0.055 | CI17: 15 | CJ17: 1.26 | CK17: 4.523 | CL17: 4.611 | CM17: 4.455 | CN17: =CJ18-CJ17 -> -0.06 | CR17: 15 | CS17: 2.025 | CT17: =CS18-CS17 -> 0.35
A18: Modified Duration bond 10 | B18: =AC26/2/(1+F10) -> 8.0508721 | K18: 2 | L18: =$L$16/((1+$B$10)^K18) -> 1.8615344 | M18: =L18/$L$21 -> 0.018673978 | N18: =M18*K18 -> 0.037347956 | U18: 13 | V18: =$V$4/(1+$E$10)^U18 -> 1.5632153 | W18: =V18/$V$20 -> 0.015807251 | X18: =W18*U18 -> 0.20549426 | Z18: 13 | AA18: =$AA$4/(1+$F$10)^Z18 -> 1.5942782 | AB18: =AA18/$AA$26 -> 0.016228159 | AC18: =AB18*Z18 -> 0.21096606 | AF18: 13 | AG18: =$AG$4/(1+$G$10)^AF18 -> 1.8147014 | AH18: =AG18/$AG$46 -> 0.018124246 | AI18: =AH18*AF18 -> 0.2356152 | AL18: 13 | AM18: =$AM$4/(1+$H$10)^AL18 -> 1.7261544 | AN18: =AM18/$AM$66 -> 0.01787124 | AO18: =AN18*AL18 -> 0.23232612 | AV18: 16 | AW18: 1.804 | AX18: =AW19-AW18 -> -0.117 | BB18: 16 | BC18: 1.766 | BD18: =BC19-BC18 -> -0.145 | BH18: 16 | BI18: 1.757 | BJ18: =BI19-BI18 -> -0.157 | BN18: 16 | BO18: 1.836 | BP18: =BO19-BO18 -> -0.167 | BT18: 16 | BU18: 1.901 | BV18: =BU19-BU18 -> -0.179 | CA18: 16 | CB18: 0.45 | CC18: 4.043 | CD18: 4.194 | CE18: 4.041 | CF18: =CB19-CB18 -> 0.029 | CI18: 16 | CJ18: 1.2 | CK18: 4.356 | CL18: 4.495 | CM18: 4.352 | CN18: =CJ19-CJ18 -> 0.034 | CR18: 16 | CS18: 2.375 | CT18: =CS19-CS18 -> -0.216
A19: Modified Duration bond 20 | B19: =AI46/2/(1+G10) -> 12.556771 | K19: 3 | L19: =$L$16/((1+$B$10)^K19) -> 1.824676 | M19: =L19/$L$21 -> 0.018304232 | N19: =M19*K19 -> 0.054912697 | U19: 14 | V19: =(100+$V$4)/(1+$E$10)^U19 -> 75.723627 | W19: =V19/$V$20 -> 0.7657182 | X19: =W19*U19 -> 10.720055 | Z19: 14 | AA19: =$AA$4/(1+$F$10)^Z19 -> 1.5594251 | AB19: =AA19/$AA$26 -> 0.015873388 | AC19: =AB19*Z19 -> 0.22222744 | AF19: 14 | AG19: =$AG$4/(1+$G$10)^AF19 -> 1.7705267 | AH19: =AG19/$AG$46 -> 0.017683054 | AI19: =AH19*AF19 -> 0.24756276 | AL19: 14 | AM19: =$AM$4/(1+$H$10)^AL19 -> 1.6842996 | AN19: =AM19/$AM$66 -> 0.017437908 | AO19: =AN19*AL19 -> 0.24413071 | AV19: 17 | AW19: 1.687 | AX19: =AW20-AW19 -> -0.049 | BB19: 17 | BC19: 1.621 | BD19: =BC20-BC19 -> -0.045 | BH19: 17 | BI19: 1.6 | BJ19: =BI20-BI19 -> -0.035 | BN19: 17 | BO19: 1.669 | BP19: =BO20-BO19 -> -0.039 | BT19: 17 | BU19: 1.722 | BV19: =BU20-BU19 -> -0.035 | CA19: 17 | CB19: 0.479 | CC19: 4.101 | CD19: 4.106 | CE19: 3.786 | CF19: =CB20-CB19 -> -0.022 | CI19: 17 | CJ19: 1.234 | CK19: 4.493 | CL19: 4.494 | CM19: 4.163 | CN19: =CJ20-CJ19 -> -0.056 | CR19: 17 | CS19: 2.159 | CT19: =CS20-CS19 -> -0.028
A20: Modified Duration bond 30 | B20: =AO66/2/(1+H10) -> 15.651927 | K20: 4 | L20: =(100+$L$16)/((1+$B$10)^K20) -> 94.100667 | M20: =L20/$L$21 -> 0.9439706 | N20: =M20*K20 -> 3.7758824 | V20: =SUM(V6:V19) -> 98.892292 | W20: =V20/$V$20 -> 1 | X20: =SUM(X6:X19) -> 12.290185 | Z20: 15 | AA20: =$AA$4/(1+$F$10)^Z20 -> 1.5253339 | AB20: =AA20/$AA$26 -> 0.015526374 | AC20: =AB20*Z20 -> 0.23289561 | AF20: 15 | AG20: =$AG$4/(1+$G$10)^AF20 -> 1.7274274 | AH20: =AG20/$AG$46 -> 0.017252602 | AI20: =AH20*AF20 -> 0.25878902 | AL20: 15 | AM20: =$AM$4/(1+$H$10)^AL20 -> 1.6434596 | AN20: =AM20/$AM$66 -> 0.017015083 | AO20: =AN20*AL20 -> 0.25522624 | AV20: 18 | AW20: 1.638 | AX20: =AW21-AW20 -> -0.232 | BB20: 18 | BC20: 1.576 | BD20: =BC21-BC20 -> -0.215 | BH20: 18 | BI20: 1.565 | BJ20: =BI21-BI20 -> -0.216 | BN20: 18 | BO20: 1.63 | BP20: =BO21-BO20 -> -0.184 | BT20: 18 | BU20: 1.687 | BV20: =BU21-BU20 -> -0.158 | CA20: 18 | CB20: 0.457 | CC20: 4.11 | CD20: 4.162 | CE20: 4.044 | CF20: =CB21-CB20 -> 0.029 | CI20: 18 | CJ20: 1.178 | CK20: 4.466 | CL20: 4.541 | CM20: 4.41 | CN20: =CJ21-CJ20 -> 0.08 | CR20: 18 | CS20: 2.131 | CT20: =CS21-CS20 -> -0.117
L21: =SUM(L17:L20) -> 99.686015 | M21: =L21/$L$21 -> 1 | N21: =SUM(N17:N20) -> 3.8871942 | Z21: 16 | AA21: =$AA$4/(1+$F$10)^Z21 -> 1.4919879 | AB21: =AA21/$AA$26 -> 0.015186946 | AC21: =AB21*Z21 -> 0.24299113 | AF21: 16 | AG21: =$AG$4/(1+$G$10)^AF21 -> 1.6853773 | AH21: =AG21/$AG$46 -> 0.016832628 | AI21: =AH21*AF21 -> 0.26932204 | AL21: 16 | AM21: =$AM$4/(1+$H$10)^AL21 -> 1.6036099 | AN21: =AM21/$AM$66 -> 0.01660251 | AO21: =AN21*AL21 -> 0.26564017 | AV21: 19 | AW21: 1.406 | AX21: =AW22-AW21 -> 0.191 | BB21: 19 | BC21: 1.361 | BD21: =BC22-BC21 -> 0.207 | BH21: 19 | BI21: 1.349 | BJ21: =BI22-BI21 -> 0.207 | BN21: 19 | BO21: 1.446 | BP21: =BO22-BO21 -> 0.2 | BT21: 19 | BU21: 1.529 | BV21: =BU22-BU21 -> 0.205 | CA21: 19 | CB21: 0.486 | CC21: 3.935 | CD21: 4.168 | CE21: 3.927 | CF21: =CB22-CB21 -> 0.065 | CI21: 19 | CJ21: 1.258 | CK21: 4.33 | CL21: 4.529 | CM21: 4.326 | CN21: =CJ22-CJ21 -> 0.08 | CR21: 19 | CS21: 2.014 | CT21: =CS22-CS21 -> 0.183
Z22: 17 | AA22: =$AA$4/(1+$F$10)^Z22 -> 1.459371 | AB22: =AA22/$AA$26 -> 0.014854938 | AC22: =AB22*Z22 -> 0.25253394 | AF22: 17 | AG22: =$AG$4/(1+$G$10)^AF22 -> 1.6443507 | AH22: =AG22/$AG$46 -> 0.016422877 | AI22: =AH22*AF22 -> 0.27918891 | AL22: 17 | AM22: =$AM$4/(1+$H$10)^AL22 -> 1.5647264 | AN22: =AM22/$AM$66 -> 0.016199942 | AO22: =AN22*AL22 -> 0.27539901 | AV22: 20 | AW22: 1.597 | AX22: =AW23-AW22 -> -0.019 | BB22: 20 | BC22: 1.568 | BD22: =BC23-BC22 -> -0.013 | BH22: 20 | BI22: 1.556 | BJ22: =BI23-BI22 -> 0.01 | BN22: 20 | BO22: 1.646 | BP22: =BO23-BO22 -> 0.01 | BT22: 20 | BU22: 1.734 | BV22: =BU23-BU22 -> 0.02 | CA22: 20 | CB22: 0.551 | CC22: 4.036 | CD22: 4.061 | CE22: 3.863 | CF22: =CB23-CB22 -> -0.02 | CI22: 20 | CJ22: 1.338 | CK22: 4.358 | CL22: 4.387 | CM22: 4.267 | CN22: =CJ23-CJ22 -> -0.035 | CR22: 20 | CS22: 2.197 | CT22: =CS23-CS22 -> 0.052
Z23: 18 | AA23: =$AA$4/(1+$F$10)^Z23 -> 1.4274671 | AB23: =AA23/$AA$26 -> 0.014530188 | AC23: =AB23*Z23 -> 0.26154339 | AF23: 18 | AG23: =$AG$4/(1+$G$10)^AF23 -> 1.6043229 | AH23: =AG23/$AG$46 -> 0.0160231 | AI23: =AH23*AF23 -> 0.28841581 | AL23: 18 | AM23: =$AM$4/(1+$H$10)^AL23 -> 1.5267858 | AN23: =AM23/$AM$66 -> 0.015807135 | AO23: =AN23*AL23 -> 0.28452842 | AV23: 21 | AW23: 1.578 | AX23: =AW24-AW23 -> 0.046 | BB23: 21 | BC23: 1.555 | BD23: =BC24-BC23 -> 0.067 | BH23: 21 | BI23: 1.566 | BJ23: =BI24-BI23 -> 0.06 | BN23: 21 | BO23: 1.656 | BP23: =BO24-BO23 -> 0.057 | BT23: 21 | BU23: 1.754 | BV23: =BU24-BU23 -> 0.045 | CA23: 21 | CB23: 0.531 | CC23: 3.919 | CD23: 4.114 | CE23: 3.884 | CF23: =CB24-CB23 -> 0.075 | CI23: 21 | CJ23: 1.303 | CK23: 4.222 | CL23: 4.396 | CM23: 4.188 | CN23: =CJ24-CJ23 -> 0.1 | CR23: 21 | CS23: 2.249 | CT23: =CS24-CS23 -> 0.04
Z24: 19 | AA24: =$AA$4/(1+$F$10)^Z24 -> 1.3962607 | AB24: =AA24/$AA$26 -> 0.014212538 | AC24: =AB24*Z24 -> 0.27003822 | AF24: 19 | AG24: =$AG$4/(1+$G$10)^AF24 -> 1.5652694 | AH24: =AG24/$AG$46 -> 0.015633056 | AI24: =AH24*AF24 -> 0.29702806 | AL24: 19 | AM24: =$AM$4/(1+$H$10)^AL24 -> 1.4897651 | AN24: =AM24/$AM$66 -> 0.015423852 | AO24: =AN24*AL24 -> 0.29305319 | AV24: 22 | AW24: 1.624 | AX24: =AW25-AW24 -> -0.07 | BB24: 22 | BC24: 1.622 | BD24: =BC25-BC24 -> -0.076 | BH24: 22 | BI24: 1.626 | BJ24: =BI25-BI24 -> -0.082 | BN24: 22 | BO24: 1.713 | BP24: =BO25-BO24 -> -0.083 | BT24: 22 | BU24: 1.799 | BV24: =BU25-BU24 -> -0.085 | CA24: 22 | CB24: 0.606 | CC24: 3.916 | CD24: 3.93 | CE24: 3.803 | CF24: =CB25-CB24 -> 0.038 | CI24: 22 | CJ24: 1.403 | CK24: 4.217 | CL24: 4.22 | CM24: 4.094 | CN24: =CJ25-CJ24 -> 0.021 | CR24: 22 | CS24: 2.289 | CT24: =CS25-CS24 -> -0.096
Z25: 20 | AA25: =(100+$AA$4)/(1+$F$10)^Z25 -> 65.635688 | AB25: =AA25/$AA$26 -> 0.66810569 | AC25: =AB25*Z25 -> 13.362114 | AF25: 20 | AG25: =$AG$4/(1+$G$10)^AF25 -> 1.5271666 | AH25: =AG25/$AG$46 -> 0.015252506 | AI25: =AH25*AF25 -> 0.30505011 | AL25: 20 | AM25: =$AM$4/(1+$H$10)^AL25 -> 1.4536421 | AN25: =AM25/$AM$66 -> 0.015049863 | AO25: =AN25*AL25 -> 0.30099726 | AV25: 23 | AW25: 1.554 | AX25: =AW26-AW25 -> 0.126 | BB25: 23 | BC25: 1.546 | BD25: =BC26-BC25 -> 0.165 | BH25: 23 | BI25: 1.544 | BJ25: =BI26-BI25 -> 0.207 | BN25: 23 | BO25: 1.63 | BP25: =BO26-BO25 -> 0.232 | BT25: 23 | BU25: 1.714 | BV25: =BU26-BU25 -> 0.231 | CA25: 23 | CB25: 0.644 | CC25: 3.952 | CD25: 3.99 | CE25: 3.843 | CF25: =CB26-CB25 -> -0.052 | CI25: 23 | CJ25: 1.424 | CK25: 4.215 | CL25: 4.258 | CM25: 4.143 | CN25: =CJ26-CJ25 -> -0.054 | CR25: 23 | CS25: 2.193 | CT25: =CS26-CS25 -> 0.234
AA26: =SUM(AA6:AA25) -> 98.241474 | AB26: =AA26/$AA$26 -> 1 | AC26: =SUM(AC6:AC25) -> 16.461618 | AF26: 21 | AG26: =$AG$4/(1+$G$10)^AF26 -> 1.4899913 | AH26: =AG26/$AG$46 -> 0.014881219 | AI26: =AH26*AF26 -> 0.31250561 | AL26: 21 | AM26: =$AM$4/(1+$H$10)^AL26 -> 1.418395 | AN26: =AM26/$AM$66 -> 0.014684942 | AO26: =AN26*AL26 -> 0.30838378 | AV26: 24 | AW26: 1.68 | AX26: =AW27-AW26 -> -0.066 | BB26: 24 | BC26: 1.711 | BD26: =BC27-BC26 -> -0.094 | BH26: 24 | BI26: 1.751 | BJ26: =BI27-BI26 -> -0.098 | BN26: 24 | BO26: 1.862 | BP26: =BO27-BO26 -> -0.11 | BT26: 24 | BU26: 1.945 | BV26: =BU27-BU26 -> -0.109 | CA26: 24 | CB26: 0.592 | CC26: 4.283 | CD26: 4.341 | CE26: 3.889 | CF26: =CB27-CB26 -> 0.062 | CI26: 24 | CJ26: 1.37 | CK26: 4.501 | CL26: 4.555 | CM26: 4.176 | CN26: =CJ27-CJ26 -> 0.051 | CR26: 24 | CS26: 2.427 | CT26: =CS27-CS26 -> -0.119
AF27: 22 | AG27: =$AG$4/(1+$G$10)^AF27 -> 1.453721 | AH27: =AG27/$AG$46 -> 0.014518971 | AI27: =AH27*AF27 -> 0.31941736 | AL27: 22 | AM27: =$AM$4/(1+$H$10)^AL27 -> 1.3840026 | AN27: =AM27/$AM$66 -> 0.01432887 | AO27: =AN27*AL27 -> 0.31523513 | AV27: 25 | AW27: 1.614 | AX27: =AW28-AW27 -> 0.012 | BB27: 25 | BC27: 1.617 | BD27: =BC28-BC27 -> -0.006 | BH27: 25 | BI27: 1.653 | BJ27: =BI28-BI27 -> -0.029 | BN27: 25 | BO27: 1.752 | BP27: =BO28-BO27 -> -0.044 | BT27: 25 | BU27: 1.836 | BV27: =BU28-BU27 -> -0.065 | CA27: 25 | CB27: 0.654 | CC27: 4.23 | CD27: 4.326 | CE27: 4.136 | CF27: =CB28-CB27 -> -0.048 | CI27: 25 | CJ27: 1.421 | CK27: 4.575 | CL27: 4.636 | CM27: 4.383 | CN27: =CJ28-CJ27 -> -0.1 | CR27: 25 | CS27: 2.308 | CT27: =CS28-CS27 -> -0.089
AF28: 23 | AG28: =$AG$4/(1+$G$10)^AF28 -> 1.4183335 | AH28: =AG28/$AG$46 -> 0.014165541 | AI28: =AH28*AF28 -> 0.32580744 | AL28: 23 | AM28: =$AM$4/(1+$H$10)^AL28 -> 1.350444 | AN28: =AM28/$AM$66 -> 0.013981431 | AO28: =AN28*AL28 -> 0.32157291 | AV28: 26 | AW28: 1.626 | AX28: =AW29-AW28 -> -0.014 | BB28: 26 | BC28: 1.611 | BD28: =BC29-BC28 -> -0.002 | BH28: 26 | BI28: 1.624 | BJ28: =BI29-BI28 -> 0 | BN28: 26 | BO28: 1.708 | BP28: =BO29-BO28 -> 0.021 | BT28: 26 | BU28: 1.771 | BV28: =BU29-BU28 -> 0.003 | CA28: 26 | CB28: 0.606 | CC28: 4.535 | CD28: 4.56 | CE28: 4.201 | CF28: =CB29-CB28 -> 0.008 | CI28: 26 | CJ28: 1.321 | CK28: 4.821 | CL28: 4.841 | CM28: 4.559 | CN28: =CJ29-CJ28 -> 0.043 | CR28: 26 | CS28: 2.219 | CT28: =CS29-CS28 -> -0.016
B29: 5-Year Bond Yield | C29: 7-Year Bond Yield | D29: 10-Year Bond Yield | G29: Standard deviation | H29: Price Value Basis Point | AF29: 24 | AG29: =$AG$4/(1+$G$10)^AF29 -> 1.3838075 | AH29: =AG29/$AG$46 -> 0.013820714 | AI29: =AH29*AF29 -> 0.33169713 | AL29: 24 | AM29: =$AM$4/(1+$H$10)^AL29 -> 1.3176992 | AN29: =AM29/$AM$66 -> 0.013642417 | AO29: =AN29*AL29 -> 0.32741801 | AV29: 27 | AW29: 1.612 | AX29: =AW30-AW29 -> 0.007 | BB29: 27 | BC29: 1.609 | BD29: =BC30-BC29 -> 0.035 | BH29: 27 | BI29: 1.624 | BJ29: =BI30-BI29 -> 0.044 | BN29: 27 | BO29: 1.729 | BP29: =BO30-BO29 -> 0.049 | BT29: 27 | BU29: 1.774 | BV29: =BU30-BU29 -> 0.069 | CA29: 27 | CB29: 0.614 | CC29: 4.489 | CD29: 4.537 | CE29: 4.394 | CF29: =CB30-CB29 -> 0.091 | CI29: 27 | CJ29: 1.364 | CK29: 4.826 | CL29: 4.852 | CM29: 4.706 | CN29: =CJ30-CJ29 -> 0.169 | CR29: 27 | CS29: 2.203 | CT29: =CS30-CS29 -> 0.081
A30: Coupon | B30: 0.04 | C30: 0.04125 | D30: 0.0425 | F30: Bond 5-y | G30: 0.13424646 | H30: =B16*D8*0.0001 -> 0.044685498 | J30: Correlation B5 - B7 | K30: 0.97972709 | AF30: 25 | AG30: =$AG$4/(1+$G$10)^AF30 -> 1.350122 | AH30: =AG30/$AG$46 -> 0.013484281 | AI30: =AH30*AF30 -> 0.33710703 | AL30: 25 | AM30: =$AM$4/(1+$H$10)^AL30 -> 1.2857484 | AN30: =AM30/$AM$66 -> 0.013311623 | AO30: =AN30*AL30 -> 0.33279058 | AV30: 28 | AW30: 1.619 | AX30: =AW31-AW30 -> -0.011 | BB30: 28 | BC30: 1.644 | BD30: =BC31-BC30 -> -0.019 | BH30: 28 | BI30: 1.668 | BJ30: =BI31-BI30 -> -0.012 | BN30: 28 | BO30: 1.778 | BP30: =BO31-BO30 -> -0.016 | BT30: 28 | BU30: 1.843 | BV30: =BU31-BU30 -> -0.019 | CA30: 28 | CB30: 0.705 | CC30: 4.71 | CD30: 4.755 | CE30: 4.396 | CF30: =CB31-CB30 -> -0.078 | CI30: 28 | CJ30: 1.533 | CK30: 4.983 | CL30: 5.02 | CM30: 4.759 | CN30: =CJ31-CJ30 -> -0.114 | CR30: 28 | CS30: 2.284 | CT30: =CS31-CS30 -> -0.03
A31: Maturity | B31: 31.05.2030 | C31: 31.05.2032 | D31: 15.05.2035 | F31: Bond 7-y | G31: 0.13216548 | H31: =B17*E8*0.0001 -> 0.059420709 | J31: Correlation B5 - B10 | K31: 0.93035485 | AF31: 26 | AG31: =$AG$4/(1+$G$10)^AF31 -> 1.3172565 | AH31: =AG31/$AG$46 -> 0.013156038 | AI31: =AH31*AF31 -> 0.34205699 | AL31: 26 | AM31: =$AM$4/(1+$H$10)^AL31 -> 1.2545722 | AN31: =AM31/$AM$66 -> 0.01298885 | AO31: =AN31*AL31 -> 0.3377101 | AV31: 29 | AW31: 1.608 | AX31: =AW32-AW31 -> 0.024 | BB31: 29 | BC31: 1.625 | BD31: =BC32-BC31 -> 0.038 | BH31: 29 | BI31: 1.656 | BJ31: =BI32-BI31 -> 0.078 | BN31: 29 | BO31: 1.762 | BP31: =BO32-BO31 -> 0.087 | BT31: 29 | BU31: 1.824 | BV31: =BU32-BU31 -> 0.095 | CA31: 29 | CB31: 0.627 | CC31: 4.578 | CD31: 4.715 | CE31: 4.517 | CF31: =CB32-CB31 -> 0.033 | CI31: 29 | CJ31: 1.419 | CK31: 4.959 | CL31: 5.02 | CM31: 4.806 | CN31: =CJ32-CJ31 -> 0.066 | CR31: 29 | CS31: 2.254 | CT31: =CS32-CS31 -> 0.09
A32: Price (USD) | B32: 99.56 | C32: 98.78 | D32: 98.31 | F32: Bond 10-y | G32: 0.12806445 | H32: =B18*F8*0.0001 -> 0.079148124 | J32: Correlation B7 - B10 | K32: 0.98048245 | AF32: 27 | AG32: =$AG$4/(1+$G$10)^AF32 -> 1.2851909 | AH32: =AG32/$AG$46 -> 0.012835785 | AI32: =AH32*AF32 -> 0.3465662 | AL32: 27 | AM32: =$AM$4/(1+$H$10)^AL32 -> 1.2241521 | AN32: =AM32/$AM$66 -> 0.012673904 | AO32: =AN32*AL32 -> 0.3421954 | AV32: 30 | AW32: 1.632 | AX32: =AW33-AW32 -> -0.045 | BB32: 30 | BC32: 1.663 | BD32: =BC33-BC32 -> -0.063 | BH32: 30 | BI32: 1.734 | BJ32: =BI33-BI32 -> -0.056 | BN32: 30 | BO32: 1.849 | BP32: =BO33-BO32 -> -0.049 | BT32: 30 | BU32: 1.919 | BV32: =BU33-BU32 -> -0.042 | CA32: 30 | CB32: 0.66 | CC32: 4.883 | CD32: 4.939 | CE32: 4.501 | CF32: =CB33-CB32 -> -0.013 | CI32: 30 | CJ32: 1.485 | CK32: 5.241 | CL32: 5.289 | CM32: 4.851 | CN32: =CJ33-CJ32 -> -0.026 | CR32: 30 | CS32: 2.344 | CT32: =CS33-CS32 -> -0.026
A33: Yield | B33: 0.0409 | C33: 0.0431 | D33: 0.0447 | AF33: 28 | AG33: =$AG$4/(1+$G$10)^AF33 -> 1.253906 | AH33: =AG33/$AG$46 -> 0.012523328 | AI33: =AH33*AF33 -> 0.35065319 | AL33: 28 | AM33: =$AM$4/(1+$H$10)^AL33 -> 1.1944695 | AN33: =AM33/$AM$66 -> 0.012366594 | AO33: =AN33*AL33 -> 0.34626463 | AV33: 31 | AW33: 1.587 | AX33: =AW34-AW33 -> -0.054 | BB33: 31 | BC33: 1.6 | BD33: =BC34-BC33 -> -0.054 | BH33: 31 | BI33: 1.678 | BJ33: =BI34-BI33 -> -0.084 | BN33: 31 | BO33: 1.8 | BP33: =BO34-BO33 -> -0.091 | BT33: 31 | BU33: 1.877 | BV33: =BU34-BU33 -> -0.084 | CA33: 31 | CB33: 0.647 | CC33: 4.958 | CD33: 5.019 | CE33: 4.817 | CF33: =CB34-CB33 -> 0.001 | CI33: 31 | CJ33: 1.459 | CK33: 5.332 | CL33: 5.388 | CM33: 5.144 | CN33: =CJ34-CJ33 -> -0.016 | CR33: 31 | CS33: 2.318 | CT33: =CS34-CS33 -> -0.069
B34: =B33/2 -> 0.02045 | C34: =C33/2 -> 0.02155 | D34: =D33/2 -> 0.02235 | AF34: 29 | AG34: =$AG$4/(1+$G$10)^AF34 -> 1.2233826 | AH34: =AG34/$AG$46 -> 0.012218477 | AI34: =AH34*AF34 -> 0.35433584 | AL34: 29 | AM34: =$AM$4/(1+$H$10)^AL34 -> 1.1655067 | AN34: =AM34/$AM$66 -> 0.012066735 | AO34: =AN34*AL34 -> 0.34993533 | AV34: 32 | AW34: 1.533 | AX34: =AW35-AW34 -> 0.037 | BB34: 32 | BC34: 1.546 | BD34: =BC35-BC34 -> 0.04 | BH34: 32 | BI34: 1.594 | BJ34: =BI35-BI34 -> 0.039 | BN34: 32 | BO34: 1.709 | BP34: =BO35-BO34 -> 0.031 | BT34: 32 | BU34: 1.793 | BV34: =BU35-BU34 -> 0.027 | CA34: 32 | CB34: 0.648 | CC34: 4.682 | CD34: 5.031 | CE34: 4.675 | CF34: =CB35-CB34 -> 0.165 | CI34: 32 | CJ34: 1.443 | CK34: 5.001 | CL34: 5.363 | CM34: 4.997 | CN34: =CJ35-CJ34 -> 0.227 | CR34: 32 | CS34: 2.249 | CT34: =CS35-CS34 -> 0.03
AF35: 30 | AG35: =$AG$4/(1+$G$10)^AF35 -> 1.1936022 | AH35: =AG35/$AG$46 -> 0.011921047 | AI35: =AH35*AF35 -> 0.35763141 | AL35: 30 | AM35: =$AM$4/(1+$H$10)^AL35 -> 1.1372461 | AN35: =AM35/$AM$66 -> 0.011774148 | AO35: =AN35*AL35 -> 0.35322444 | AV35: 33 | AW35: 1.57 | AX35: =AW36-AW35 -> -0.005 | BB35: 33 | BC35: 1.586 | BD35: =BC36-BC35 -> -0.011 | BH35: 33 | BI35: 1.633 | BJ35: =BI36-BI35 -> -0.01 | BN35: 33 | BO35: 1.74 | BP35: =BO36-BO35 -> -0.005 | BT35: 33 | BU35: 1.82 | BV35: =BU36-BU35 -> 0.005 | CA35: 33 | CB35: 0.813 | CC35: 4.627 | CD35: 4.753 | CE35: 4.561 | CF35: =CB36-CB35 -> -0.04 | CI35: 33 | CJ35: 1.67 | CK35: 5.009 | CL35: 5.109 | CM35: 4.869 | CN35: =CJ36-CJ35 -> -0.032 | CR35: 33 | CS35: 2.279 | CT35: =CS36-CS35 -> 0.006
A36: Conventional | B36: Q2 = | C36: =-(H31/H30)*100 -> -132.97537 | AF36: 31 | AG36: =$AG$4/(1+$G$10)^AF36 -> 1.1645468 | AH36: =AG36/$AG$46 -> 0.011630857 | AI36: =AH36*AF36 -> 0.36055657 | AL36: 31 | AM36: =$AM$4/(1+$H$10)^AL36 -> 1.1096708 | AN36: =AM36/$AM$66 -> 0.011488655 | AO36: =AN36*AL36 -> 0.3561483 | AV36: 34 | AW36: 1.565 | AX36: =AW37-AW36 -> -0.07 | BB36: 34 | BC36: 1.575 | BD36: =BC37-BC36 -> -0.094 | BH36: 34 | BI36: 1.623 | BJ36: =BI37-BI36 -> -0.114 | BN36: 34 | BO36: 1.735 | BP36: =BO37-BO36 -> -0.131 | BT36: 34 | BU36: 1.825 | BV36: =BU37-BU36 -> -0.139 | CA36: 34 | CB36: 0.773 | CC36: 4.659 | CD36: 4.913 | CE36: 4.646 | CF36: =CB37-CB36 -> -0.011 | CI36: 34 | CJ36: 1.638 | CK36: 4.935 | CL36: 5.252 | CM36: 4.923 | CN36: =CJ37-CJ36 -> 0.015 | CR36: 34 | CS36: 2.285 | CT36: =CS37-CS36 -> -0.15
B37: Q3 = | C37: =-(H31/H32)*100 -> -75.075322 | AF37: 32 | AG37: =$AG$4/(1+$G$10)^AF37 -> 1.1361986 | AH37: =AG37/$AG$46 -> 0.011347731 | AI37: =AH37*AF37 -> 0.3631274 | AL37: 32 | AM37: =$AM$4/(1+$H$10)^AL37 -> 1.0827641 | AN37: =AM37/$AM$66 -> 0.011210084 | AO37: =AN37*AL37 -> 0.35872269 | AV37: 35 | AW37: 1.495 | AX37: =AW38-AW37 -> -0.176 | BB37: 35 | BC37: 1.481 | BD37: =BC38-BC37 -> -0.184 | BH37: 35 | BI37: 1.509 | BJ37: =BI38-BI37 -> -0.194 | BN37: 35 | BO37: 1.604 | BP37: =BO38-BO37 -> -0.184 | BT37: 35 | BU37: 1.686 | BV37: =BU38-BU37 -> -0.181 | CA37: 35 | CB37: 0.762 | CC37: 4.526 | CD37: 4.756 | CE37: 4.526 | CF37: =CB38-CB37 -> 0 | CI37: 35 | CJ37: 1.653 | CK37: 4.724 | CL37: 5.009 | CM37: 4.722 | CN37: =CJ38-CJ37 -> -0.004 | CR37: 35 | CS37: 2.135 | CT37: =CS38-CS37 -> -0.138
AF38: 33 | AG38: =$AG$4/(1+$G$10)^AF38 -> 1.1085405 | AH38: =AG38/$AG$46 -> 0.011071497 | AI38: =AH38*AF38 -> 0.36535941 | AL38: 33 | AM38: =$AM$4/(1+$H$10)^AL38 -> 1.0565098 | AN38: =AM38/$AM$66 -> 0.010938268 | AO38: =AN38*AL38 -> 0.36096285 | AV38: 36 | AW38: 1.319 | AX38: =AW39-AW38 -> 0.082 | BB38: 36 | BC38: 1.297 | BD38: =BC39-BC38 -> 0.091 | BH38: 36 | BI38: 1.315 | BJ38: =BI39-BI38 -> 0.089 | BN38: 36 | BO38: 1.42 | BP38: =BO39-BO38 -> 0.085 | BT38: 36 | BU38: 1.505 | BV38: =BU39-BU38 -> 0.077 | CA38: 36 | CB38: 0.762 | CC38: 4.397 | CD38: 4.601 | CE38: 4.393 | CF38: =CB39-CB38 -> 0.062 | CI38: 36 | CJ38: 1.649 | CK38: 4.569 | CL38: 4.786 | CM38: 4.565 | CN38: =CJ39-CJ38 -> 0.137 | CR38: 36 | CS38: 1.997 | CT38: =CS39-CS38 -> 0.049
A39: Optimal | B39: Q2 = | C39: =-(((K30-(K32*K31))*H31*G31)/((1-K31^2)*H30*G30))*100 -> -65.759461 | AF39: 34 | AG39: =$AG$4/(1+$G$10)^AF39 -> 1.0815557 | AH39: =AG39/$AG$46 -> 0.010801988 | AI39: =AH39*AF39 -> 0.36726758 | AL39: 34 | AM39: =$AM$4/(1+$H$10)^AL39 -> 1.0308921 | AN39: =AM39/$AM$66 -> 0.010673043 | AO39: =AN39*AL39 -> 0.36288347 | AV39: 37 | AW39: 1.401 | AX39: =AW40-AW39 -> 0.029 | BB39: 37 | BC39: 1.388 | BD39: =BC40-BC39 -> 0.011 | BH39: 37 | BI39: 1.404 | BJ39: =BI40-BI39 -> 0.014 | BN39: 37 | BO39: 1.505 | BP39: =BO40-BO39 -> 0.005 | BT39: 37 | BU39: 1.582 | BV39: =BU40-BU39 -> 0.006 | CA39: 37 | CB39: 0.824 | CC39: 4.382 | CD39: 4.448 | CE39: 4.303 | CF39: =CB40-CB39 -> 0.023 | CI39: 37 | CJ39: 1.786 | CK39: 4.55 | CL39: 4.618 | CM39: 4.502 | CN39: =CJ40-CJ39 -> 0.047 | CR39: 37 | CS39: 2.046 | CT39: =CS40-CS39 -> -0.008
B40: Q3 = | C40: =-(((K32-(K30*K31))*H31*G31)/((1-K31^2)*H32*G32))*100 -> -39.75905 | AF40: 35 | AG40: =$AG$4/(1+$G$10)^AF40 -> 1.0552278 | AH40: =AG40/$AG$46 -> 0.010539039 | AI40: =AH40*AF40 -> 0.36886635 | AL40: 35 | AM40: =$AM$4/(1+$H$10)^AL40 -> 1.0058956 | AN40: =AM40/$AM$66 -> 0.010414249 | AO40: =AN40*AL40 -> 0.36449872 | AV40: 38 | AW40: 1.43 | AX40: =AW41-AW40 -> -0.076 | BB40: 38 | BC40: 1.399 | BD40: =BC41-BC40 -> -0.08 | BH40: 38 | BI40: 1.418 | BJ40: =BI41-BI40 -> -0.096 | BN40: 38 | BO40: 1.51 | BP40: =BO41-BO40 -> -0.105 | BT40: 38 | BU40: 1.588 | BV40: =BU41-BU40 -> -0.115 | CA40: 38 | CB40: 0.847 | CC40: 4.293 | CD40: 4.404 | CE40: 4.288 | CF40: =CB41-CB40 -> 0.125 | CI40: 38 | CJ40: 1.833 | CK40: 4.505 | CL40: 4.613 | CM40: 4.488 | CN40: =CJ41-CJ40 -> 0.142 | CR40: 38 | CS40: 2.038 | CT40: =CS41-CS40 -> -0.121
AF41: 36 | AG41: =$AG$4/(1+$G$10)^AF41 -> 1.0295407 | AH41: =AG41/$AG$46 -> 0.010282491 | AI41: =AH41*AF41 -> 0.37016966 | AL41: 36 | AM41: =$AM$4/(1+$H$10)^AL41 -> 0.98150523 | AN41: =AM41/$AM$66 -> 0.01016173 | AO41: =AN41*AL41 -> 0.36582228 | AV41: 39 | AW41: 1.354 | AX41: =AW42-AW41 -> -0.423 | BB41: 39 | BC41: 1.319 | BD41: =BC42-BC41 -> -0.403 | BH41: 39 | BI41: 1.322 | BJ41: =BI42-BI41 -> -0.37 | BN41: 39 | BO41: 1.405 | BP41: =BO42-BO41 -> -0.326 | BT41: 39 | BU41: 1.473 | BV41: =BU42-BU41 -> -0.31 | CA41: 39 | CB41: 0.972 | CC41: 4.382 | CD41: 4.385 | CE41: 4.138 | CF41: =CB42-CB41 -> 0.148 | CI41: 39 | CJ41: 1.975 | CK41: 4.505 | CL41: 4.516 | CM41: 4.37 | CN41: =CJ42-CJ41 -> 0.072 | CR41: 39 | CS41: 1.917 | CT41: =CS42-CS41 -> -0.233
AF42: 37 | AG42: =$AG$4/(1+$G$10)^AF42 -> 1.004479 | AH42: =AG42/$AG$46 -> 0.010032187 | AI42: =AH42*AF42 -> 0.37119094 | AL42: 37 | AM42: =$AM$4/(1+$H$10)^AL42 -> 0.95770623 | AN42: =AM42/$AM$66 -> 0.009915334 | AO42: =AN42*AL42 -> 0.36686736 | AV42: 40 | AW42: 0.931 | AX42: =AW43-AW42 -> -0.421 | BB42: 40 | BC42: 0.916 | BD42: =BC43-BC42 -> -0.358 | BH42: 40 | BI42: 0.952 | BJ42: =BI43-BI42 -> -0.339 | BN42: 40 | BO42: 1.079 | BP42: =BO43-BO42 -> -0.358 | BT42: 40 | BU42: 1.163 | BV42: =BU43-BU42 -> -0.39 | CA42: 40 | CB42: 1.12 | CC42: 4.352 | CD42: 4.462 | CE42: 4.289 | CF42: =CB43-CB42 -> 0.122 | CI42: 40 | CJ42: 2.047 | CK42: 4.568 | CL42: 4.663 | CM42: 4.445 | CN42: =CJ43-CJ42 -> 0.152 | CR42: 40 | CS42: 1.684 | CT42: =CS43-CS42 -> -0.387
AF43: 38 | AG43: =$AG$4/(1+$G$10)^AF43 -> 0.98002731 | AH43: =AG43/$AG$46 -> 0.0097879775 | AI43: =AH43*AF43 -> 0.37194314 | AL43: 38 | AM43: =$AM$4/(1+$H$10)^AL43 -> 0.93448429 | AN43: =AM43/$AM$66 -> 0.0096749124 | AO43: =AN43*AL43 -> 0.36764667 | AV43: 41 | AW43: 0.51 | AX43: =AW44-AW43 -> -0.002 | BB43: 41 | BC43: 0.558 | BD43: =BC44-BC43 -> 0.066 | BH43: 41 | BI43: 0.613 | BJ43: =BI44-BI43 -> 0.118 | BN43: 41 | BO43: 0.721 | BP43: =BO44-BO43 -> 0.209 | BT43: 41 | BU43: 0.773 | BV43: =BU44-BU43 -> 0.21 | CA43: 41 | CB43: 1.242 | CC43: 4.269 | CD43: 4.427 | CE43: 4.24 | CF43: =CB44-CB43 -> 0.043 | CI43: 41 | CJ43: 2.199 | CK43: 4.457 | CL43: 4.609 | CM43: 4.422 | CN43: =CJ44-CJ43 -> 0.092 | CR43: 41 | CS43: 1.297 | CT43: =CS44-CS43 -> 0.3
AF44: 39 | AG44: =$AG$4/(1+$G$10)^AF44 -> 0.95617085 | AH44: =AG44/$AG$46 -> 0.0095497121 | AI44: =AH44*AF44 -> 0.37243877 | AL44: 39 | AM44: =$AM$4/(1+$H$10)^AL44 -> 0.91182543 | AN44: =AM44/$AM$66 -> 0.0094403205 | AO44: =AN44*AL44 -> 0.3681725 | AV44: 42 | AW44: 0.508 | AX44: =AW45-AW44 -> -0.183 | BB44: 42 | BC44: 0.624 | BD44: =BC45-BC44 -> -0.237 | BH44: 42 | BI44: 0.731 | BJ44: =BI45-BI44 -> -0.25 | BN44: 42 | BO44: 0.93 | BP44: =BO45-BO44 -> -0.162 | BT44: 42 | BU44: 0.983 | BV44: =BU45-BU44 -> -0.098 | CA44: 42 | CB44: 1.285 | CC44: 4.105 | CD44: 4.268 | CE44: 4.021 | CF44: =CB45-CB44 -> 0.089 | CI44: 42 | CJ44: 2.291 | CK44: 4.374 | CL44: 4.464 | CM44: 4.296 | CN44: =CJ45-CJ44 -> 0.057 | CR44: 42 | CS44: 1.597 | CT44: =CS45-CS44 -> -0.124
AF45: 40 | AG45: =(100+$AG$4)/(1+$G$10)^AF45 -> 38.2487 | AH45: =AG45/$AG$46 -> 0.38200712 | AI45: =AH45*AF45 -> 15.280285 | AL45: 40 | AM45: =$AM$4/(1+$H$10)^AL45 -> 0.88971599 | AN45: =AM45/$AM$66 -> 0.0092114167 | AO45: =AN45*AL45 -> 0.36845667 | AV45: 43 | AW45: 0.325 | AX45: =AW46-AW45 -> -0.077 | BB45: 43 | BC45: 0.387 | BD45: =BC46-BC45 -> -0.089 | BH45: 43 | BI45: 0.481 | BJ45: =BI46-BI45 -> -0.081 | BN45: 43 | BO45: 0.768 | BP45: =BO46-BO45 -> -0.198 | BT45: 43 | BU45: 0.885 | BV45: =BU46-BU45 -> -0.209 | CA45: 43 | CB45: 1.374 | CC45: 4.083 | CD45: 4.311 | CE45: 4.047 | CF45: =CB46-CB45 -> -0.04 | CI45: 43 | CJ45: 2.348 | CK45: 4.227 | CL45: 4.508 | CM45: 4.188 | CN45: =CJ46-CJ45 -> -0.069 | CR45: 43 | CS45: 1.473 | CT45: =CS46-CS45 -> -0.229
AG46: =SUM(AG6:AG45) -> 100.12562 | AH46: =AG46/$AG$46 -> 1 | AI46: =SUM(AI6:AI45) -> 25.740126 | AL46: 41 | AM46: =$AM$4/(1+$H$10)^AL46 -> 0.86814265 | AN46: =AM46/$AM$66 -> 0.0089880634 | AO46: =AN46*AL46 -> 0.3685106 | AV46: 44 | AW46: 0.248 | AX46: =AW47-AW46 -> -0.021 | BB46: 44 | BC46: 0.298 | BD46: =BC47-BC46 -> -0.001 | BH46: 44 | BI46: 0.4 | BJ46: =BI47-BI46 -> -0.014 | BN46: 44 | BO46: 0.57 | BP46: =BO47-BO46 -> -0.051 | BT46: 44 | BU46: 0.676 | BV46: =BU47-BU46 -> -0.077 | CA46: 44 | CB46: 1.334 | CC46: 3.982 | CD46: 4.171 | CE46: 3.925 | CF46: =CB47-CB46 -> 0.029 | CI46: 44 | CJ46: 2.279 | CK46: 4.111 | CL46: 4.295 | CM46: 4.063 | CN46: =CJ47-CJ46 -> -0.045 | CR46: 44 | CS46: 1.244 | CT46: =CS47-CS46 -> -0.027
AL47: 42 | AM47: =$AM$4/(1+$H$10)^AL47 -> 0.8470924 | AN47: =AM47/$AM$66 -> 0.0087701257 | AO47: =AN47*AL47 -> 0.36834528 | AV47: 45 | AW47: 0.227 | AX47: =AW48-AW47 -> 0.004 | BB47: 45 | BC47: 0.297 | BD47: =BC48-BC47 -> 0.005 | BH47: 45 | BI47: 0.386 | BJ47: =BI48-BI47 -> 0.025 | BN47: 45 | BO47: 0.519 | BP47: =BO48-BO47 -> 0.085 | BT47: 45 | BU47: 0.599 | BV47: =BU48-BU47 -> 0.13 | CA47: 45 | CB47: 1.363 | CC47: 3.94 | CD47: 4.01 | CE47: 3.829 | CF47: =CB48-CB47 -> -0.038 | CI47: 45 | CJ47: 2.234 | CK47: 4.102 | CL47: 4.13 | CM47: 4.018 | CN47: =CJ48-CJ47 -> -0.014 | CR47: 45 | CS47: 1.217 | CT47: =CS48-CS47 -> 0.136
